Workbook

Sheet Notes
A1: El Cerrito financial statements from audited reports, FY2014-FY2025 (+ unaudited FY2025-26)
A3: HOW TO READ | B3: Blue tabs (GF_) = General Fund only - the City's main operating fund, modified-accrual basis. Green tabs (CW_) = citywide governmental activities, full-accrual basis, including buildings/equipment, long-term debt and pension liabilities. GF_to_Citywide_Bridge walks from one to the other. The GF_ tabs do not depend on the CW_ tabs.
A4: FY2025-26 UNAUDITED | B4: FY2026 columns and blocks (orange, marked UNAUDITED / 2026*) come from the City's FY2025-26 Fourth Quarter General Fund Budget Update (Agenda Bill 8.A, 9/15/2026), not an audited ACFR. They use the City's budget-report classifications, which differ from the ACFR (e.g. ~$1M of cost reimbursements appear as 'Other Financing Sources' rather than charges for services). The original expenditure budget is only available as a total. No FY2026 balance sheet, cash flow or citywide statements exist yet; the ACFR is expected December 2026.
A5: Standards | B5: See Standards_Alignment for how each tab maps to GASB 34, 54, 100, 103, 41, 44, 9, 68/75, 87/96 and GFOA practice, and where it deviates. Stat_Trends reproduces the ACFR statistical-section (GASB 44) schedules and cross-checks them against the City's own FY2025 tables. Template pages: ../templates/ElCerrito_FY2025_ACFR_reference_pages.pdf.
A6: Sources | B6: Audited CAFRs (FY2014-FY2020) and ACFRs (FY2021-FY2025) from elcerrito.gov/Archive.aspx?AMID=76 (PDFs in ../acfr/); FY2026 from ../council-packets/. Page references are in cell comments on year headers.
A7: GF_Operating_Statement | B7: Revenues, expenditures, transfers and change in General Fund fund balance (the government 'P&L').
A8: GF_Balance_Sheet | B8: General Fund assets, liabilities, deferred inflows and fund balance at June 30.
A9: GF_Cash_Flow_Derived | B9: NOT audited - reconstructed indirect-method cash flow (governmental funds have no cash-flow statement under GASB).
A10: GF_Budget_Variance / GF_Variance_Trend | B10: Original vs. final vs. actual by category and year; trend sheet gives cumulative totals with and without FY2026.
A11: GF_to_Citywide_Bridge | B11: General Fund fund balance -> all governmental funds -> plus capital assets, less debt and pension -> citywide net position.
A12: CW_Net_Position | B12: Government-wide Statement of Net Position, governmental activities column (excludes the waste-management enterprise fund), with the due-within-one-year split.
A13: CW_Statement_of_Activities | B13: Expenses by function, program and general revenues, change in net position and restatements, FY2014-FY2025.
A14: CW_Pension_OPEB | B14: CalPERS ten-year schedules (proportionate share, contributions, funded ratio), discount-rate sensitivity, OPEB history.
... A25: Color key | B25: Blue text = transcribed input; black = formula; green = formula linking another tab; light-green rows = tie-out checks (should be 0); orange = unaudited.

Sheet Standards_Alignment
A1: Alignment with governmental GAAP (GASB) and GFOA presentation practice
A2: Governmental GAAP in the U.S. is set by GASB, not FASB. Status: Aligned = follows the standard's format; Partial = follows it with a noted limitation; Supplementary = beyond what GASB requires; Not included = outside this workbook's scope.
A4: Standard / guidance | B4: Requirement (summary) | C4: Where in this workbook | D4: Status | E4: Notes / deviations
A5: GASB 34 - fund financial statements | B5: Governmental funds balance sheet: assets, deferred outflows, liabilities, deferred inflows, fund balances; total liabilities, deferred inflows and fund balances equals total assets. | C5: GF_Balance_Sheet | D5: Aligned | E5: General Fund column only (other governmental funds summarized in GF_to_Citywide_Bridge). No deferred outflows exist in the General Fund.
A6: GASB 34 - statement of revenues, expenditures and changes in fund balances | B6: Revenues by source; expenditures by function (current, capital outlay, debt service principal/interest); excess (deficiency); other financing sources (uses); special items; net change; beginning and ending fund balance. | C6: GF_Operating_Statement | D6: Aligned | E6: Category names standardized across years because the City changed its captions in FY2022 (see GF_Budget_Detail for lines as printed).
A7: GASB 54 - fund balance classification | B7: Nonspendable, restricted, committed, assigned, unassigned. | C7: GF_Balance_Sheet; Stat_Trends Schedule 2 | D7: Aligned | E7: Committed is shown although El Cerrito reports none. The Emergency Disaster Relief reserve is shown as unassigned, as the City reports it.
A8: GASB 100 - accounting changes and error corrections | B8: Display adjustments to beginning balances separately (as previously reported, adjustment, as restated). | C8: GF_Operating_Statement (fund balance section) | D8: Aligned | E8: FY2017, FY2020, FY2023, FY2024 adjustments shown with source comments. GASB 100 applies from FY2024; earlier years are presented the same way for comparability.
A9: GASB 34 / GASB 41 - budgetary comparison (RSI) | B9: General Fund: original budget, final budget, actual on the budgetary basis; variance with final budget encouraged; basis disclosed. | C9: GF_Budget_Variance | D9: Aligned | E9: City budgets on a GAAP basis (ACFR 'Budget and Actual (GAAP Basis)'). FY2026 is on the City's budget-report basis and flagged.
A10: GASB 103 - financial reporting model improvements (FY2026+) | B10: Budgetary comparison as RSI with separate columns for original-to-final and final-to-actual variances; notes explaining significant variances; 'unusual or infrequent items' replaces special/extraordinary items. | C10: GF_Budget_Variance columns E-F and I; GF_Variance_Notes; GF_Operating_Statement | D10: Partial | E10: Both variance columns are present for all years (early application). GF_Variance_Notes explains the major variances FY2019-FY2026 from public sources; smaller flagged lines have no public explanation. 'Special items' caption retained for audited years, with a GASB 103 note.
A11: GASB legal level of budgetary control (GFOA) | B11: Budgetary comparisons at the legal level of control. | C11: GF_Budget_Variance | D11: Aligned | E11: El Cerrito's legal level of budgetary control is the fund level (FY2025 ACFR budgetary note), so the fund totals meet this; category detail is supplementary.
A12: GASB 34 - government-wide statement of net position | B12: Assets, deferred outflows, liabilities, deferred inflows; net position as net investment in capital assets, restricted, unrestricted; long-term liabilities split due within / beyond one year. | C12: CW_Net_Position | D12: Aligned | E12: Liabilities by type with a separate due-within / due-beyond one-year section (bottom of tab). Governmental activities column only.
A13: GASB 34 - statement of activities | B13: Expenses by function, program revenues, general revenues, change in net position. | C13: CW_Statement_of_Activities | D13: Aligned | E13: Expenses, program revenues (charges, operating and capital grants) and net (expense) revenue by function, general revenues, change in net position and restatements, FY2014-FY2025. Grants by function come from each year's basic statement.
A14: GASB 34 - reconciliation of fund balance to net position | B14: Reconcile total governmental fund balances to governmental activities net position. | C14: GF_to_Citywide_Bridge | D14: Aligned | E14: Starts from the General Fund and adds other funds; the bottom section reproduces each year's ACFR reconciliation line by line (capital assets, internal service fund, unavailable revenue, interest, deferrals, debt, leave, claims, OPEB, pension) and ties to net position.
A15: GASB 9 - statement of cash flows | B15: Required for proprietary funds only (operating, noncapital financing, capital and related financing, investing). | C15: GF_Cash_Flow_Derived | D15: Supplementary | E15: Not a GASB requirement for governmental funds; reconstructed using GASB 9 categories and labelled as derived/unaudited.
... A20: Unaudited / preliminary data | B20: Clearly distinguish unaudited figures from audited statements. | C20: FY2026 columns and blocks | D20: Aligned | E20: Orange shading, 'UNAUDITED' labels, separate cumulative totals with and without FY2026.
A22: Templates and references
A23: El Cerrito FY2025 ACFR template pages | B23: ../templates/ElCerrito_FY2025_ACFR_reference_pages.pdf: Statement of Net Position, governmental funds balance sheet, reconciliation, statement of revenues/expenditures, General Fund budgetary comparison, Statistical Tables 1, 3, 4, 10, 13.
A24: GASB 103 summaries | B24: https://weaver.com/resources/are-you-ready-to-implement-the-new-gasb-103-financial-reporting-model-improvements ; https://blog.becpas.com/navigating-gasb-103-key-changes-to-the-financial-reporting-model
A25: GASB 100 summary | B25: https://rsmus.com/insights/financial-reporting/gasb-revises-requirements-for-accounting-changes-and-error-corre.html
A26: GASB 44 statistical section guide | B26: https://www.nj.gov/education/finance/fp/acfr/statguide.pdf
A27: CalPERS valuation reports | B27: https://www.calpers.ca.gov/documents/el-cerrito-city-miscellaneous-2025/download ; https://www.calpers.ca.gov/documents/el-cerrito-city-safety-fire-2025/download (2024 versions at the same address with -2024)
A28: GFOA budget-to-actual guidance | B28: https://gfoa.org/materials/retaining-budget-to-actual-comparisons-within-the-audited

Sheet GF_Operating_Statement
A1: City of El Cerrito - GENERAL FUND ONLY
A2: Statement of Revenues, Expenditures and Changes in Fund Balance (the government 'P&L'), actuals, $
A3: Modified-accrual basis. FY2014-FY2025 audited; FY2026* UNAUDITED (Q4 update, budget-report basis - see Notes). Each figure is a SUMIFS on GF_Budget_Detail. Taxes and Police/Fire are reported combined from FY2022.
N5: UNAUDITED
A6: Fiscal year ended June 30 | B6: 2014 | C6: 2015 | D6: 2016 | E6: 2017 | F6: 2018 | G6: 2019 | H6: 2020 | I6: 2021 | J6: 2022 | K6: 2023 | L6: 2024 | M6: 2025 | N6: 2026
A7: REVENUES
A8: Property taxes | B8: =SUMIFS(GF_Budget_Detail!$G$5:$G$295,GF_Budget_Detail!$A$5:$A$295,B$6,GF_Budget_Detail!$D$5:$D$295,"Property taxes") | C8: =SUMIFS(GF_Budget_Detail!$G$5:$G$295,GF_Budget_Detail!$A$5:$A$295,C$6,GF_Budget_Detail!$D$5:$D$295,"Property taxes") | D8: =SUMIFS(GF_Budget_Detail!$G$5:$G$295,GF_Budget_Detail!$A$5:$A$295,D$6,GF_Budget_Detail!$D$5:$D$295,"Property taxes") | E8: =SUMIFS(GF_Budget_Detail!$G$5:$G$295,GF_Budget_Detail!$A$5:$A$295,E$6,GF_Budget_Detail!$D$5:$D$295,"Property taxes") | F8: =SUMIFS(GF_Budget_Detail!$G$5:$G$295,GF_Budget_Detail!$A$5:$A$295,F$6,GF_Budget_Detail!$D$5:$D$295,"Property taxes") | G8: =SUMIFS(GF_Budget_Detail!$G$5:$G$295,GF_Budget_Detail!$A$5:$A$295,G$6,GF_Budget_Detail!$D$5:$D$295,"Property taxes") | H8: =SUMIFS(GF_Budget_Detail!$G$5:$G$295,GF_Budget_Detail!$A$5:$A$295,H$6,GF_Budget_Detail!$D$5:$D$295,"Property taxes") | I8: =SUMIFS(GF_Budget_Detail!$G$5:$G$295,GF_Budget_Detail!$A$5:$A$295,I$6,GF_Budget_Detail!$D$5:$D$295,"Property taxes") | ... N8: =SUMIFS(GF_Budget_Detail!$G$5:$G$295,GF_Budget_Detail!$A$5:$A$295,N$6,GF_Budget_Detail!$D$5:$D$295,"Property taxes")
A9: Taxes other than property | B9: =SUMIFS(GF_Budget_Detail!$G$5:$G$295,GF_Budget_Detail!$A$5:$A$295,B$6,GF_Budget_Detail!$D$5:$D$295,"Taxes other than property") | C9: =SUMIFS(GF_Budget_Detail!$G$5:$G$295,GF_Budget_Detail!$A$5:$A$295,C$6,GF_Budget_Detail!$D$5:$D$295,"Taxes other than property") | D9: =SUMIFS(GF_Budget_Detail!$G$5:$G$295,GF_Budget_Detail!$A$5:$A$295,D$6,GF_Budget_Detail!$D$5:$D$295,"Taxes other than property") | E9: =SUMIFS(GF_Budget_Detail!$G$5:$G$295,GF_Budget_Detail!$A$5:$A$295,E$6,GF_Budget_Detail!$D$5:$D$295,"Taxes other than property") | F9: =SUMIFS(GF_Budget_Detail!$G$5:$G$295,GF_Budget_Detail!$A$5:$A$295,F$6,GF_Budget_Detail!$D$5:$D$295,"Taxes other than property") | G9: =SUMIFS(GF_Budget_Detail!$G$5:$G$295,GF_Budget_Detail!$A$5:$A$295,G$6,GF_Budget_Detail!$D$5:$D$295,"Taxes other than property") | H9: =SUMIFS(GF_Budget_Detail!$G$5:$G$295,GF_Budget_Detail!$A$5:$A$295,H$6,GF_Budget_Detail!$D$5:$D$295,"Taxes other than property") | I9: =SUMIFS(GF_Budget_Detail!$G$5:$G$295,GF_Budget_Detail!$A$5:$A$295,I$6,GF_Budget_Detail!$D$5:$D$295,"Taxes other than property") | ... N9: =SUMIFS(GF_Budget_Detail!$G$5:$G$295,GF_Budget_Detail!$A$5:$A$295,N$6,GF_Budget_Detail!$D$5:$D$295,"Taxes other than property")
A10: Taxes and assessments (combined) | B10: =SUMIFS(GF_Budget_Detail!$G$5:$G$295,GF_Budget_Detail!$A$5:$A$295,B$6,GF_Budget_Detail!$D$5:$D$295,"Taxes and assessments (combined)") | C10: =SUMIFS(GF_Budget_Detail!$G$5:$G$295,GF_Budget_Detail!$A$5:$A$295,C$6,GF_Budget_Detail!$D$5:$D$295,"Taxes and assessments (combined)") | D10: =SUMIFS(GF_Budget_Detail!$G$5:$G$295,GF_Budget_Detail!$A$5:$A$295,D$6,GF_Budget_Detail!$D$5:$D$295,"Taxes and assessments (combined)") | E10: =SUMIFS(GF_Budget_Detail!$G$5:$G$295,GF_Budget_Detail!$A$5:$A$295,E$6,GF_Budget_Detail!$D$5:$D$295,"Taxes and assessments (combined)") | F10: =SUMIFS(GF_Budget_Detail!$G$5:$G$295,GF_Budget_Detail!$A$5:$A$295,F$6,GF_Budget_Detail!$D$5:$D$295,"Taxes and assessments (combined)") | G10: =SUMIFS(GF_Budget_Detail!$G$5:$G$295,GF_Budget_Detail!$A$5:$A$295,G$6,GF_Budget_Detail!$D$5:$D$295,"Taxes and assessments (combined)") | H10: =SUMIFS(GF_Budget_Detail!$G$5:$G$295,GF_Budget_Detail!$A$5:$A$295,H$6,GF_Budget_Detail!$D$5:$D$295,"Taxes and assessments (combined)") | I10: =SUMIFS(GF_Budget_Detail!$G$5:$G$295,GF_Budget_Detail!$A$5:$A$295,I$6,GF_Budget_Detail!$D$5:$D$295,"Taxes and assessments (combined)") | ... N10: =SUMIFS(GF_Budget_Detail!$G$5:$G$295,GF_Budget_Detail!$A$5:$A$295,N$6,GF_Budget_Detail!$D$5:$D$295,"Taxes and assessments (combined)")
A11: Licenses and permits | B11: =SUMIFS(GF_Budget_Detail!$G$5:$G$295,GF_Budget_Detail!$A$5:$A$295,B$6,GF_Budget_Detail!$D$5:$D$295,"Licenses and permits") | C11: =SUMIFS(GF_Budget_Detail!$G$5:$G$295,GF_Budget_Detail!$A$5:$A$295,C$6,GF_Budget_Detail!$D$5:$D$295,"Licenses and permits") | D11: =SUMIFS(GF_Budget_Detail!$G$5:$G$295,GF_Budget_Detail!$A$5:$A$295,D$6,GF_Budget_Detail!$D$5:$D$295,"Licenses and permits") | E11: =SUMIFS(GF_Budget_Detail!$G$5:$G$295,GF_Budget_Detail!$A$5:$A$295,E$6,GF_Budget_Detail!$D$5:$D$295,"Licenses and permits") | F11: =SUMIFS(GF_Budget_Detail!$G$5:$G$295,GF_Budget_Detail!$A$5:$A$295,F$6,GF_Budget_Detail!$D$5:$D$295,"Licenses and permits") | G11: =SUMIFS(GF_Budget_Detail!$G$5:$G$295,GF_Budget_Detail!$A$5:$A$295,G$6,GF_Budget_Detail!$D$5:$D$295,"Licenses and permits") | H11: =SUMIFS(GF_Budget_Detail!$G$5:$G$295,GF_Budget_Detail!$A$5:$A$295,H$6,GF_Budget_Detail!$D$5:$D$295,"Licenses and permits") | I11: =SUMIFS(GF_Budget_Detail!$G$5:$G$295,GF_Budget_Detail!$A$5:$A$295,I$6,GF_Budget_Detail!$D$5:$D$295,"Licenses and permits") | ... N11: =SUMIFS(GF_Budget_Detail!$G$5:$G$295,GF_Budget_Detail!$A$5:$A$295,N$6,GF_Budget_Detail!$D$5:$D$295,"Licenses and permits")
A12: Fines and forfeitures | B12: =SUMIFS(GF_Budget_Detail!$G$5:$G$295,GF_Budget_Detail!$A$5:$A$295,B$6,GF_Budget_Detail!$D$5:$D$295,"Fines and forfeitures") | C12: =SUMIFS(GF_Budget_Detail!$G$5:$G$295,GF_Budget_Detail!$A$5:$A$295,C$6,GF_Budget_Detail!$D$5:$D$295,"Fines and forfeitures") | D12: =SUMIFS(GF_Budget_Detail!$G$5:$G$295,GF_Budget_Detail!$A$5:$A$295,D$6,GF_Budget_Detail!$D$5:$D$295,"Fines and forfeitures") | E12: =SUMIFS(GF_Budget_Detail!$G$5:$G$295,GF_Budget_Detail!$A$5:$A$295,E$6,GF_Budget_Detail!$D$5:$D$295,"Fines and forfeitures") | F12: =SUMIFS(GF_Budget_Detail!$G$5:$G$295,GF_Budget_Detail!$A$5:$A$295,F$6,GF_Budget_Detail!$D$5:$D$295,"Fines and forfeitures") | G12: =SUMIFS(GF_Budget_Detail!$G$5:$G$295,GF_Budget_Detail!$A$5:$A$295,G$6,GF_Budget_Detail!$D$5:$D$295,"Fines and forfeitures") | H12: =SUMIFS(GF_Budget_Detail!$G$5:$G$295,GF_Budget_Detail!$A$5:$A$295,H$6,GF_Budget_Detail!$D$5:$D$295,"Fines and forfeitures") | I12: =SUMIFS(GF_Budget_Detail!$G$5:$G$295,GF_Budget_Detail!$A$5:$A$295,I$6,GF_Budget_Detail!$D$5:$D$295,"Fines and forfeitures") | ... N12: =SUMIFS(GF_Budget_Detail!$G$5:$G$295,GF_Budget_Detail!$A$5:$A$295,N$6,GF_Budget_Detail!$D$5:$D$295,"Fines and forfeitures")
A13: Use of money and property | B13: =SUMIFS(GF_Budget_Detail!$G$5:$G$295,GF_Budget_Detail!$A$5:$A$295,B$6,GF_Budget_Detail!$D$5:$D$295,"Use of money and property") | C13: =SUMIFS(GF_Budget_Detail!$G$5:$G$295,GF_Budget_Detail!$A$5:$A$295,C$6,GF_Budget_Detail!$D$5:$D$295,"Use of money and property") | D13: =SUMIFS(GF_Budget_Detail!$G$5:$G$295,GF_Budget_Detail!$A$5:$A$295,D$6,GF_Budget_Detail!$D$5:$D$295,"Use of money and property") | E13: =SUMIFS(GF_Budget_Detail!$G$5:$G$295,GF_Budget_Detail!$A$5:$A$295,E$6,GF_Budget_Detail!$D$5:$D$295,"Use of money and property") | F13: =SUMIFS(GF_Budget_Detail!$G$5:$G$295,GF_Budget_Detail!$A$5:$A$295,F$6,GF_Budget_Detail!$D$5:$D$295,"Use of money and property") | G13: =SUMIFS(GF_Budget_Detail!$G$5:$G$295,GF_Budget_Detail!$A$5:$A$295,G$6,GF_Budget_Detail!$D$5:$D$295,"Use of money and property") | H13: =SUMIFS(GF_Budget_Detail!$G$5:$G$295,GF_Budget_Detail!$A$5:$A$295,H$6,GF_Budget_Detail!$D$5:$D$295,"Use of money and property") | I13: =SUMIFS(GF_Budget_Detail!$G$5:$G$295,GF_Budget_Detail!$A$5:$A$295,I$6,GF_Budget_Detail!$D$5:$D$295,"Use of money and property") | ... N13: =SUMIFS(GF_Budget_Detail!$G$5:$G$295,GF_Budget_Detail!$A$5:$A$295,N$6,GF_Budget_Detail!$D$5:$D$295,"Use of money and property")
A14: Intergovernmental | B14: =SUMIFS(GF_Budget_Detail!$G$5:$G$295,GF_Budget_Detail!$A$5:$A$295,B$6,GF_Budget_Detail!$D$5:$D$295,"Intergovernmental") | C14: =SUMIFS(GF_Budget_Detail!$G$5:$G$295,GF_Budget_Detail!$A$5:$A$295,C$6,GF_Budget_Detail!$D$5:$D$295,"Intergovernmental") | D14: =SUMIFS(GF_Budget_Detail!$G$5:$G$295,GF_Budget_Detail!$A$5:$A$295,D$6,GF_Budget_Detail!$D$5:$D$295,"Intergovernmental") | E14: =SUMIFS(GF_Budget_Detail!$G$5:$G$295,GF_Budget_Detail!$A$5:$A$295,E$6,GF_Budget_Detail!$D$5:$D$295,"Intergovernmental") | F14: =SUMIFS(GF_Budget_Detail!$G$5:$G$295,GF_Budget_Detail!$A$5:$A$295,F$6,GF_Budget_Detail!$D$5:$D$295,"Intergovernmental") | G14: =SUMIFS(GF_Budget_Detail!$G$5:$G$295,GF_Budget_Detail!$A$5:$A$295,G$6,GF_Budget_Detail!$D$5:$D$295,"Intergovernmental") | H14: =SUMIFS(GF_Budget_Detail!$G$5:$G$295,GF_Budget_Detail!$A$5:$A$295,H$6,GF_Budget_Detail!$D$5:$D$295,"Intergovernmental") | I14: =SUMIFS(GF_Budget_Detail!$G$5:$G$295,GF_Budget_Detail!$A$5:$A$295,I$6,GF_Budget_Detail!$D$5:$D$295,"Intergovernmental") | ... N14: =SUMIFS(GF_Budget_Detail!$G$5:$G$295,GF_Budget_Detail!$A$5:$A$295,N$6,GF_Budget_Detail!$D$5:$D$295,"Intergovernmental")
A15: Charges for services | B15: =SUMIFS(GF_Budget_Detail!$G$5:$G$295,GF_Budget_Detail!$A$5:$A$295,B$6,GF_Budget_Detail!$D$5:$D$295,"Charges for services") | C15: =SUMIFS(GF_Budget_Detail!$G$5:$G$295,GF_Budget_Detail!$A$5:$A$295,C$6,GF_Budget_Detail!$D$5:$D$295,"Charges for services") | D15: =SUMIFS(GF_Budget_Detail!$G$5:$G$295,GF_Budget_Detail!$A$5:$A$295,D$6,GF_Budget_Detail!$D$5:$D$295,"Charges for services") | E15: =SUMIFS(GF_Budget_Detail!$G$5:$G$295,GF_Budget_Detail!$A$5:$A$295,E$6,GF_Budget_Detail!$D$5:$D$295,"Charges for services") | F15: =SUMIFS(GF_Budget_Detail!$G$5:$G$295,GF_Budget_Detail!$A$5:$A$295,F$6,GF_Budget_Detail!$D$5:$D$295,"Charges for services") | G15: =SUMIFS(GF_Budget_Detail!$G$5:$G$295,GF_Budget_Detail!$A$5:$A$295,G$6,GF_Budget_Detail!$D$5:$D$295,"Charges for services") | H15: =SUMIFS(GF_Budget_Detail!$G$5:$G$295,GF_Budget_Detail!$A$5:$A$295,H$6,GF_Budget_Detail!$D$5:$D$295,"Charges for services") | I15: =SUMIFS(GF_Budget_Detail!$G$5:$G$295,GF_Budget_Detail!$A$5:$A$295,I$6,GF_Budget_Detail!$D$5:$D$295,"Charges for services") | ... N15: =SUMIFS(GF_Budget_Detail!$G$5:$G$295,GF_Budget_Detail!$A$5:$A$295,N$6,GF_Budget_Detail!$D$5:$D$295,"Charges for services")
A16: Other revenues | B16: =SUMIFS(GF_Budget_Detail!$G$5:$G$295,GF_Budget_Detail!$A$5:$A$295,B$6,GF_Budget_Detail!$D$5:$D$295,"Other revenues") | C16: =SUMIFS(GF_Budget_Detail!$G$5:$G$295,GF_Budget_Detail!$A$5:$A$295,C$6,GF_Budget_Detail!$D$5:$D$295,"Other revenues") | D16: =SUMIFS(GF_Budget_Detail!$G$5:$G$295,GF_Budget_Detail!$A$5:$A$295,D$6,GF_Budget_Detail!$D$5:$D$295,"Other revenues") | E16: =SUMIFS(GF_Budget_Detail!$G$5:$G$295,GF_Budget_Detail!$A$5:$A$295,E$6,GF_Budget_Detail!$D$5:$D$295,"Other revenues") | F16: =SUMIFS(GF_Budget_Detail!$G$5:$G$295,GF_Budget_Detail!$A$5:$A$295,F$6,GF_Budget_Detail!$D$5:$D$295,"Other revenues") | G16: =SUMIFS(GF_Budget_Detail!$G$5:$G$295,GF_Budget_Detail!$A$5:$A$295,G$6,GF_Budget_Detail!$D$5:$D$295,"Other revenues") | H16: =SUMIFS(GF_Budget_Detail!$G$5:$G$295,GF_Budget_Detail!$A$5:$A$295,H$6,GF_Budget_Detail!$D$5:$D$295,"Other revenues") | I16: =SUMIFS(GF_Budget_Detail!$G$5:$G$295,GF_Budget_Detail!$A$5:$A$295,I$6,GF_Budget_Detail!$D$5:$D$295,"Other revenues") | ... N16: =SUMIFS(GF_Budget_Detail!$G$5:$G$295,GF_Budget_Detail!$A$5:$A$295,N$6,GF_Budget_Detail!$D$5:$D$295,"Other revenues")
A17: Total revenues | B17: =SUM(B8:B16) | C17: =SUM(C8:C16) | D17: =SUM(D8:D16) | E17: =SUM(E8:E16) | F17: =SUM(F8:F16) | G17: =SUM(G8:G16) | H17: =SUM(H8:H16) | I17: =SUM(I8:I16) | ... N17: =SUM(N8:N16)
A19: EXPENDITURES
A20: Current:
A21: General government | B21: =SUMIFS(GF_Budget_Detail!$G$5:$G$295,GF_Budget_Detail!$A$5:$A$295,B$6,GF_Budget_Detail!$D$5:$D$295,"General government") | C21: =SUMIFS(GF_Budget_Detail!$G$5:$G$295,GF_Budget_Detail!$A$5:$A$295,C$6,GF_Budget_Detail!$D$5:$D$295,"General government") | D21: =SUMIFS(GF_Budget_Detail!$G$5:$G$295,GF_Budget_Detail!$A$5:$A$295,D$6,GF_Budget_Detail!$D$5:$D$295,"General government") | E21: =SUMIFS(GF_Budget_Detail!$G$5:$G$295,GF_Budget_Detail!$A$5:$A$295,E$6,GF_Budget_Detail!$D$5:$D$295,"General government") | F21: =SUMIFS(GF_Budget_Detail!$G$5:$G$295,GF_Budget_Detail!$A$5:$A$295,F$6,GF_Budget_Detail!$D$5:$D$295,"General government") | G21: =SUMIFS(GF_Budget_Detail!$G$5:$G$295,GF_Budget_Detail!$A$5:$A$295,G$6,GF_Budget_Detail!$D$5:$D$295,"General government") | H21: =SUMIFS(GF_Budget_Detail!$G$5:$G$295,GF_Budget_Detail!$A$5:$A$295,H$6,GF_Budget_Detail!$D$5:$D$295,"General government") | I21: =SUMIFS(GF_Budget_Detail!$G$5:$G$295,GF_Budget_Detail!$A$5:$A$295,I$6,GF_Budget_Detail!$D$5:$D$295,"General government") | ... N21: =SUMIFS(GF_Budget_Detail!$G$5:$G$295,GF_Budget_Detail!$A$5:$A$295,N$6,GF_Budget_Detail!$D$5:$D$295,"General government")
A22: Public works | B22: =SUMIFS(GF_Budget_Detail!$G$5:$G$295,GF_Budget_Detail!$A$5:$A$295,B$6,GF_Budget_Detail!$D$5:$D$295,"Public works") | C22: =SUMIFS(GF_Budget_Detail!$G$5:$G$295,GF_Budget_Detail!$A$5:$A$295,C$6,GF_Budget_Detail!$D$5:$D$295,"Public works") | D22: =SUMIFS(GF_Budget_Detail!$G$5:$G$295,GF_Budget_Detail!$A$5:$A$295,D$6,GF_Budget_Detail!$D$5:$D$295,"Public works") | E22: =SUMIFS(GF_Budget_Detail!$G$5:$G$295,GF_Budget_Detail!$A$5:$A$295,E$6,GF_Budget_Detail!$D$5:$D$295,"Public works") | F22: =SUMIFS(GF_Budget_Detail!$G$5:$G$295,GF_Budget_Detail!$A$5:$A$295,F$6,GF_Budget_Detail!$D$5:$D$295,"Public works") | G22: =SUMIFS(GF_Budget_Detail!$G$5:$G$295,GF_Budget_Detail!$A$5:$A$295,G$6,GF_Budget_Detail!$D$5:$D$295,"Public works") | H22: =SUMIFS(GF_Budget_Detail!$G$5:$G$295,GF_Budget_Detail!$A$5:$A$295,H$6,GF_Budget_Detail!$D$5:$D$295,"Public works") | I22: =SUMIFS(GF_Budget_Detail!$G$5:$G$295,GF_Budget_Detail!$A$5:$A$295,I$6,GF_Budget_Detail!$D$5:$D$295,"Public works") | ... N22: =SUMIFS(GF_Budget_Detail!$G$5:$G$295,GF_Budget_Detail!$A$5:$A$295,N$6,GF_Budget_Detail!$D$5:$D$295,"Public works")
A23: Recreation | B23: =SUMIFS(GF_Budget_Detail!$G$5:$G$295,GF_Budget_Detail!$A$5:$A$295,B$6,GF_Budget_Detail!$D$5:$D$295,"Recreation") | C23: =SUMIFS(GF_Budget_Detail!$G$5:$G$295,GF_Budget_Detail!$A$5:$A$295,C$6,GF_Budget_Detail!$D$5:$D$295,"Recreation") | D23: =SUMIFS(GF_Budget_Detail!$G$5:$G$295,GF_Budget_Detail!$A$5:$A$295,D$6,GF_Budget_Detail!$D$5:$D$295,"Recreation") | E23: =SUMIFS(GF_Budget_Detail!$G$5:$G$295,GF_Budget_Detail!$A$5:$A$295,E$6,GF_Budget_Detail!$D$5:$D$295,"Recreation") | F23: =SUMIFS(GF_Budget_Detail!$G$5:$G$295,GF_Budget_Detail!$A$5:$A$295,F$6,GF_Budget_Detail!$D$5:$D$295,"Recreation") | G23: =SUMIFS(GF_Budget_Detail!$G$5:$G$295,GF_Budget_Detail!$A$5:$A$295,G$6,GF_Budget_Detail!$D$5:$D$295,"Recreation") | H23: =SUMIFS(GF_Budget_Detail!$G$5:$G$295,GF_Budget_Detail!$A$5:$A$295,H$6,GF_Budget_Detail!$D$5:$D$295,"Recreation") | I23: =SUMIFS(GF_Budget_Detail!$G$5:$G$295,GF_Budget_Detail!$A$5:$A$295,I$6,GF_Budget_Detail!$D$5:$D$295,"Recreation") | ... N23: =SUMIFS(GF_Budget_Detail!$G$5:$G$295,GF_Budget_Detail!$A$5:$A$295,N$6,GF_Budget_Detail!$D$5:$D$295,"Recreation")
A24: Community development | B24: =SUMIFS(GF_Budget_Detail!$G$5:$G$295,GF_Budget_Detail!$A$5:$A$295,B$6,GF_Budget_Detail!$D$5:$D$295,"Community development") | C24: =SUMIFS(GF_Budget_Detail!$G$5:$G$295,GF_Budget_Detail!$A$5:$A$295,C$6,GF_Budget_Detail!$D$5:$D$295,"Community development") | D24: =SUMIFS(GF_Budget_Detail!$G$5:$G$295,GF_Budget_Detail!$A$5:$A$295,D$6,GF_Budget_Detail!$D$5:$D$295,"Community development") | E24: =SUMIFS(GF_Budget_Detail!$G$5:$G$295,GF_Budget_Detail!$A$5:$A$295,E$6,GF_Budget_Detail!$D$5:$D$295,"Community development") | F24: =SUMIFS(GF_Budget_Detail!$G$5:$G$295,GF_Budget_Detail!$A$5:$A$295,F$6,GF_Budget_Detail!$D$5:$D$295,"Community development") | G24: =SUMIFS(GF_Budget_Detail!$G$5:$G$295,GF_Budget_Detail!$A$5:$A$295,G$6,GF_Budget_Detail!$D$5:$D$295,"Community development") | H24: =SUMIFS(GF_Budget_Detail!$G$5:$G$295,GF_Budget_Detail!$A$5:$A$295,H$6,GF_Budget_Detail!$D$5:$D$295,"Community development") | I24: =SUMIFS(GF_Budget_Detail!$G$5:$G$295,GF_Budget_Detail!$A$5:$A$295,I$6,GF_Budget_Detail!$D$5:$D$295,"Community development") | ... N24: =SUMIFS(GF_Budget_Detail!$G$5:$G$295,GF_Budget_Detail!$A$5:$A$295,N$6,GF_Budget_Detail!$D$5:$D$295,"Community development")
A25: Public safety - Police | B25: =SUMIFS(GF_Budget_Detail!$G$5:$G$295,GF_Budget_Detail!$A$5:$A$295,B$6,GF_Budget_Detail!$D$5:$D$295,"Public safety - Police") | C25: =SUMIFS(GF_Budget_Detail!$G$5:$G$295,GF_Budget_Detail!$A$5:$A$295,C$6,GF_Budget_Detail!$D$5:$D$295,"Public safety - Police") | D25: =SUMIFS(GF_Budget_Detail!$G$5:$G$295,GF_Budget_Detail!$A$5:$A$295,D$6,GF_Budget_Detail!$D$5:$D$295,"Public safety - Police") | E25: =SUMIFS(GF_Budget_Detail!$G$5:$G$295,GF_Budget_Detail!$A$5:$A$295,E$6,GF_Budget_Detail!$D$5:$D$295,"Public safety - Police") | F25: =SUMIFS(GF_Budget_Detail!$G$5:$G$295,GF_Budget_Detail!$A$5:$A$295,F$6,GF_Budget_Detail!$D$5:$D$295,"Public safety - Police") | G25: =SUMIFS(GF_Budget_Detail!$G$5:$G$295,GF_Budget_Detail!$A$5:$A$295,G$6,GF_Budget_Detail!$D$5:$D$295,"Public safety - Police") | H25: =SUMIFS(GF_Budget_Detail!$G$5:$G$295,GF_Budget_Detail!$A$5:$A$295,H$6,GF_Budget_Detail!$D$5:$D$295,"Public safety - Police") | I25: =SUMIFS(GF_Budget_Detail!$G$5:$G$295,GF_Budget_Detail!$A$5:$A$295,I$6,GF_Budget_Detail!$D$5:$D$295,"Public safety - Police") | ... N25: =SUMIFS(GF_Budget_Detail!$G$5:$G$295,GF_Budget_Detail!$A$5:$A$295,N$6,GF_Budget_Detail!$D$5:$D$295,"Public safety - Police")
A26: Public safety - Fire | B26: =SUMIFS(GF_Budget_Detail!$G$5:$G$295,GF_Budget_Detail!$A$5:$A$295,B$6,GF_Budget_Detail!$D$5:$D$295,"Public safety - Fire") | C26: =SUMIFS(GF_Budget_Detail!$G$5:$G$295,GF_Budget_Detail!$A$5:$A$295,C$6,GF_Budget_Detail!$D$5:$D$295,"Public safety - Fire") | D26: =SUMIFS(GF_Budget_Detail!$G$5:$G$295,GF_Budget_Detail!$A$5:$A$295,D$6,GF_Budget_Detail!$D$5:$D$295,"Public safety - Fire") | E26: =SUMIFS(GF_Budget_Detail!$G$5:$G$295,GF_Budget_Detail!$A$5:$A$295,E$6,GF_Budget_Detail!$D$5:$D$295,"Public safety - Fire") | F26: =SUMIFS(GF_Budget_Detail!$G$5:$G$295,GF_Budget_Detail!$A$5:$A$295,F$6,GF_Budget_Detail!$D$5:$D$295,"Public safety - Fire") | G26: =SUMIFS(GF_Budget_Detail!$G$5:$G$295,GF_Budget_Detail!$A$5:$A$295,G$6,GF_Budget_Detail!$D$5:$D$295,"Public safety - Fire") | H26: =SUMIFS(GF_Budget_Detail!$G$5:$G$295,GF_Budget_Detail!$A$5:$A$295,H$6,GF_Budget_Detail!$D$5:$D$295,"Public safety - Fire") | I26: =SUMIFS(GF_Budget_Detail!$G$5:$G$295,GF_Budget_Detail!$A$5:$A$295,I$6,GF_Budget_Detail!$D$5:$D$295,"Public safety - Fire") | ... N26: =SUMIFS(GF_Budget_Detail!$G$5:$G$295,GF_Budget_Detail!$A$5:$A$295,N$6,GF_Budget_Detail!$D$5:$D$295,"Public safety - Fire")
A27: Public safety (combined) | B27: =SUMIFS(GF_Budget_Detail!$G$5:$G$295,GF_Budget_Detail!$A$5:$A$295,B$6,GF_Budget_Detail!$D$5:$D$295,"Public safety (combined)") | C27: =SUMIFS(GF_Budget_Detail!$G$5:$G$295,GF_Budget_Detail!$A$5:$A$295,C$6,GF_Budget_Detail!$D$5:$D$295,"Public safety (combined)") | D27: =SUMIFS(GF_Budget_Detail!$G$5:$G$295,GF_Budget_Detail!$A$5:$A$295,D$6,GF_Budget_Detail!$D$5:$D$295,"Public safety (combined)") | E27: =SUMIFS(GF_Budget_Detail!$G$5:$G$295,GF_Budget_Detail!$A$5:$A$295,E$6,GF_Budget_Detail!$D$5:$D$295,"Public safety (combined)") | F27: =SUMIFS(GF_Budget_Detail!$G$5:$G$295,GF_Budget_Detail!$A$5:$A$295,F$6,GF_Budget_Detail!$D$5:$D$295,"Public safety (combined)") | G27: =SUMIFS(GF_Budget_Detail!$G$5:$G$295,GF_Budget_Detail!$A$5:$A$295,G$6,GF_Budget_Detail!$D$5:$D$295,"Public safety (combined)") | H27: =SUMIFS(GF_Budget_Detail!$G$5:$G$295,GF_Budget_Detail!$A$5:$A$295,H$6,GF_Budget_Detail!$D$5:$D$295,"Public safety (combined)") | I27: =SUMIFS(GF_Budget_Detail!$G$5:$G$295,GF_Budget_Detail!$A$5:$A$295,I$6,GF_Budget_Detail!$D$5:$D$295,"Public safety (combined)") | ... N27: =SUMIFS(GF_Budget_Detail!$G$5:$G$295,GF_Budget_Detail!$A$5:$A$295,N$6,GF_Budget_Detail!$D$5:$D$295,"Public safety (combined)")
A28: Payment of sales tax to City of Richmond | B28: =SUMIFS(GF_Budget_Detail!$G$5:$G$295,GF_Budget_Detail!$A$5:$A$295,B$6,GF_Budget_Detail!$D$5:$D$295,"Payment of sales tax to City of Richmond") | C28: =SUMIFS(GF_Budget_Detail!$G$5:$G$295,GF_Budget_Detail!$A$5:$A$295,C$6,GF_Budget_Detail!$D$5:$D$295,"Payment of sales tax to City of Richmond") | D28: =SUMIFS(GF_Budget_Detail!$G$5:$G$295,GF_Budget_Detail!$A$5:$A$295,D$6,GF_Budget_Detail!$D$5:$D$295,"Payment of sales tax to City of Richmond") | E28: =SUMIFS(GF_Budget_Detail!$G$5:$G$295,GF_Budget_Detail!$A$5:$A$295,E$6,GF_Budget_Detail!$D$5:$D$295,"Payment of sales tax to City of Richmond") | F28: =SUMIFS(GF_Budget_Detail!$G$5:$G$295,GF_Budget_Detail!$A$5:$A$295,F$6,GF_Budget_Detail!$D$5:$D$295,"Payment of sales tax to City of Richmond") | G28: =SUMIFS(GF_Budget_Detail!$G$5:$G$295,GF_Budget_Detail!$A$5:$A$295,G$6,GF_Budget_Detail!$D$5:$D$295,"Payment of sales tax to City of Richmond") | H28: =SUMIFS(GF_Budget_Detail!$G$5:$G$295,GF_Budget_Detail!$A$5:$A$295,H$6,GF_Budget_Detail!$D$5:$D$295,"Payment of sales tax to City of Richmond") | I28: =SUMIFS(GF_Budget_Detail!$G$5:$G$295,GF_Budget_Detail!$A$5:$A$295,I$6,GF_Budget_Detail!$D$5:$D$295,"Payment of sales tax to City of Richmond") | ... N28: =SUMIFS(GF_Budget_Detail!$G$5:$G$295,GF_Budget_Detail!$A$5:$A$295,N$6,GF_Budget_Detail!$D$5:$D$295,"Payment of sales tax to City of Richmond")
A29: Non-departmental (budget-report basis) | B29: =SUMIFS(GF_Budget_Detail!$G$5:$G$295,GF_Budget_Detail!$A$5:$A$295,B$6,GF_Budget_Detail!$D$5:$D$295,"Non-departmental (budget-report basis)") | C29: =SUMIFS(GF_Budget_Detail!$G$5:$G$295,GF_Budget_Detail!$A$5:$A$295,C$6,GF_Budget_Detail!$D$5:$D$295,"Non-departmental (budget-report basis)") | D29: =SUMIFS(GF_Budget_Detail!$G$5:$G$295,GF_Budget_Detail!$A$5:$A$295,D$6,GF_Budget_Detail!$D$5:$D$295,"Non-departmental (budget-report basis)") | E29: =SUMIFS(GF_Budget_Detail!$G$5:$G$295,GF_Budget_Detail!$A$5:$A$295,E$6,GF_Budget_Detail!$D$5:$D$295,"Non-departmental (budget-report basis)") | F29: =SUMIFS(GF_Budget_Detail!$G$5:$G$295,GF_Budget_Detail!$A$5:$A$295,F$6,GF_Budget_Detail!$D$5:$D$295,"Non-departmental (budget-report basis)") | G29: =SUMIFS(GF_Budget_Detail!$G$5:$G$295,GF_Budget_Detail!$A$5:$A$295,G$6,GF_Budget_Detail!$D$5:$D$295,"Non-departmental (budget-report basis)") | H29: =SUMIFS(GF_Budget_Detail!$G$5:$G$295,GF_Budget_Detail!$A$5:$A$295,H$6,GF_Budget_Detail!$D$5:$D$295,"Non-departmental (budget-report basis)") | I29: =SUMIFS(GF_Budget_Detail!$G$5:$G$295,GF_Budget_Detail!$A$5:$A$295,I$6,GF_Budget_Detail!$D$5:$D$295,"Non-departmental (budget-report basis)") | ... N29: =SUMIFS(GF_Budget_Detail!$G$5:$G$295,GF_Budget_Detail!$A$5:$A$295,N$6,GF_Budget_Detail!$D$5:$D$295,"Non-departmental (budget-report basis)")
A30: Capital outlay | B30: =SUMIFS(GF_Budget_Detail!$G$5:$G$295,GF_Budget_Detail!$A$5:$A$295,B$6,GF_Budget_Detail!$D$5:$D$295,"Capital outlay") | C30: =SUMIFS(GF_Budget_Detail!$G$5:$G$295,GF_Budget_Detail!$A$5:$A$295,C$6,GF_Budget_Detail!$D$5:$D$295,"Capital outlay") | D30: =SUMIFS(GF_Budget_Detail!$G$5:$G$295,GF_Budget_Detail!$A$5:$A$295,D$6,GF_Budget_Detail!$D$5:$D$295,"Capital outlay") | E30: =SUMIFS(GF_Budget_Detail!$G$5:$G$295,GF_Budget_Detail!$A$5:$A$295,E$6,GF_Budget_Detail!$D$5:$D$295,"Capital outlay") | F30: =SUMIFS(GF_Budget_Detail!$G$5:$G$295,GF_Budget_Detail!$A$5:$A$295,F$6,GF_Budget_Detail!$D$5:$D$295,"Capital outlay") | G30: =SUMIFS(GF_Budget_Detail!$G$5:$G$295,GF_Budget_Detail!$A$5:$A$295,G$6,GF_Budget_Detail!$D$5:$D$295,"Capital outlay") | H30: =SUMIFS(GF_Budget_Detail!$G$5:$G$295,GF_Budget_Detail!$A$5:$A$295,H$6,GF_Budget_Detail!$D$5:$D$295,"Capital outlay") | I30: =SUMIFS(GF_Budget_Detail!$G$5:$G$295,GF_Budget_Detail!$A$5:$A$295,I$6,GF_Budget_Detail!$D$5:$D$295,"Capital outlay") | ... N30: =SUMIFS(GF_Budget_Detail!$G$5:$G$295,GF_Budget_Detail!$A$5:$A$295,N$6,GF_Budget_Detail!$D$5:$D$295,"Capital outlay")
A31: Debt service:
A32: Principal | B32: =SUMIFS(GF_Budget_Detail!$G$5:$G$295,GF_Budget_Detail!$A$5:$A$295,B$6,GF_Budget_Detail!$D$5:$D$295,"Debt service - principal") | C32: =SUMIFS(GF_Budget_Detail!$G$5:$G$295,GF_Budget_Detail!$A$5:$A$295,C$6,GF_Budget_Detail!$D$5:$D$295,"Debt service - principal") | D32: =SUMIFS(GF_Budget_Detail!$G$5:$G$295,GF_Budget_Detail!$A$5:$A$295,D$6,GF_Budget_Detail!$D$5:$D$295,"Debt service - principal") | E32: =SUMIFS(GF_Budget_Detail!$G$5:$G$295,GF_Budget_Detail!$A$5:$A$295,E$6,GF_Budget_Detail!$D$5:$D$295,"Debt service - principal") | F32: =SUMIFS(GF_Budget_Detail!$G$5:$G$295,GF_Budget_Detail!$A$5:$A$295,F$6,GF_Budget_Detail!$D$5:$D$295,"Debt service - principal") | G32: =SUMIFS(GF_Budget_Detail!$G$5:$G$295,GF_Budget_Detail!$A$5:$A$295,G$6,GF_Budget_Detail!$D$5:$D$295,"Debt service - principal") | H32: =SUMIFS(GF_Budget_Detail!$G$5:$G$295,GF_Budget_Detail!$A$5:$A$295,H$6,GF_Budget_Detail!$D$5:$D$295,"Debt service - principal") | I32: =SUMIFS(GF_Budget_Detail!$G$5:$G$295,GF_Budget_Detail!$A$5:$A$295,I$6,GF_Budget_Detail!$D$5:$D$295,"Debt service - principal") | ... N32: =SUMIFS(GF_Budget_Detail!$G$5:$G$295,GF_Budget_Detail!$A$5:$A$295,N$6,GF_Budget_Detail!$D$5:$D$295,"Debt service - principal")
A33: Interest and fiscal charges | B33: =SUMIFS(GF_Budget_Detail!$G$5:$G$295,GF_Budget_Detail!$A$5:$A$295,B$6,GF_Budget_Detail!$D$5:$D$295,"Debt service - interest") | C33: =SUMIFS(GF_Budget_Detail!$G$5:$G$295,GF_Budget_Detail!$A$5:$A$295,C$6,GF_Budget_Detail!$D$5:$D$295,"Debt service - interest") | D33: =SUMIFS(GF_Budget_Detail!$G$5:$G$295,GF_Budget_Detail!$A$5:$A$295,D$6,GF_Budget_Detail!$D$5:$D$295,"Debt service - interest") | E33: =SUMIFS(GF_Budget_Detail!$G$5:$G$295,GF_Budget_Detail!$A$5:$A$295,E$6,GF_Budget_Detail!$D$5:$D$295,"Debt service - interest") | F33: =SUMIFS(GF_Budget_Detail!$G$5:$G$295,GF_Budget_Detail!$A$5:$A$295,F$6,GF_Budget_Detail!$D$5:$D$295,"Debt service - interest") | G33: =SUMIFS(GF_Budget_Detail!$G$5:$G$295,GF_Budget_Detail!$A$5:$A$295,G$6,GF_Budget_Detail!$D$5:$D$295,"Debt service - interest") | H33: =SUMIFS(GF_Budget_Detail!$G$5:$G$295,GF_Budget_Detail!$A$5:$A$295,H$6,GF_Budget_Detail!$D$5:$D$295,"Debt service - interest") | I33: =SUMIFS(GF_Budget_Detail!$G$5:$G$295,GF_Budget_Detail!$A$5:$A$295,I$6,GF_Budget_Detail!$D$5:$D$295,"Debt service - interest") | ... N33: =SUMIFS(GF_Budget_Detail!$G$5:$G$295,GF_Budget_Detail!$A$5:$A$295,N$6,GF_Budget_Detail!$D$5:$D$295,"Debt service - interest")
A34: Total expenditures | B34: =SUM(B20:B33) | C34: =SUM(C20:C33) | D34: =SUM(D20:D33) | E34: =SUM(E20:E33) | F34: =SUM(F20:F33) | G34: =SUM(G20:G33) | H34: =SUM(H20:H33) | I34: =SUM(I20:I33) | ... N34: =SUM(N20:N33)
A36: Excess (deficiency) of revenues over (under) expenditures | B36: =B17-B34 | C36: =C17-C34 | D36: =D17-D34 | E36: =E17-E34 | F36: =F17-F34 | G36: =G17-G34 | H36: =H17-H34 | I36: =I17-I34 | ... N36: =N17-N34
A38: OTHER FINANCING SOURCES (USES)
A39: Transfers in | B39: =SUMIFS(GF_Budget_Detail!$G$5:$G$295,GF_Budget_Detail!$A$5:$A$295,B$6,GF_Budget_Detail!$D$5:$D$295,"Transfers in") | C39: =SUMIFS(GF_Budget_Detail!$G$5:$G$295,GF_Budget_Detail!$A$5:$A$295,C$6,GF_Budget_Detail!$D$5:$D$295,"Transfers in") | D39: =SUMIFS(GF_Budget_Detail!$G$5:$G$295,GF_Budget_Detail!$A$5:$A$295,D$6,GF_Budget_Detail!$D$5:$D$295,"Transfers in") | E39: =SUMIFS(GF_Budget_Detail!$G$5:$G$295,GF_Budget_Detail!$A$5:$A$295,E$6,GF_Budget_Detail!$D$5:$D$295,"Transfers in") | F39: =SUMIFS(GF_Budget_Detail!$G$5:$G$295,GF_Budget_Detail!$A$5:$A$295,F$6,GF_Budget_Detail!$D$5:$D$295,"Transfers in") | G39: =SUMIFS(GF_Budget_Detail!$G$5:$G$295,GF_Budget_Detail!$A$5:$A$295,G$6,GF_Budget_Detail!$D$5:$D$295,"Transfers in") | H39: =SUMIFS(GF_Budget_Detail!$G$5:$G$295,GF_Budget_Detail!$A$5:$A$295,H$6,GF_Budget_Detail!$D$5:$D$295,"Transfers in") | I39: =SUMIFS(GF_Budget_Detail!$G$5:$G$295,GF_Budget_Detail!$A$5:$A$295,I$6,GF_Budget_Detail!$D$5:$D$295,"Transfers in") | ... N39: =SUMIFS(GF_Budget_Detail!$G$5:$G$295,GF_Budget_Detail!$A$5:$A$295,N$6,GF_Budget_Detail!$D$5:$D$295,"Transfers in")
A40: Transfers out | B40: =SUMIFS(GF_Budget_Detail!$G$5:$G$295,GF_Budget_Detail!$A$5:$A$295,B$6,GF_Budget_Detail!$D$5:$D$295,"Transfers out") | C40: =SUMIFS(GF_Budget_Detail!$G$5:$G$295,GF_Budget_Detail!$A$5:$A$295,C$6,GF_Budget_Detail!$D$5:$D$295,"Transfers out") | D40: =SUMIFS(GF_Budget_Detail!$G$5:$G$295,GF_Budget_Detail!$A$5:$A$295,D$6,GF_Budget_Detail!$D$5:$D$295,"Transfers out") | E40: =SUMIFS(GF_Budget_Detail!$G$5:$G$295,GF_Budget_Detail!$A$5:$A$295,E$6,GF_Budget_Detail!$D$5:$D$295,"Transfers out") | F40: =SUMIFS(GF_Budget_Detail!$G$5:$G$295,GF_Budget_Detail!$A$5:$A$295,F$6,GF_Budget_Detail!$D$5:$D$295,"Transfers out") | G40: =SUMIFS(GF_Budget_Detail!$G$5:$G$295,GF_Budget_Detail!$A$5:$A$295,G$6,GF_Budget_Detail!$D$5:$D$295,"Transfers out") | H40: =SUMIFS(GF_Budget_Detail!$G$5:$G$295,GF_Budget_Detail!$A$5:$A$295,H$6,GF_Budget_Detail!$D$5:$D$295,"Transfers out") | I40: =SUMIFS(GF_Budget_Detail!$G$5:$G$295,GF_Budget_Detail!$A$5:$A$295,I$6,GF_Budget_Detail!$D$5:$D$295,"Transfers out") | ... N40: =SUMIFS(GF_Budget_Detail!$G$5:$G$295,GF_Budget_Detail!$A$5:$A$295,N$6,GF_Budget_Detail!$D$5:$D$295,"Transfers out")
A41: Debt issuance / lease financing | B41: =SUMIFS(GF_Budget_Detail!$G$5:$G$295,GF_Budget_Detail!$A$5:$A$295,B$6,GF_Budget_Detail!$D$5:$D$295,"Debt / lease financing proceeds") | C41: =SUMIFS(GF_Budget_Detail!$G$5:$G$295,GF_Budget_Detail!$A$5:$A$295,C$6,GF_Budget_Detail!$D$5:$D$295,"Debt / lease financing proceeds") | D41: =SUMIFS(GF_Budget_Detail!$G$5:$G$295,GF_Budget_Detail!$A$5:$A$295,D$6,GF_Budget_Detail!$D$5:$D$295,"Debt / lease financing proceeds") | E41: =SUMIFS(GF_Budget_Detail!$G$5:$G$295,GF_Budget_Detail!$A$5:$A$295,E$6,GF_Budget_Detail!$D$5:$D$295,"Debt / lease financing proceeds") | F41: =SUMIFS(GF_Budget_Detail!$G$5:$G$295,GF_Budget_Detail!$A$5:$A$295,F$6,GF_Budget_Detail!$D$5:$D$295,"Debt / lease financing proceeds") | G41: =SUMIFS(GF_Budget_Detail!$G$5:$G$295,GF_Budget_Detail!$A$5:$A$295,G$6,GF_Budget_Detail!$D$5:$D$295,"Debt / lease financing proceeds") | H41: =SUMIFS(GF_Budget_Detail!$G$5:$G$295,GF_Budget_Detail!$A$5:$A$295,H$6,GF_Budget_Detail!$D$5:$D$295,"Debt / lease financing proceeds") | I41: =SUMIFS(GF_Budget_Detail!$G$5:$G$295,GF_Budget_Detail!$A$5:$A$295,I$6,GF_Budget_Detail!$D$5:$D$295,"Debt / lease financing proceeds") | ... N41: =SUMIFS(GF_Budget_Detail!$G$5:$G$295,GF_Budget_Detail!$A$5:$A$295,N$6,GF_Budget_Detail!$D$5:$D$295,"Debt / lease financing proceeds")
A42: Proceeds from sale of capital assets | B42: =SUMIFS(GF_Budget_Detail!$G$5:$G$295,GF_Budget_Detail!$A$5:$A$295,B$6,GF_Budget_Detail!$D$5:$D$295,"Proceeds from sale of capital assets") | C42: =SUMIFS(GF_Budget_Detail!$G$5:$G$295,GF_Budget_Detail!$A$5:$A$295,C$6,GF_Budget_Detail!$D$5:$D$295,"Proceeds from sale of capital assets") | D42: =SUMIFS(GF_Budget_Detail!$G$5:$G$295,GF_Budget_Detail!$A$5:$A$295,D$6,GF_Budget_Detail!$D$5:$D$295,"Proceeds from sale of capital assets") | E42: =SUMIFS(GF_Budget_Detail!$G$5:$G$295,GF_Budget_Detail!$A$5:$A$295,E$6,GF_Budget_Detail!$D$5:$D$295,"Proceeds from sale of capital assets") | F42: =SUMIFS(GF_Budget_Detail!$G$5:$G$295,GF_Budget_Detail!$A$5:$A$295,F$6,GF_Budget_Detail!$D$5:$D$295,"Proceeds from sale of capital assets") | G42: =SUMIFS(GF_Budget_Detail!$G$5:$G$295,GF_Budget_Detail!$A$5:$A$295,G$6,GF_Budget_Detail!$D$5:$D$295,"Proceeds from sale of capital assets") | H42: =SUMIFS(GF_Budget_Detail!$G$5:$G$295,GF_Budget_Detail!$A$5:$A$295,H$6,GF_Budget_Detail!$D$5:$D$295,"Proceeds from sale of capital assets") | I42: =SUMIFS(GF_Budget_Detail!$G$5:$G$295,GF_Budget_Detail!$A$5:$A$295,I$6,GF_Budget_Detail!$D$5:$D$295,"Proceeds from sale of capital assets") | ... N42: =SUMIFS(GF_Budget_Detail!$G$5:$G$295,GF_Budget_Detail!$A$5:$A$295,N$6,GF_Budget_Detail!$D$5:$D$295,"Proceeds from sale of capital assets")
A43: Total other financing sources (uses) | B43: =SUM(B39:B42) | C43: =SUM(C39:C42) | D43: =SUM(D39:D42) | E43: =SUM(E39:E42) | F43: =SUM(F39:F42) | G43: =SUM(G39:G42) | H43: =SUM(H39:H42) | I43: =SUM(I39:I42) | ... N43: =SUM(N39:N42)
A45: SPECIAL ITEMS (GASB 34; 'unusual or infrequent items' under GASB 103 from FY2026)
A46: Special items | B46: =SUMIFS(GF_Budget_Detail!$G$5:$G$295,GF_Budget_Detail!$A$5:$A$295,B$6,GF_Budget_Detail!$D$5:$D$295,"Special items") | C46: =SUMIFS(GF_Budget_Detail!$G$5:$G$295,GF_Budget_Detail!$A$5:$A$295,C$6,GF_Budget_Detail!$D$5:$D$295,"Special items") | D46: =SUMIFS(GF_Budget_Detail!$G$5:$G$295,GF_Budget_Detail!$A$5:$A$295,D$6,GF_Budget_Detail!$D$5:$D$295,"Special items") | E46: =SUMIFS(GF_Budget_Detail!$G$5:$G$295,GF_Budget_Detail!$A$5:$A$295,E$6,GF_Budget_Detail!$D$5:$D$295,"Special items") | F46: =SUMIFS(GF_Budget_Detail!$G$5:$G$295,GF_Budget_Detail!$A$5:$A$295,F$6,GF_Budget_Detail!$D$5:$D$295,"Special items") | G46: =SUMIFS(GF_Budget_Detail!$G$5:$G$295,GF_Budget_Detail!$A$5:$A$295,G$6,GF_Budget_Detail!$D$5:$D$295,"Special items") | H46: =SUMIFS(GF_Budget_Detail!$G$5:$G$295,GF_Budget_Detail!$A$5:$A$295,H$6,GF_Budget_Detail!$D$5:$D$295,"Special items") | I46: =SUMIFS(GF_Budget_Detail!$G$5:$G$295,GF_Budget_Detail!$A$5:$A$295,I$6,GF_Budget_Detail!$D$5:$D$295,"Special items") | ... N46: =SUMIFS(GF_Budget_Detail!$G$5:$G$295,GF_Budget_Detail!$A$5:$A$295,N$6,GF_Budget_Detail!$D$5:$D$295,"Special items")
A48: Net change in fund balance | B48: =B36+B43+B46 | C48: =C36+C43+C46 | D48: =D36+D43+D46 | E48: =E36+E43+E46 | F48: =F36+F43+F46 | G48: =G36+G43+G46 | H48: =H36+H43+H46 | I48: =I36+I43+I46 | ... N48: =N36+N43+N46
A50: Fund balance - beginning, as previously reported | B50: 2341238 | C50: =B53 | D50: =C53 | E50: =D53 | F50: =E53 | G50: =F53 | H50: =G53 | I50: =H53 | J50: =I53 | ... N50: =M53
A51: Adjustment to beginning balance - restatement / error correction (GASB 100) | B51: 0 | C51: 0 | D51: 0 | E51: -1278327 | F51: 0 | G51: 0 | H51: 17729 | I51: 0 | J51: 0 | K51: -409799 | L51: 404 | M51: 0 | N51: 0
A52: Fund balance - beginning, as restated | B52: =B50+B51 | C52: =C50+C51 | D52: =D50+D51 | E52: =E50+E51 | F52: =F50+F51 | G52: =G50+G51 | H52: =H50+H51 | I52: =I50+I51 | ... N52: =N50+N51
A53: Fund balance - ending | B53: =B52+B48 | C53: =C52+C48 | D53: =D52+D48 | E53: =E52+E48 | F53: =F52+F48 | G53: =G52+G48 | H53: =H52+H48 | I53: =I52+I48 | ... N53: =N52+N48
A55: TREND MEASURES (GASB 44 / GFOA)
A56: Total revenues - % change from prior year | C56: =IFERROR(C17/B17-1,0) | D56: =IFERROR(D17/C17-1,0) | E56: =IFERROR(E17/D17-1,0) | F56: =IFERROR(F17/E17-1,0) | G56: =IFERROR(G17/F17-1,0) | H56: =IFERROR(H17/G17-1,0) | I56: =IFERROR(I17/H17-1,0) | J56: =IFERROR(J17/I17-1,0) | ... N56: =IFERROR(N17/M17-1,0)
A57: Total expenditures - % change from prior year | C57: =IFERROR(C34/B34-1,0) | D57: =IFERROR(D34/C34-1,0) | E57: =IFERROR(E34/D34-1,0) | F57: =IFERROR(F34/E34-1,0) | G57: =IFERROR(G34/F34-1,0) | H57: =IFERROR(H34/G34-1,0) | I57: =IFERROR(I34/H34-1,0) | J57: =IFERROR(J34/I34-1,0) | ... N57: =IFERROR(N34/M34-1,0)
A58: Debt service as % of noncapital expenditures | B58: =IFERROR((B32+B33)/(B34-B30),0) | C58: =IFERROR((C32+C33)/(C34-C30),0) | D58: =IFERROR((D32+D33)/(D34-D30),0) | E58: =IFERROR((E32+E33)/(E34-E30),0) | F58: =IFERROR((F32+F33)/(F34-F30),0) | G58: =IFERROR((G32+G33)/(G34-G30),0) | H58: =IFERROR((H32+H33)/(H34-H30),0) | I58: =IFERROR((I32+I33)/(I34-I30),0) | ... N58: =IFERROR((N32+N33)/(N34-N30),0)
A59: Expenditures + transfers out (total uses) | B59: =B34-B40 | C59: =C34-C40 | D59: =D34-D40 | E59: =E34-E40 | F59: =F34-F40 | G59: =G34-G40 | H59: =H34-H40 | I59: =I34-I40 | ... N59: =N34-N40
A60: Ending fund balance as % of expenditures | B60: =IFERROR(B53/B34,0) | C60: =IFERROR(C53/C34,0) | D60: =IFERROR(D53/D34,0) | E60: =IFERROR(E53/E34,0) | F60: =IFERROR(F53/F34,0) | G60: =IFERROR(G53/G34,0) | H60: =IFERROR(H53/H34,0) | I60: =IFERROR(I53/I34,0) | ... N60: =IFERROR(N53/N34,0)
A62: Check: beginning balance as restated per source document | B62: 2341238 | C62: 1270466 | D62: 1461512 | E62: 615515 | F62: 818720 | G62: 87570 | H62: -38963 | I62: -110021 | J62: 7143262 | K62: 16214375 | L62: 23143485 | M62: 22893338 | N62: 24250508
A63: Check: beginning as restated - source (should be 0) | B63: =B52-B62 | C63: =C52-C62 | D63: =D52-D62 | E63: =E52-E62 | F63: =F52-F62 | G63: =G52-G62 | H63: =H52-H62 | I63: =I52-I62 | ... N63: =N52-N62
A64: Check: ending fund balance per source document | B64: 1270466 | C64: 1461512 | D64: 1893842 | E64: 818720 | F64: 87570 | G64: -56692 | H64: -110021 | I64: 7143262 | J64: 16624174 | K64: 23143081 | L64: 22893338 | M64: 24250508 | N64: 23166797
A65: Check: ending - source (should be 0) | B65: =B53-B64 | C65: =C53-C64 | D65: =D53-D64 | E65: =E53-E64 | F65: =F53-F64 | G65: =G53-G64 | H65: =H53-H64 | I65: =I53-I64 | ... N65: =N53-N64

Sheet GF_Balance_Sheet
A1: City of El Cerrito - GENERAL FUND ONLY
A2: Balance Sheet, June 30, $ (General Fund column of the Governmental Funds Balance Sheet)
A3: Modified-accrual fund statement: excludes buildings/equipment, long-term debt and pension liabilities (see the CW_ tabs for those). No FY2025-26 balance sheet has been published yet (unaudited Q4 update reports only the projected ending fund balance).
A6: June 30 | B6: 2014 | C6: 2015 | D6: 2016 | E6: 2017 | F6: 2018 | G6: 2019 | H6: 2020 | I6: 2021 | J6: 2022 | K6: 2023 | L6: 2024 | M6: 2025
A7: ASSETS
A8: Cash and investments | B8: 1 | C8: 1 | D8: 5116309 | E8: 3107248 | F8: 3419338 | G8: 4349089 | H8: 9016794 | I8: 13011276 | J8: 23310907 | K8: 24481528 | L8: 25339004 | M8: 25387360
A9: Cash with fiscal agents | B9: 150445 | C9: 10170 | D9: 10187 | E9: 10205 | F9: 0 | G9: 0 | H9: 0 | I9: 0 | J9: 0 | K9: 0 | L9: 0 | M9: 0
A10: Accounts receivable | B10: 187946 | C10: 29493 | D10: 155287 | E10: 3743 | F10: 9530 | G10: 0 | H10: 633574 | I10: 0 | J10: 6747 | K10: 0 | L10: 1078 | M10: 1890204
A11: Interest receivable | B11: 1 | C11: 0 | D11: 0 | E11: 0 | F11: 0 | G11: 0 | H11: 32158 | I11: 11858 | J11: 24077 | K11: 203968 | L11: 272482 | M11: 220648
A12: Due from other governments | B12: 1747713 | C12: 3253667 | D12: 1663837 | E12: 2348549 | F12: 2778497 | G12: 2113059 | H12: 1249313 | I12: 2955585 | J12: 1027427 | K12: 3481165 | L12: 3291852 | M12: 1952392
A13: Due from other funds | B13: 310035 | C13: 0 | D13: 1270421 | E13: 1671263 | F13: 385338 | G13: 951617 | H13: 374902 | I13: 2846549 | J13: 3051028 | K13: 303058 | L13: 0 | M13: 467019
A14: Advances to other funds | B14: 0 | C14: 0 | D14: 0 | E14: 0 | F14: 988351 | G14: 317967 | H14: 315306 | I14: 0 | J14: 0 | K14: 0 | L14: 0 | M14: 0
A15: Advance to Successor Agency (former RDA) | B15: 0 | C15: 0 | D15: 0 | E15: 873766 | F15: 1321189 | G15: 1321189 | H15: 1321189 | I15: 0 | J15: 0 | K15: 0 | L15: 0 | M15: 0
A16: Inventory | B16: 26965 | C16: 73942 | D16: 110975 | E16: 23595 | F16: 11537 | G16: 11772 | H16: 27737 | I16: 25694 | J16: 38763 | K16: 46338 | L16: 0 | M16: 0
A17: Prepaid items and other assets | B17: 31361 | C17: 54300 | D17: 59378 | E17: 97381 | F17: 0 | G17: 0 | H17: 3279 | I17: 0 | J17: 161576 | K17: 62527 | L17: 138615 | M17: 187240
A18: Total assets | B18: =SUM(B8:B17) | C18: =SUM(C8:C17) | D18: =SUM(D8:D17) | E18: =SUM(E8:E17) | F18: =SUM(F8:F17) | G18: =SUM(G8:G17) | H18: =SUM(H8:H17) | I18: =SUM(I8:I17) | ... M18: =SUM(M8:M17)
A20: LIABILITIES
A21: Accounts payable | B21: 596507 | C21: 732767 | D21: 883120 | E21: 524897 | F21: 346261 | G21: 888579 | H21: 844519 | I21: 806511 | J21: 1248347 | K21: 899927 | L21: 745552 | M21: 1424412
A22: Accrued liabilities | B22: 34074 | C22: 47553 | D22: 61268 | E22: 1081986 | F22: 1102088 | G22: 1231944 | H22: 1551848 | I22: 398547 | J22: 1589666 | K22: 970665 | L22: 1390950 | M22: 1063940
A23: Due to other funds | B23: 250000 | C23: 849386 | D23: 0 | E23: 0 | F23: 0 | G23: 0 | H23: 0 | I23: 0 | J23: 0 | K23: 0 | L23: 0 | M23: 0
A24: Deposits payable | B24: 272842 | C24: 296624 | D24: 500482 | E24: 515730 | F24: 645593 | G24: 804162 | H24: 1605016 | I24: 1759634 | J24: 2006664 | K24: 2222396 | L24: 2465295 | M24: 2394927
A25: Unearned revenue | B25: 30578 | C25: 33731 | D25: 47682 | E25: 47389 | F25: 65497 | G25: 80381 | H25: 82890 | I25: 83463 | J25: 90782 | K25: 1342515 | L25: 1251292 | M25: 729770
A26: Note payable (short-term TRAN) | B26: 0 | C26: 0 | D26: 5000000 | E26: 5000000 | F26: 6000000 | G26: 6000000 | H26: 9000000 | I26: 8659545 | J26: 6060892 | K26: 0 | L26: 0 | M26: 0
A27: Total liabilities | B27: =SUM(B21:B26) | C27: =SUM(C21:C26) | D27: =SUM(D21:D26) | E27: =SUM(E21:E26) | F27: =SUM(F21:F26) | G27: =SUM(G21:G26) | H27: =SUM(H21:H26) | I27: =SUM(I21:I26) | ... M27: =SUM(M21:M26)
A29: DEFERRED INFLOWS OF RESOURCES
A30: Unavailable revenue | B30: 0 | C30: 0 | D30: 0 | E30: 147028 | F30: 666771 | G30: 116319 | H30: 0 | I30: 0 | J30: 0 | K30: 0 | L30: 296604 | M30: 241306
A31: Total deferred inflows | B31: =SUM(B30:B30) | C31: =SUM(C30:C30) | D31: =SUM(D30:D30) | E31: =SUM(E30:E30) | F31: =SUM(F30:F30) | G31: =SUM(G30:G30) | H31: =SUM(H30:H30) | I31: =SUM(I30:I30) | ... M31: =SUM(M30:M30)
A33: FUND BALANCE
A34: Nonspendable | B34: 58326 | C34: 128242 | D34: 170353 | E34: 994742 | F34: 2321077 | G34: 1650928 | H34: 1667511 | I34: 25694 | J34: 200339 | K34: 108865 | L34: 126751 | M34: 175376
A35: Restricted | B35: 150445 | C35: 10170 | D35: 10187 | E35: 10205 | F35: 0 | G35: 0 | H35: 0 | I35: 0 | J35: 0 | K35: 0 | L35: 1372890 | M35: 2960245
A36: Committed | B36: 0 | C36: 0 | D36: 0 | E36: 0 | F36: 0 | G36: 0 | H36: 0 | I36: 0 | J36: 0 | K36: 0 | L36: 0 | M36: 0
A37: Assigned | B37: 53108 | C37: 0 | D37: 0 | E37: 0 | F37: 0 | G37: 0 | H37: 0 | I37: 0 | J37: 0 | K37: 0 | L37: 0 | M37: 0
A38: Unassigned - Emergency Disaster Relief reserve | B38: 0 | C38: 0 | D38: 0 | E38: 0 | F38: 0 | G38: 0 | H38: 0 | I38: 0 | J38: 0 | K38: 0 | L38: 9000000 | M38: 7500000
A39: Unassigned - remaining | B39: 1008587 | C39: 1323100 | D39: 1713302 | E39: -186227 | F39: -2233507 | G39: -1707620 | H39: -1777532 | I39: 7117568 | J39: 16423835 | K39: 23034216 | L39: 12393697 | M39: 13614887
A40: Total fund balance | B40: =SUM(B34:B39) | C40: =SUM(C34:C39) | D40: =SUM(D34:D39) | E40: =SUM(E34:E39) | F40: =SUM(F34:F39) | G40: =SUM(G34:G39) | H40: =SUM(H34:H39) | I40: =SUM(I34:I39) | ... M40: =SUM(M34:M39)
A42: Total liabilities, deferred inflows and fund balance | B42: =B27+B31+B40 | C42: =C27+C31+C40 | D42: =D27+D31+D40 | E42: =E27+E31+E40 | F42: =F27+F31+F40 | G42: =G27+G31+G40 | H42: =H27+H31+H40 | I42: =I27+I31+I40 | ... M42: =M27+M31+M40
A44: Memo: working capital (assets less liabilities, excl. advances) | B44: =B18-B14-B15-B27 | C44: =C18-C14-C15-C27 | D44: =D18-D14-D15-D27 | E44: =E18-E14-E15-E27 | F44: =F18-F14-F15-F27 | G44: =G18-G14-G15-G27 | H44: =H18-H14-H15-H27 | I44: =I18-I14-I15-I27 | ... M44: =M18-M14-M15-M27
A45: Memo: unassigned fund balance incl. EDRF | B45: =B38+B39 | C45: =C38+C39 | D45: =D38+D39 | E45: =E38+E39 | F45: =F38+F39 | G45: =G38+G39 | H45: =H38+H39 | I45: =I38+I39 | ... M45: =M38+M39
A46: Memo: unassigned fund balance as % of expenditures | B46: =IFERROR(B45/GF_Operating_Statement!B34,0) | C46: =IFERROR(C45/GF_Operating_Statement!C34,0) | D46: =IFERROR(D45/GF_Operating_Statement!D34,0) | E46: =IFERROR(E45/GF_Operating_Statement!E34,0) | F46: =IFERROR(F45/GF_Operating_Statement!F34,0) | G46: =IFERROR(G45/GF_Operating_Statement!G34,0) | H46: =IFERROR(H45/GF_Operating_Statement!H34,0) | I46: =IFERROR(I45/GF_Operating_Statement!I34,0) | ... M46: =IFERROR(M45/GF_Operating_Statement!M34,0)
A48: Check: total assets per audited balance sheet | B48: 2454467 | C48: 3421573 | D48: 8386394 | E48: 8135750 | F48: 8913780 | G48: 9064693 | H48: 12974252 | I48: 18850962 | J48: 27620525 | K48: 28578584 | L48: 29043031 | M48: 30104863
A49: Check: assets - reported (should be 0) | B49: =B18-B48 | C49: =C18-C48 | D49: =D18-D48 | E49: =E18-E48 | F49: =F18-F48 | G49: =G18-G48 | H49: =H18-H48 | I49: =I18-I48 | ... M49: =M18-M48
A50: Check: assets - (liabilities + deferred + fund balance) | B50: =B18-B42 | C50: =C18-C42 | D50: =D18-D42 | E50: =E18-E42 | F50: =F18-F42 | G50: =G18-G42 | H50: =H18-H42 | I50: =I18-I42 | ... M50: =M18-M42
A51: Check: fund balance vs. GF_Operating_Statement ending | B51: =B40-GF_Operating_Statement!B53 | C51: =C40-GF_Operating_Statement!C53 | D51: =D40-GF_Operating_Statement!D53 | E51: =E40-GF_Operating_Statement!E53 | F51: =F40-GF_Operating_Statement!F53 | G51: =G40-GF_Operating_Statement!G53 | H51: =H40-GF_Operating_Statement!H53 | I51: =I40-GF_Operating_Statement!I53 | ... M51: =M40-GF_Operating_Statement!M53

Sheet GF_Cash_Flow_Derived
A1: City of El Cerrito - GENERAL FUND ONLY
A2: Statement of Cash Flows - DERIVED (indirect method, GASB 9 categories), $
A3: Not an audited statement: governmental funds do not report cash flows under GASB. Built from GF_Operating_Statement and year-over-year GF_Balance_Sheet changes. FY2014 omitted (needs the June 30, 2013 balance sheet); FY2026 omitted (no balance sheet yet).
A6: Fiscal year ended June 30 | B6: 2014 | C6: 2015 | D6: 2016 | E6: 2017 | F6: 2018 | G6: 2019 | H6: 2020 | I6: 2021 | J6: 2022 | K6: 2023 | L6: 2024 | M6: 2025
A7: CASH FLOWS FROM OPERATING ACTIVITIES
A8: Revenues less current (operating) expenditures | C8: =GF_Operating_Statement!C36+GF_Operating_Statement!C30+GF_Operating_Statement!C32+GF_Operating_Statement!C33 | D8: =GF_Operating_Statement!D36+GF_Operating_Statement!D30+GF_Operating_Statement!D32+GF_Operating_Statement!D33 | E8: =GF_Operating_Statement!E36+GF_Operating_Statement!E30+GF_Operating_Statement!E32+GF_Operating_Statement!E33 | F8: =GF_Operating_Statement!F36+GF_Operating_Statement!F30+GF_Operating_Statement!F32+GF_Operating_Statement!F33 | G8: =GF_Operating_Statement!G36+GF_Operating_Statement!G30+GF_Operating_Statement!G32+GF_Operating_Statement!G33 | H8: =GF_Operating_Statement!H36+GF_Operating_Statement!H30+GF_Operating_Statement!H32+GF_Operating_Statement!H33 | I8: =GF_Operating_Statement!I36+GF_Operating_Statement!I30+GF_Operating_Statement!I32+GF_Operating_Statement!I33 | J8: =GF_Operating_Statement!J36+GF_Operating_Statement!J30+GF_Operating_Statement!J32+GF_Operating_Statement!J33 | ... M8: =GF_Operating_Statement!M36+GF_Operating_Statement!M30+GF_Operating_Statement!M32+GF_Operating_Statement!M33
A9: (Increase) decrease in receivables (AR, interest, due from governments) | C9: =-(GF_Balance_Sheet!C10-GF_Balance_Sheet!B10+GF_Balance_Sheet!C11-GF_Balance_Sheet!B11+GF_Balance_Sheet!C12-GF_Balance_Sheet!B12) | D9: =-(GF_Balance_Sheet!D10-GF_Balance_Sheet!C10+GF_Balance_Sheet!D11-GF_Balance_Sheet!C11+GF_Balance_Sheet!D12-GF_Balance_Sheet!C12) | E9: =-(GF_Balance_Sheet!E10-GF_Balance_Sheet!D10+GF_Balance_Sheet!E11-GF_Balance_Sheet!D11+GF_Balance_Sheet!E12-GF_Balance_Sheet!D12) | F9: =-(GF_Balance_Sheet!F10-GF_Balance_Sheet!E10+GF_Balance_Sheet!F11-GF_Balance_Sheet!E11+GF_Balance_Sheet!F12-GF_Balance_Sheet!E12) | G9: =-(GF_Balance_Sheet!G10-GF_Balance_Sheet!F10+GF_Balance_Sheet!G11-GF_Balance_Sheet!F11+GF_Balance_Sheet!G12-GF_Balance_Sheet!F12) | H9: =-(GF_Balance_Sheet!H10-GF_Balance_Sheet!G10+GF_Balance_Sheet!H11-GF_Balance_Sheet!G11+GF_Balance_Sheet!H12-GF_Balance_Sheet!G12) | I9: =-(GF_Balance_Sheet!I10-GF_Balance_Sheet!H10+GF_Balance_Sheet!I11-GF_Balance_Sheet!H11+GF_Balance_Sheet!I12-GF_Balance_Sheet!H12) | J9: =-(GF_Balance_Sheet!J10-GF_Balance_Sheet!I10+GF_Balance_Sheet!J11-GF_Balance_Sheet!I11+GF_Balance_Sheet!J12-GF_Balance_Sheet!I12) | ... M9: =-(GF_Balance_Sheet!M10-GF_Balance_Sheet!L10+GF_Balance_Sheet!M11-GF_Balance_Sheet!L11+GF_Balance_Sheet!M12-GF_Balance_Sheet!L12)
A10: (Increase) decrease in inventory and prepaids | C10: =-(GF_Balance_Sheet!C16-GF_Balance_Sheet!B16+GF_Balance_Sheet!C17-GF_Balance_Sheet!B17) | D10: =-(GF_Balance_Sheet!D16-GF_Balance_Sheet!C16+GF_Balance_Sheet!D17-GF_Balance_Sheet!C17) | E10: =-(GF_Balance_Sheet!E16-GF_Balance_Sheet!D16+GF_Balance_Sheet!E17-GF_Balance_Sheet!D17) | F10: =-(GF_Balance_Sheet!F16-GF_Balance_Sheet!E16+GF_Balance_Sheet!F17-GF_Balance_Sheet!E17) | G10: =-(GF_Balance_Sheet!G16-GF_Balance_Sheet!F16+GF_Balance_Sheet!G17-GF_Balance_Sheet!F17) | H10: =-(GF_Balance_Sheet!H16-GF_Balance_Sheet!G16+GF_Balance_Sheet!H17-GF_Balance_Sheet!G17) | I10: =-(GF_Balance_Sheet!I16-GF_Balance_Sheet!H16+GF_Balance_Sheet!I17-GF_Balance_Sheet!H17) | J10: =-(GF_Balance_Sheet!J16-GF_Balance_Sheet!I16+GF_Balance_Sheet!J17-GF_Balance_Sheet!I17) | ... M10: =-(GF_Balance_Sheet!M16-GF_Balance_Sheet!L16+GF_Balance_Sheet!M17-GF_Balance_Sheet!L17)
A11: Increase (decrease) in accounts payable and accrued liabilities | C11: =(GF_Balance_Sheet!C21-GF_Balance_Sheet!B21+GF_Balance_Sheet!C22-GF_Balance_Sheet!B22) | D11: =(GF_Balance_Sheet!D21-GF_Balance_Sheet!C21+GF_Balance_Sheet!D22-GF_Balance_Sheet!C22) | E11: =(GF_Balance_Sheet!E21-GF_Balance_Sheet!D21+GF_Balance_Sheet!E22-GF_Balance_Sheet!D22) | F11: =(GF_Balance_Sheet!F21-GF_Balance_Sheet!E21+GF_Balance_Sheet!F22-GF_Balance_Sheet!E22) | G11: =(GF_Balance_Sheet!G21-GF_Balance_Sheet!F21+GF_Balance_Sheet!G22-GF_Balance_Sheet!F22) | H11: =(GF_Balance_Sheet!H21-GF_Balance_Sheet!G21+GF_Balance_Sheet!H22-GF_Balance_Sheet!G22) | I11: =(GF_Balance_Sheet!I21-GF_Balance_Sheet!H21+GF_Balance_Sheet!I22-GF_Balance_Sheet!H22) | J11: =(GF_Balance_Sheet!J21-GF_Balance_Sheet!I21+GF_Balance_Sheet!J22-GF_Balance_Sheet!I22) | ... M11: =(GF_Balance_Sheet!M21-GF_Balance_Sheet!L21+GF_Balance_Sheet!M22-GF_Balance_Sheet!L22)
A12: Increase (decrease) in deposits payable | C12: =(GF_Balance_Sheet!C24-GF_Balance_Sheet!B24) | D12: =(GF_Balance_Sheet!D24-GF_Balance_Sheet!C24) | E12: =(GF_Balance_Sheet!E24-GF_Balance_Sheet!D24) | F12: =(GF_Balance_Sheet!F24-GF_Balance_Sheet!E24) | G12: =(GF_Balance_Sheet!G24-GF_Balance_Sheet!F24) | H12: =(GF_Balance_Sheet!H24-GF_Balance_Sheet!G24) | I12: =(GF_Balance_Sheet!I24-GF_Balance_Sheet!H24) | J12: =(GF_Balance_Sheet!J24-GF_Balance_Sheet!I24) | ... M12: =(GF_Balance_Sheet!M24-GF_Balance_Sheet!L24)
A13: Increase (decrease) in unearned revenue and unavailable revenue | C13: =(GF_Balance_Sheet!C25-GF_Balance_Sheet!B25+GF_Balance_Sheet!C30-GF_Balance_Sheet!B30) | D13: =(GF_Balance_Sheet!D25-GF_Balance_Sheet!C25+GF_Balance_Sheet!D30-GF_Balance_Sheet!C30) | E13: =(GF_Balance_Sheet!E25-GF_Balance_Sheet!D25+GF_Balance_Sheet!E30-GF_Balance_Sheet!D30) | F13: =(GF_Balance_Sheet!F25-GF_Balance_Sheet!E25+GF_Balance_Sheet!F30-GF_Balance_Sheet!E30) | G13: =(GF_Balance_Sheet!G25-GF_Balance_Sheet!F25+GF_Balance_Sheet!G30-GF_Balance_Sheet!F30) | H13: =(GF_Balance_Sheet!H25-GF_Balance_Sheet!G25+GF_Balance_Sheet!H30-GF_Balance_Sheet!G30) | I13: =(GF_Balance_Sheet!I25-GF_Balance_Sheet!H25+GF_Balance_Sheet!I30-GF_Balance_Sheet!H30) | J13: =(GF_Balance_Sheet!J25-GF_Balance_Sheet!I25+GF_Balance_Sheet!J30-GF_Balance_Sheet!I30) | ... M13: =(GF_Balance_Sheet!M25-GF_Balance_Sheet!L25+GF_Balance_Sheet!M30-GF_Balance_Sheet!L30)
A14: Net cash provided (used) by operating activities | C14: =SUM(C8:C13) | D14: =SUM(D8:D13) | E14: =SUM(E8:E13) | F14: =SUM(F8:F13) | G14: =SUM(G8:G13) | H14: =SUM(H8:H13) | I14: =SUM(I8:I13) | J14: =SUM(J8:J13) | ... M14: =SUM(M8:M13)
A16: CASH FLOWS FROM NONCAPITAL FINANCING ACTIVITIES
A17: Transfers in | C17: =GF_Operating_Statement!C39 | D17: =GF_Operating_Statement!D39 | E17: =GF_Operating_Statement!E39 | F17: =GF_Operating_Statement!F39 | G17: =GF_Operating_Statement!G39 | H17: =GF_Operating_Statement!H39 | I17: =GF_Operating_Statement!I39 | J17: =GF_Operating_Statement!J39 | ... M17: =GF_Operating_Statement!M39
A18: Transfers out | C18: =GF_Operating_Statement!C40 | D18: =GF_Operating_Statement!D40 | E18: =GF_Operating_Statement!E40 | F18: =GF_Operating_Statement!F40 | G18: =GF_Operating_Statement!G40 | H18: =GF_Operating_Statement!H40 | I18: =GF_Operating_Statement!I40 | J18: =GF_Operating_Statement!J40 | ... M18: =GF_Operating_Statement!M40
A19: Special items | C19: =GF_Operating_Statement!C46 | D19: =GF_Operating_Statement!D46 | E19: =GF_Operating_Statement!E46 | F19: =GF_Operating_Statement!F46 | G19: =GF_Operating_Statement!G46 | H19: =GF_Operating_Statement!H46 | I19: =GF_Operating_Statement!I46 | J19: =GF_Operating_Statement!J46 | ... M19: =GF_Operating_Statement!M46
A20: Net change in interfund balances and advances | C20: =-(GF_Balance_Sheet!C13-GF_Balance_Sheet!B13+GF_Balance_Sheet!C14-GF_Balance_Sheet!B14+GF_Balance_Sheet!C15-GF_Balance_Sheet!B15)+(GF_Balance_Sheet!C23-GF_Balance_Sheet!B23) | D20: =-(GF_Balance_Sheet!D13-GF_Balance_Sheet!C13+GF_Balance_Sheet!D14-GF_Balance_Sheet!C14+GF_Balance_Sheet!D15-GF_Balance_Sheet!C15)+(GF_Balance_Sheet!D23-GF_Balance_Sheet!C23) | E20: =-(GF_Balance_Sheet!E13-GF_Balance_Sheet!D13+GF_Balance_Sheet!E14-GF_Balance_Sheet!D14+GF_Balance_Sheet!E15-GF_Balance_Sheet!D15)+(GF_Balance_Sheet!E23-GF_Balance_Sheet!D23) | F20: =-(GF_Balance_Sheet!F13-GF_Balance_Sheet!E13+GF_Balance_Sheet!F14-GF_Balance_Sheet!E14+GF_Balance_Sheet!F15-GF_Balance_Sheet!E15)+(GF_Balance_Sheet!F23-GF_Balance_Sheet!E23) | G20: =-(GF_Balance_Sheet!G13-GF_Balance_Sheet!F13+GF_Balance_Sheet!G14-GF_Balance_Sheet!F14+GF_Balance_Sheet!G15-GF_Balance_Sheet!F15)+(GF_Balance_Sheet!G23-GF_Balance_Sheet!F23) | H20: =-(GF_Balance_Sheet!H13-GF_Balance_Sheet!G13+GF_Balance_Sheet!H14-GF_Balance_Sheet!G14+GF_Balance_Sheet!H15-GF_Balance_Sheet!G15)+(GF_Balance_Sheet!H23-GF_Balance_Sheet!G23) | I20: =-(GF_Balance_Sheet!I13-GF_Balance_Sheet!H13+GF_Balance_Sheet!I14-GF_Balance_Sheet!H14+GF_Balance_Sheet!I15-GF_Balance_Sheet!H15)+(GF_Balance_Sheet!I23-GF_Balance_Sheet!H23) | J20: =-(GF_Balance_Sheet!J13-GF_Balance_Sheet!I13+GF_Balance_Sheet!J14-GF_Balance_Sheet!I14+GF_Balance_Sheet!J15-GF_Balance_Sheet!I15)+(GF_Balance_Sheet!J23-GF_Balance_Sheet!I23) | ... M20: =-(GF_Balance_Sheet!M13-GF_Balance_Sheet!L13+GF_Balance_Sheet!M14-GF_Balance_Sheet!L14+GF_Balance_Sheet!M15-GF_Balance_Sheet!L15)+(GF_Balance_Sheet!M23-GF_Balance_Sheet!L23)
A21: Short-term notes (TRAN) issued (repaid), net | C21: =(GF_Balance_Sheet!C26-GF_Balance_Sheet!B26) | D21: =(GF_Balance_Sheet!D26-GF_Balance_Sheet!C26) | E21: =(GF_Balance_Sheet!E26-GF_Balance_Sheet!D26) | F21: =(GF_Balance_Sheet!F26-GF_Balance_Sheet!E26) | G21: =(GF_Balance_Sheet!G26-GF_Balance_Sheet!F26) | H21: =(GF_Balance_Sheet!H26-GF_Balance_Sheet!G26) | I21: =(GF_Balance_Sheet!I26-GF_Balance_Sheet!H26) | J21: =(GF_Balance_Sheet!J26-GF_Balance_Sheet!I26) | ... M21: =(GF_Balance_Sheet!M26-GF_Balance_Sheet!L26)
A22: Net cash provided (used) by noncapital financing activities | C22: =SUM(C17:C21) | D22: =SUM(D17:D21) | E22: =SUM(E17:E21) | F22: =SUM(F17:F21) | G22: =SUM(G17:G21) | H22: =SUM(H17:H21) | I22: =SUM(I17:I21) | J22: =SUM(J17:J21) | ... M22: =SUM(M17:M21)
A24: CASH FLOWS FROM CAPITAL AND RELATED FINANCING ACTIVITIES
A25: Capital outlay | C25: =-GF_Operating_Statement!C30 | D25: =-GF_Operating_Statement!D30 | E25: =-GF_Operating_Statement!E30 | F25: =-GF_Operating_Statement!F30 | G25: =-GF_Operating_Statement!G30 | H25: =-GF_Operating_Statement!H30 | I25: =-GF_Operating_Statement!I30 | J25: =-GF_Operating_Statement!J30 | ... M25: =-GF_Operating_Statement!M30
A26: Principal paid on debt and leases | C26: =-GF_Operating_Statement!C32 | D26: =-GF_Operating_Statement!D32 | E26: =-GF_Operating_Statement!E32 | F26: =-GF_Operating_Statement!F32 | G26: =-GF_Operating_Statement!G32 | H26: =-GF_Operating_Statement!H32 | I26: =-GF_Operating_Statement!I32 | J26: =-GF_Operating_Statement!J32 | ... M26: =-GF_Operating_Statement!M32
A27: Interest and fiscal charges paid | C27: =-GF_Operating_Statement!C33 | D27: =-GF_Operating_Statement!D33 | E27: =-GF_Operating_Statement!E33 | F27: =-GF_Operating_Statement!F33 | G27: =-GF_Operating_Statement!G33 | H27: =-GF_Operating_Statement!H33 | I27: =-GF_Operating_Statement!I33 | J27: =-GF_Operating_Statement!J33 | ... M27: =-GF_Operating_Statement!M33
A28: Debt / lease proceeds and sale of capital assets | C28: =GF_Operating_Statement!C41+GF_Operating_Statement!C42 | D28: =GF_Operating_Statement!D41+GF_Operating_Statement!D42 | E28: =GF_Operating_Statement!E41+GF_Operating_Statement!E42 | F28: =GF_Operating_Statement!F41+GF_Operating_Statement!F42 | G28: =GF_Operating_Statement!G41+GF_Operating_Statement!G42 | H28: =GF_Operating_Statement!H41+GF_Operating_Statement!H42 | I28: =GF_Operating_Statement!I41+GF_Operating_Statement!I42 | J28: =GF_Operating_Statement!J41+GF_Operating_Statement!J42 | ... M28: =GF_Operating_Statement!M41+GF_Operating_Statement!M42
A29: Net cash provided (used) by capital and related financing activities | C29: =SUM(C25:C28) | D29: =SUM(D25:D28) | E29: =SUM(E25:E28) | F29: =SUM(F25:F28) | G29: =SUM(G25:G28) | H29: =SUM(H25:H28) | I29: =SUM(I25:I28) | J29: =SUM(J25:J28) | ... M29: =SUM(M25:M28)
A31: CASH FLOWS FROM INVESTING ACTIVITIES
A32: Not separately identifiable (interest income is in 'Use of money and property', combined with rents)
A34: Total identified cash flows | C34: =C14+C22+C29 | D34: =D14+D22+D29 | E34: =E14+E22+E29 | F34: =F14+F22+F29 | G34: =G14+G22+G29 | H34: =H14+H22+H29 | I34: =I14+I22+I29 | J34: =J14+J22+J29 | ... M34: =M14+M22+M29
A35: Prior-period restatements / unreconciled | C35: =C37-C34 | D35: =D37-D34 | E35: =E37-E34 | F35: =F37-F34 | G35: =G37-G34 | H35: =H37-H34 | I35: =I37-I34 | J35: =J37-J34 | ... M35: =M37-M34
A37: Net change in cash (cash + cash with fiscal agents) | C37: =(GF_Balance_Sheet!C8+GF_Balance_Sheet!C9)-(GF_Balance_Sheet!B8+GF_Balance_Sheet!B9) | D37: =(GF_Balance_Sheet!D8+GF_Balance_Sheet!D9)-(GF_Balance_Sheet!C8+GF_Balance_Sheet!C9) | E37: =(GF_Balance_Sheet!E8+GF_Balance_Sheet!E9)-(GF_Balance_Sheet!D8+GF_Balance_Sheet!D9) | F37: =(GF_Balance_Sheet!F8+GF_Balance_Sheet!F9)-(GF_Balance_Sheet!E8+GF_Balance_Sheet!E9) | G37: =(GF_Balance_Sheet!G8+GF_Balance_Sheet!G9)-(GF_Balance_Sheet!F8+GF_Balance_Sheet!F9) | H37: =(GF_Balance_Sheet!H8+GF_Balance_Sheet!H9)-(GF_Balance_Sheet!G8+GF_Balance_Sheet!G9) | I37: =(GF_Balance_Sheet!I8+GF_Balance_Sheet!I9)-(GF_Balance_Sheet!H8+GF_Balance_Sheet!H9) | J37: =(GF_Balance_Sheet!J8+GF_Balance_Sheet!J9)-(GF_Balance_Sheet!I8+GF_Balance_Sheet!I9) | ... M37: =(GF_Balance_Sheet!M8+GF_Balance_Sheet!M9)-(GF_Balance_Sheet!L8+GF_Balance_Sheet!L9)
A38: Cash, beginning of year | C38: =GF_Balance_Sheet!B8+GF_Balance_Sheet!B9 | D38: =GF_Balance_Sheet!C8+GF_Balance_Sheet!C9 | E38: =GF_Balance_Sheet!D8+GF_Balance_Sheet!D9 | F38: =GF_Balance_Sheet!E8+GF_Balance_Sheet!E9 | G38: =GF_Balance_Sheet!F8+GF_Balance_Sheet!F9 | H38: =GF_Balance_Sheet!G8+GF_Balance_Sheet!G9 | I38: =GF_Balance_Sheet!H8+GF_Balance_Sheet!H9 | J38: =GF_Balance_Sheet!I8+GF_Balance_Sheet!I9 | ... M38: =GF_Balance_Sheet!L8+GF_Balance_Sheet!L9
A39: Cash, end of year | C39: =C38+C37 | D39: =D38+D37 | E39: =E38+E37 | F39: =F38+F37 | G39: =G38+G37 | H39: =H38+H37 | I39: =I38+I37 | J39: =J38+J37 | ... M39: =M38+M37
A41: Check: end cash vs. GF_Balance_Sheet (should be 0) | C41: =C39-(GF_Balance_Sheet!C8+GF_Balance_Sheet!C9) | D41: =D39-(GF_Balance_Sheet!D8+GF_Balance_Sheet!D9) | E41: =E39-(GF_Balance_Sheet!E8+GF_Balance_Sheet!E9) | F41: =F39-(GF_Balance_Sheet!F8+GF_Balance_Sheet!F9) | G41: =G39-(GF_Balance_Sheet!G8+GF_Balance_Sheet!G9) | H41: =H39-(GF_Balance_Sheet!H8+GF_Balance_Sheet!H9) | I41: =I39-(GF_Balance_Sheet!I8+GF_Balance_Sheet!I9) | J41: =J39-(GF_Balance_Sheet!J8+GF_Balance_Sheet!J9) | ... M41: =M39-(GF_Balance_Sheet!M8+GF_Balance_Sheet!M9)
A42: Check: restatement line vs. GF_Operating_Statement restatement memo | C42: =C35-GF_Operating_Statement!C51 | D42: =D35-GF_Operating_Statement!D51 | E42: =E35-GF_Operating_Statement!E51 | F42: =F35-GF_Operating_Statement!F51 | G42: =G35-GF_Operating_Statement!G51 | H42: =H35-GF_Operating_Statement!H51 | I42: =I35-GF_Operating_Statement!I51 | J42: =J35-GF_Operating_Statement!J51 | ... M42: =M35-GF_Operating_Statement!M51

Sheet GF_Budget_Variance
A1: City of El Cerrito - GENERAL FUND ONLY
A2: Budgetary comparison schedules by fiscal year (GASB 34/41 format with GASB 103 variance columns), $ | K2: Significance threshold - $ | L2: 100000
A3: Columns B-F follow the required RSI layout; column G is supplementary. Positive (negative) = favorable (unfavorable). FY2025-26 block is UNAUDITED. All figures are SUMIFS on GF_Budget_Detail. | K3: Significance threshold - % of final budget | L3: 0.1
A5: FY2013-14 (year ended June 30, 2014) - Budgetary comparison schedule, General Fund - GAAP (modified accrual) budgetary basis | J5: 2014
A6: Category | B6: Budgeted amounts - Original | C6: Budgeted amounts - Final | D6: Actual amounts (budgetary basis) | E6: Variance: Original to Final budget, increase (decrease) | F6: Variance with Final budget, positive (negative) | G6: Variance with Original budget, positive (negative) [supplementary] | H6: Variance with Final budget % | I6: Significant variance? (GASB 103 note candidate)
A7: Property taxes | B7: =SUMIFS(GF_Budget_Detail!$E$5:$E$295,GF_Budget_Detail!$A$5:$A$295,$J$5,GF_Budget_Detail!$D$5:$D$295,"Property taxes") | C7: =SUMIFS(GF_Budget_Detail!$F$5:$F$295,GF_Budget_Detail!$A$5:$A$295,$J$5,GF_Budget_Detail!$D$5:$D$295,"Property taxes") | D7: =SUMIFS(GF_Budget_Detail!$G$5:$G$295,GF_Budget_Detail!$A$5:$A$295,$J$5,GF_Budget_Detail!$D$5:$D$295,"Property taxes") | E7: =C7-B7 | F7: =(D7-C7) | G7: =(D7-B7) | H7: =IFERROR(F7/ABS(C7),0) | I7: =IF(AND(ABS(F7)>=$L$2,ABS(H7)>=$L$3),"Explain","")
A8: Taxes other than property | B8: =SUMIFS(GF_Budget_Detail!$E$5:$E$295,GF_Budget_Detail!$A$5:$A$295,$J$5,GF_Budget_Detail!$D$5:$D$295,"Taxes other than property") | C8: =SUMIFS(GF_Budget_Detail!$F$5:$F$295,GF_Budget_Detail!$A$5:$A$295,$J$5,GF_Budget_Detail!$D$5:$D$295,"Taxes other than property") | D8: =SUMIFS(GF_Budget_Detail!$G$5:$G$295,GF_Budget_Detail!$A$5:$A$295,$J$5,GF_Budget_Detail!$D$5:$D$295,"Taxes other than property") | E8: =C8-B8 | F8: =(D8-C8) | G8: =(D8-B8) | H8: =IFERROR(F8/ABS(C8),0) | I8: =IF(AND(ABS(F8)>=$L$2,ABS(H8)>=$L$3),"Explain","")
A9: Taxes and assessments (combined) | B9: =SUMIFS(GF_Budget_Detail!$E$5:$E$295,GF_Budget_Detail!$A$5:$A$295,$J$5,GF_Budget_Detail!$D$5:$D$295,"Taxes and assessments (combined)") | C9: =SUMIFS(GF_Budget_Detail!$F$5:$F$295,GF_Budget_Detail!$A$5:$A$295,$J$5,GF_Budget_Detail!$D$5:$D$295,"Taxes and assessments (combined)") | D9: =SUMIFS(GF_Budget_Detail!$G$5:$G$295,GF_Budget_Detail!$A$5:$A$295,$J$5,GF_Budget_Detail!$D$5:$D$295,"Taxes and assessments (combined)") | E9: =C9-B9 | F9: =(D9-C9) | G9: =(D9-B9) | H9: =IFERROR(F9/ABS(C9),0) | I9: =IF(AND(ABS(F9)>=$L$2,ABS(H9)>=$L$3),"Explain","")
A10: Licenses and permits | B10: =SUMIFS(GF_Budget_Detail!$E$5:$E$295,GF_Budget_Detail!$A$5:$A$295,$J$5,GF_Budget_Detail!$D$5:$D$295,"Licenses and permits") | C10: =SUMIFS(GF_Budget_Detail!$F$5:$F$295,GF_Budget_Detail!$A$5:$A$295,$J$5,GF_Budget_Detail!$D$5:$D$295,"Licenses and permits") | D10: =SUMIFS(GF_Budget_Detail!$G$5:$G$295,GF_Budget_Detail!$A$5:$A$295,$J$5,GF_Budget_Detail!$D$5:$D$295,"Licenses and permits") | E10: =C10-B10 | F10: =(D10-C10) | G10: =(D10-B10) | H10: =IFERROR(F10/ABS(C10),0) | I10: =IF(AND(ABS(F10)>=$L$2,ABS(H10)>=$L$3),"Explain","")
A11: Fines and forfeitures | B11: =SUMIFS(GF_Budget_Detail!$E$5:$E$295,GF_Budget_Detail!$A$5:$A$295,$J$5,GF_Budget_Detail!$D$5:$D$295,"Fines and forfeitures") | C11: =SUMIFS(GF_Budget_Detail!$F$5:$F$295,GF_Budget_Detail!$A$5:$A$295,$J$5,GF_Budget_Detail!$D$5:$D$295,"Fines and forfeitures") | D11: =SUMIFS(GF_Budget_Detail!$G$5:$G$295,GF_Budget_Detail!$A$5:$A$295,$J$5,GF_Budget_Detail!$D$5:$D$295,"Fines and forfeitures") | E11: =C11-B11 | F11: =(D11-C11) | G11: =(D11-B11) | H11: =IFERROR(F11/ABS(C11),0) | I11: =IF(AND(ABS(F11)>=$L$2,ABS(H11)>=$L$3),"Explain","")
A12: Use of money and property | B12: =SUMIFS(GF_Budget_Detail!$E$5:$E$295,GF_Budget_Detail!$A$5:$A$295,$J$5,GF_Budget_Detail!$D$5:$D$295,"Use of money and property") | C12: =SUMIFS(GF_Budget_Detail!$F$5:$F$295,GF_Budget_Detail!$A$5:$A$295,$J$5,GF_Budget_Detail!$D$5:$D$295,"Use of money and property") | D12: =SUMIFS(GF_Budget_Detail!$G$5:$G$295,GF_Budget_Detail!$A$5:$A$295,$J$5,GF_Budget_Detail!$D$5:$D$295,"Use of money and property") | E12: =C12-B12 | F12: =(D12-C12) | G12: =(D12-B12) | H12: =IFERROR(F12/ABS(C12),0) | I12: =IF(AND(ABS(F12)>=$L$2,ABS(H12)>=$L$3),"Explain","")
A13: Intergovernmental | B13: =SUMIFS(GF_Budget_Detail!$E$5:$E$295,GF_Budget_Detail!$A$5:$A$295,$J$5,GF_Budget_Detail!$D$5:$D$295,"Intergovernmental") | C13: =SUMIFS(GF_Budget_Detail!$F$5:$F$295,GF_Budget_Detail!$A$5:$A$295,$J$5,GF_Budget_Detail!$D$5:$D$295,"Intergovernmental") | D13: =SUMIFS(GF_Budget_Detail!$G$5:$G$295,GF_Budget_Detail!$A$5:$A$295,$J$5,GF_Budget_Detail!$D$5:$D$295,"Intergovernmental") | E13: =C13-B13 | F13: =(D13-C13) | G13: =(D13-B13) | H13: =IFERROR(F13/ABS(C13),0) | I13: =IF(AND(ABS(F13)>=$L$2,ABS(H13)>=$L$3),"Explain","")
A14: Charges for services | B14: =SUMIFS(GF_Budget_Detail!$E$5:$E$295,GF_Budget_Detail!$A$5:$A$295,$J$5,GF_Budget_Detail!$D$5:$D$295,"Charges for services") | C14: =SUMIFS(GF_Budget_Detail!$F$5:$F$295,GF_Budget_Detail!$A$5:$A$295,$J$5,GF_Budget_Detail!$D$5:$D$295,"Charges for services") | D14: =SUMIFS(GF_Budget_Detail!$G$5:$G$295,GF_Budget_Detail!$A$5:$A$295,$J$5,GF_Budget_Detail!$D$5:$D$295,"Charges for services") | E14: =C14-B14 | F14: =(D14-C14) | G14: =(D14-B14) | H14: =IFERROR(F14/ABS(C14),0) | I14: =IF(AND(ABS(F14)>=$L$2,ABS(H14)>=$L$3),"Explain","")
A15: Other revenues | B15: =SUMIFS(GF_Budget_Detail!$E$5:$E$295,GF_Budget_Detail!$A$5:$A$295,$J$5,GF_Budget_Detail!$D$5:$D$295,"Other revenues") | C15: =SUMIFS(GF_Budget_Detail!$F$5:$F$295,GF_Budget_Detail!$A$5:$A$295,$J$5,GF_Budget_Detail!$D$5:$D$295,"Other revenues") | D15: =SUMIFS(GF_Budget_Detail!$G$5:$G$295,GF_Budget_Detail!$A$5:$A$295,$J$5,GF_Budget_Detail!$D$5:$D$295,"Other revenues") | E15: =C15-B15 | F15: =(D15-C15) | G15: =(D15-B15) | H15: =IFERROR(F15/ABS(C15),0) | I15: =IF(AND(ABS(F15)>=$L$2,ABS(H15)>=$L$3),"Explain","")
A16: Total revenues | B16: =SUM(B7:B15) | C16: =SUM(C7:C15) | D16: =SUM(D7:D15) | E16: =C16-B16 | F16: =(D16-C16) | G16: =(D16-B16) | H16: =IFERROR(F16/ABS(C16),0) | I16: =IF(AND(ABS(F16)>=$L$2,ABS(H16)>=$L$3),"Explain","")
A18: General government | B18: =SUMIFS(GF_Budget_Detail!$E$5:$E$295,GF_Budget_Detail!$A$5:$A$295,$J$5,GF_Budget_Detail!$D$5:$D$295,"General government") | C18: =SUMIFS(GF_Budget_Detail!$F$5:$F$295,GF_Budget_Detail!$A$5:$A$295,$J$5,GF_Budget_Detail!$D$5:$D$295,"General government") | D18: =SUMIFS(GF_Budget_Detail!$G$5:$G$295,GF_Budget_Detail!$A$5:$A$295,$J$5,GF_Budget_Detail!$D$5:$D$295,"General government") | E18: =C18-B18 | F18: =-(D18-C18) | G18: =-(D18-B18) | H18: =IFERROR(F18/ABS(C18),0) | I18: =IF(AND(ABS(F18)>=$L$2,ABS(H18)>=$L$3),"Explain","")
A19: Public works | B19: =SUMIFS(GF_Budget_Detail!$E$5:$E$295,GF_Budget_Detail!$A$5:$A$295,$J$5,GF_Budget_Detail!$D$5:$D$295,"Public works") | C19: =SUMIFS(GF_Budget_Detail!$F$5:$F$295,GF_Budget_Detail!$A$5:$A$295,$J$5,GF_Budget_Detail!$D$5:$D$295,"Public works") | D19: =SUMIFS(GF_Budget_Detail!$G$5:$G$295,GF_Budget_Detail!$A$5:$A$295,$J$5,GF_Budget_Detail!$D$5:$D$295,"Public works") | E19: =C19-B19 | F19: =-(D19-C19) | G19: =-(D19-B19) | H19: =IFERROR(F19/ABS(C19),0) | I19: =IF(AND(ABS(F19)>=$L$2,ABS(H19)>=$L$3),"Explain","")
A20: Recreation | B20: =SUMIFS(GF_Budget_Detail!$E$5:$E$295,GF_Budget_Detail!$A$5:$A$295,$J$5,GF_Budget_Detail!$D$5:$D$295,"Recreation") | C20: =SUMIFS(GF_Budget_Detail!$F$5:$F$295,GF_Budget_Detail!$A$5:$A$295,$J$5,GF_Budget_Detail!$D$5:$D$295,"Recreation") | D20: =SUMIFS(GF_Budget_Detail!$G$5:$G$295,GF_Budget_Detail!$A$5:$A$295,$J$5,GF_Budget_Detail!$D$5:$D$295,"Recreation") | E20: =C20-B20 | F20: =-(D20-C20) | G20: =-(D20-B20) | H20: =IFERROR(F20/ABS(C20),0) | I20: =IF(AND(ABS(F20)>=$L$2,ABS(H20)>=$L$3),"Explain","")
A21: Community development | B21: =SUMIFS(GF_Budget_Detail!$E$5:$E$295,GF_Budget_Detail!$A$5:$A$295,$J$5,GF_Budget_Detail!$D$5:$D$295,"Community development") | C21: =SUMIFS(GF_Budget_Detail!$F$5:$F$295,GF_Budget_Detail!$A$5:$A$295,$J$5,GF_Budget_Detail!$D$5:$D$295,"Community development") | D21: =SUMIFS(GF_Budget_Detail!$G$5:$G$295,GF_Budget_Detail!$A$5:$A$295,$J$5,GF_Budget_Detail!$D$5:$D$295,"Community development") | E21: =C21-B21 | F21: =-(D21-C21) | G21: =-(D21-B21) | H21: =IFERROR(F21/ABS(C21),0) | I21: =IF(AND(ABS(F21)>=$L$2,ABS(H21)>=$L$3),"Explain","")
A22: Public safety - Police | B22: =SUMIFS(GF_Budget_Detail!$E$5:$E$295,GF_Budget_Detail!$A$5:$A$295,$J$5,GF_Budget_Detail!$D$5:$D$295,"Public safety - Police") | C22: =SUMIFS(GF_Budget_Detail!$F$5:$F$295,GF_Budget_Detail!$A$5:$A$295,$J$5,GF_Budget_Detail!$D$5:$D$295,"Public safety - Police") | D22: =SUMIFS(GF_Budget_Detail!$G$5:$G$295,GF_Budget_Detail!$A$5:$A$295,$J$5,GF_Budget_Detail!$D$5:$D$295,"Public safety - Police") | E22: =C22-B22 | F22: =-(D22-C22) | G22: =-(D22-B22) | H22: =IFERROR(F22/ABS(C22),0) | I22: =IF(AND(ABS(F22)>=$L$2,ABS(H22)>=$L$3),"Explain","")
A23: Public safety - Fire | B23: =SUMIFS(GF_Budget_Detail!$E$5:$E$295,GF_Budget_Detail!$A$5:$A$295,$J$5,GF_Budget_Detail!$D$5:$D$295,"Public safety - Fire") | C23: =SUMIFS(GF_Budget_Detail!$F$5:$F$295,GF_Budget_Detail!$A$5:$A$295,$J$5,GF_Budget_Detail!$D$5:$D$295,"Public safety - Fire") | D23: =SUMIFS(GF_Budget_Detail!$G$5:$G$295,GF_Budget_Detail!$A$5:$A$295,$J$5,GF_Budget_Detail!$D$5:$D$295,"Public safety - Fire") | E23: =C23-B23 | F23: =-(D23-C23) | G23: =-(D23-B23) | H23: =IFERROR(F23/ABS(C23),0) | I23: =IF(AND(ABS(F23)>=$L$2,ABS(H23)>=$L$3),"Explain","")
A24: Public safety (combined) | B24: =SUMIFS(GF_Budget_Detail!$E$5:$E$295,GF_Budget_Detail!$A$5:$A$295,$J$5,GF_Budget_Detail!$D$5:$D$295,"Public safety (combined)") | C24: =SUMIFS(GF_Budget_Detail!$F$5:$F$295,GF_Budget_Detail!$A$5:$A$295,$J$5,GF_Budget_Detail!$D$5:$D$295,"Public safety (combined)") | D24: =SUMIFS(GF_Budget_Detail!$G$5:$G$295,GF_Budget_Detail!$A$5:$A$295,$J$5,GF_Budget_Detail!$D$5:$D$295,"Public safety (combined)") | E24: =C24-B24 | F24: =-(D24-C24) | G24: =-(D24-B24) | H24: =IFERROR(F24/ABS(C24),0) | I24: =IF(AND(ABS(F24)>=$L$2,ABS(H24)>=$L$3),"Explain","")
A25: Payment of sales tax to City of Richmond | B25: =SUMIFS(GF_Budget_Detail!$E$5:$E$295,GF_Budget_Detail!$A$5:$A$295,$J$5,GF_Budget_Detail!$D$5:$D$295,"Payment of sales tax to City of Richmond") | C25: =SUMIFS(GF_Budget_Detail!$F$5:$F$295,GF_Budget_Detail!$A$5:$A$295,$J$5,GF_Budget_Detail!$D$5:$D$295,"Payment of sales tax to City of Richmond") | D25: =SUMIFS(GF_Budget_Detail!$G$5:$G$295,GF_Budget_Detail!$A$5:$A$295,$J$5,GF_Budget_Detail!$D$5:$D$295,"Payment of sales tax to City of Richmond") | E25: =C25-B25 | F25: =-(D25-C25) | G25: =-(D25-B25) | H25: =IFERROR(F25/ABS(C25),0) | I25: =IF(AND(ABS(F25)>=$L$2,ABS(H25)>=$L$3),"Explain","")
A26: Capital outlay | B26: =SUMIFS(GF_Budget_Detail!$E$5:$E$295,GF_Budget_Detail!$A$5:$A$295,$J$5,GF_Budget_Detail!$D$5:$D$295,"Capital outlay") | C26: =SUMIFS(GF_Budget_Detail!$F$5:$F$295,GF_Budget_Detail!$A$5:$A$295,$J$5,GF_Budget_Detail!$D$5:$D$295,"Capital outlay") | D26: =SUMIFS(GF_Budget_Detail!$G$5:$G$295,GF_Budget_Detail!$A$5:$A$295,$J$5,GF_Budget_Detail!$D$5:$D$295,"Capital outlay") | E26: =C26-B26 | F26: =-(D26-C26) | G26: =-(D26-B26) | H26: =IFERROR(F26/ABS(C26),0) | I26: =IF(AND(ABS(F26)>=$L$2,ABS(H26)>=$L$3),"Explain","")
A27: Debt service - principal | B27: =SUMIFS(GF_Budget_Detail!$E$5:$E$295,GF_Budget_Detail!$A$5:$A$295,$J$5,GF_Budget_Detail!$D$5:$D$295,"Debt service - principal") | C27: =SUMIFS(GF_Budget_Detail!$F$5:$F$295,GF_Budget_Detail!$A$5:$A$295,$J$5,GF_Budget_Detail!$D$5:$D$295,"Debt service - principal") | D27: =SUMIFS(GF_Budget_Detail!$G$5:$G$295,GF_Budget_Detail!$A$5:$A$295,$J$5,GF_Budget_Detail!$D$5:$D$295,"Debt service - principal") | E27: =C27-B27 | F27: =-(D27-C27) | G27: =-(D27-B27) | H27: =IFERROR(F27/ABS(C27),0) | I27: =IF(AND(ABS(F27)>=$L$2,ABS(H27)>=$L$3),"Explain","")
A28: Debt service - interest | B28: =SUMIFS(GF_Budget_Detail!$E$5:$E$295,GF_Budget_Detail!$A$5:$A$295,$J$5,GF_Budget_Detail!$D$5:$D$295,"Debt service - interest") | C28: =SUMIFS(GF_Budget_Detail!$F$5:$F$295,GF_Budget_Detail!$A$5:$A$295,$J$5,GF_Budget_Detail!$D$5:$D$295,"Debt service - interest") | D28: =SUMIFS(GF_Budget_Detail!$G$5:$G$295,GF_Budget_Detail!$A$5:$A$295,$J$5,GF_Budget_Detail!$D$5:$D$295,"Debt service - interest") | E28: =C28-B28 | F28: =-(D28-C28) | G28: =-(D28-B28) | H28: =IFERROR(F28/ABS(C28),0) | I28: =IF(AND(ABS(F28)>=$L$2,ABS(H28)>=$L$3),"Explain","")
A29: Non-departmental (budget-report basis) | B29: =SUMIFS(GF_Budget_Detail!$E$5:$E$295,GF_Budget_Detail!$A$5:$A$295,$J$5,GF_Budget_Detail!$D$5:$D$295,"Non-departmental (budget-report basis)") | C29: =SUMIFS(GF_Budget_Detail!$F$5:$F$295,GF_Budget_Detail!$A$5:$A$295,$J$5,GF_Budget_Detail!$D$5:$D$295,"Non-departmental (budget-report basis)") | D29: =SUMIFS(GF_Budget_Detail!$G$5:$G$295,GF_Budget_Detail!$A$5:$A$295,$J$5,GF_Budget_Detail!$D$5:$D$295,"Non-departmental (budget-report basis)") | E29: =C29-B29 | F29: =-(D29-C29) | G29: =-(D29-B29) | H29: =IFERROR(F29/ABS(C29),0) | I29: =IF(AND(ABS(F29)>=$L$2,ABS(H29)>=$L$3),"Explain","")
A30: Original budget not itemized by department | B30: =SUMIFS(GF_Budget_Detail!$E$5:$E$295,GF_Budget_Detail!$A$5:$A$295,$J$5,GF_Budget_Detail!$D$5:$D$295,"Original budget not itemized by department") | C30: =SUMIFS(GF_Budget_Detail!$F$5:$F$295,GF_Budget_Detail!$A$5:$A$295,$J$5,GF_Budget_Detail!$D$5:$D$295,"Original budget not itemized by department") | D30: =SUMIFS(GF_Budget_Detail!$G$5:$G$295,GF_Budget_Detail!$A$5:$A$295,$J$5,GF_Budget_Detail!$D$5:$D$295,"Original budget not itemized by department") | E30: =C30-B30 | F30: =-(D30-C30) | G30: =-(D30-B30) | H30: =IFERROR(F30/ABS(C30),0) | I30: =IF(AND(ABS(F30)>=$L$2,ABS(H30)>=$L$3),"Explain","")
A31: Total expenditures | B31: =SUM(B18:B30) | C31: =SUM(C18:C30) | D31: =SUM(D18:D30) | E31: =C31-B31 | F31: =-(D31-C31) | G31: =-(D31-B31) | H31: =IFERROR(F31/ABS(C31),0) | I31: =IF(AND(ABS(F31)>=$L$2,ABS(H31)>=$L$3),"Explain","")
A33: Transfers in | B33: =SUMIFS(GF_Budget_Detail!$E$5:$E$295,GF_Budget_Detail!$A$5:$A$295,$J$5,GF_Budget_Detail!$D$5:$D$295,"Transfers in") | C33: =SUMIFS(GF_Budget_Detail!$F$5:$F$295,GF_Budget_Detail!$A$5:$A$295,$J$5,GF_Budget_Detail!$D$5:$D$295,"Transfers in") | D33: =SUMIFS(GF_Budget_Detail!$G$5:$G$295,GF_Budget_Detail!$A$5:$A$295,$J$5,GF_Budget_Detail!$D$5:$D$295,"Transfers in") | E33: =C33-B33 | F33: =(D33-C33) | G33: =(D33-B33) | H33: =IFERROR(F33/ABS(C33),0) | I33: =IF(AND(ABS(F33)>=$L$2,ABS(H33)>=$L$3),"Explain","")
A34: Transfers out | B34: =SUMIFS(GF_Budget_Detail!$E$5:$E$295,GF_Budget_Detail!$A$5:$A$295,$J$5,GF_Budget_Detail!$D$5:$D$295,"Transfers out") | C34: =SUMIFS(GF_Budget_Detail!$F$5:$F$295,GF_Budget_Detail!$A$5:$A$295,$J$5,GF_Budget_Detail!$D$5:$D$295,"Transfers out") | D34: =SUMIFS(GF_Budget_Detail!$G$5:$G$295,GF_Budget_Detail!$A$5:$A$295,$J$5,GF_Budget_Detail!$D$5:$D$295,"Transfers out") | E34: =C34-B34 | F34: =(D34-C34) | G34: =(D34-B34) | H34: =IFERROR(F34/ABS(C34),0) | I34: =IF(AND(ABS(F34)>=$L$2,ABS(H34)>=$L$3),"Explain","")
A35: Debt / lease financing proceeds | B35: =SUMIFS(GF_Budget_Detail!$E$5:$E$295,GF_Budget_Detail!$A$5:$A$295,$J$5,GF_Budget_Detail!$D$5:$D$295,"Debt / lease financing proceeds") | C35: =SUMIFS(GF_Budget_Detail!$F$5:$F$295,GF_Budget_Detail!$A$5:$A$295,$J$5,GF_Budget_Detail!$D$5:$D$295,"Debt / lease financing proceeds") | D35: =SUMIFS(GF_Budget_Detail!$G$5:$G$295,GF_Budget_Detail!$A$5:$A$295,$J$5,GF_Budget_Detail!$D$5:$D$295,"Debt / lease financing proceeds") | E35: =C35-B35 | F35: =(D35-C35) | G35: =(D35-B35) | H35: =IFERROR(F35/ABS(C35),0) | I35: =IF(AND(ABS(F35)>=$L$2,ABS(H35)>=$L$3),"Explain","")
A36: Proceeds from sale of capital assets | B36: =SUMIFS(GF_Budget_Detail!$E$5:$E$295,GF_Budget_Detail!$A$5:$A$295,$J$5,GF_Budget_Detail!$D$5:$D$295,"Proceeds from sale of capital assets") | C36: =SUMIFS(GF_Budget_Detail!$F$5:$F$295,GF_Budget_Detail!$A$5:$A$295,$J$5,GF_Budget_Detail!$D$5:$D$295,"Proceeds from sale of capital assets") | D36: =SUMIFS(GF_Budget_Detail!$G$5:$G$295,GF_Budget_Detail!$A$5:$A$295,$J$5,GF_Budget_Detail!$D$5:$D$295,"Proceeds from sale of capital assets") | E36: =C36-B36 | F36: =(D36-C36) | G36: =(D36-B36) | H36: =IFERROR(F36/ABS(C36),0) | I36: =IF(AND(ABS(F36)>=$L$2,ABS(H36)>=$L$3),"Explain","")
A37: Special items | B37: =SUMIFS(GF_Budget_Detail!$E$5:$E$295,GF_Budget_Detail!$A$5:$A$295,$J$5,GF_Budget_Detail!$D$5:$D$295,"Special items") | C37: =SUMIFS(GF_Budget_Detail!$F$5:$F$295,GF_Budget_Detail!$A$5:$A$295,$J$5,GF_Budget_Detail!$D$5:$D$295,"Special items") | D37: =SUMIFS(GF_Budget_Detail!$G$5:$G$295,GF_Budget_Detail!$A$5:$A$295,$J$5,GF_Budget_Detail!$D$5:$D$295,"Special items") | E37: =C37-B37 | F37: =(D37-C37) | G37: =(D37-B37) | H37: =IFERROR(F37/ABS(C37),0) | I37: =IF(AND(ABS(F37)>=$L$2,ABS(H37)>=$L$3),"Explain","")
A38: Total other financing sources (uses) and special items | B38: =SUM(B33:B37) | C38: =SUM(C33:C37) | D38: =SUM(D33:D37) | E38: =C38-B38 | F38: =(D38-C38) | G38: =(D38-B38) | H38: =IFERROR(F38/ABS(C38),0) | I38: =IF(AND(ABS(F38)>=$L$2,ABS(H38)>=$L$3),"Explain","")
A40: Net change in fund balance | B40: =B16-B31+B38 | C40: =C16-C31+C38 | D40: =D16-D31+D38 | E40: =C40-B40 | F40: =D40-C40 | G40: =D40-B40
A43: FY2014-15 (year ended June 30, 2015) - Budgetary comparison schedule, General Fund - GAAP (modified accrual) budgetary basis | J43: 2015
A44: Category | B44: Budgeted amounts - Original | C44: Budgeted amounts - Final | D44: Actual amounts (budgetary basis) | E44: Variance: Original to Final budget, increase (decrease) | F44: Variance with Final budget, positive (negative) | G44: Variance with Original budget, positive (negative) [supplementary] | H44: Variance with Final budget % | I44: Significant variance? (GASB 103 note candidate)
A45: Property taxes | B45: =SUMIFS(GF_Budget_Detail!$E$5:$E$295,GF_Budget_Detail!$A$5:$A$295,$J$43,GF_Budget_Detail!$D$5:$D$295,"Property taxes") | C45: =SUMIFS(GF_Budget_Detail!$F$5:$F$295,GF_Budget_Detail!$A$5:$A$295,$J$43,GF_Budget_Detail!$D$5:$D$295,"Property taxes") | D45: =SUMIFS(GF_Budget_Detail!$G$5:$G$295,GF_Budget_Detail!$A$5:$A$295,$J$43,GF_Budget_Detail!$D$5:$D$295,"Property taxes") | E45: =C45-B45 | F45: =(D45-C45) | G45: =(D45-B45) | H45: =IFERROR(F45/ABS(C45),0) | I45: =IF(AND(ABS(F45)>=$L$2,ABS(H45)>=$L$3),"Explain","")
A46: Taxes other than property | B46: =SUMIFS(GF_Budget_Detail!$E$5:$E$295,GF_Budget_Detail!$A$5:$A$295,$J$43,GF_Budget_Detail!$D$5:$D$295,"Taxes other than property") | C46: =SUMIFS(GF_Budget_Detail!$F$5:$F$295,GF_Budget_Detail!$A$5:$A$295,$J$43,GF_Budget_Detail!$D$5:$D$295,"Taxes other than property") | D46: =SUMIFS(GF_Budget_Detail!$G$5:$G$295,GF_Budget_Detail!$A$5:$A$295,$J$43,GF_Budget_Detail!$D$5:$D$295,"Taxes other than property") | E46: =C46-B46 | F46: =(D46-C46) | G46: =(D46-B46) | H46: =IFERROR(F46/ABS(C46),0) | I46: =IF(AND(ABS(F46)>=$L$2,ABS(H46)>=$L$3),"Explain","")
A47: Taxes and assessments (combined) | B47: =SUMIFS(GF_Budget_Detail!$E$5:$E$295,GF_Budget_Detail!$A$5:$A$295,$J$43,GF_Budget_Detail!$D$5:$D$295,"Taxes and assessments (combined)") | C47: =SUMIFS(GF_Budget_Detail!$F$5:$F$295,GF_Budget_Detail!$A$5:$A$295,$J$43,GF_Budget_Detail!$D$5:$D$295,"Taxes and assessments (combined)") | D47: =SUMIFS(GF_Budget_Detail!$G$5:$G$295,GF_Budget_Detail!$A$5:$A$295,$J$43,GF_Budget_Detail!$D$5:$D$295,"Taxes and assessments (combined)") | E47: =C47-B47 | F47: =(D47-C47) | G47: =(D47-B47) | H47: =IFERROR(F47/ABS(C47),0) | I47: =IF(AND(ABS(F47)>=$L$2,ABS(H47)>=$L$3),"Explain","")
A48: Licenses and permits | B48: =SUMIFS(GF_Budget_Detail!$E$5:$E$295,GF_Budget_Detail!$A$5:$A$295,$J$43,GF_Budget_Detail!$D$5:$D$295,"Licenses and permits") | C48: =SUMIFS(GF_Budget_Detail!$F$5:$F$295,GF_Budget_Detail!$A$5:$A$295,$J$43,GF_Budget_Detail!$D$5:$D$295,"Licenses and permits") | D48: =SUMIFS(GF_Budget_Detail!$G$5:$G$295,GF_Budget_Detail!$A$5:$A$295,$J$43,GF_Budget_Detail!$D$5:$D$295,"Licenses and permits") | E48: =C48-B48 | F48: =(D48-C48) | G48: =(D48-B48) | H48: =IFERROR(F48/ABS(C48),0) | I48: =IF(AND(ABS(F48)>=$L$2,ABS(H48)>=$L$3),"Explain","")
A49: Fines and forfeitures | B49: =SUMIFS(GF_Budget_Detail!$E$5:$E$295,GF_Budget_Detail!$A$5:$A$295,$J$43,GF_Budget_Detail!$D$5:$D$295,"Fines and forfeitures") | C49: =SUMIFS(GF_Budget_Detail!$F$5:$F$295,GF_Budget_Detail!$A$5:$A$295,$J$43,GF_Budget_Detail!$D$5:$D$295,"Fines and forfeitures") | D49: =SUMIFS(GF_Budget_Detail!$G$5:$G$295,GF_Budget_Detail!$A$5:$A$295,$J$43,GF_Budget_Detail!$D$5:$D$295,"Fines and forfeitures") | E49: =C49-B49 | F49: =(D49-C49) | G49: =(D49-B49) | H49: =IFERROR(F49/ABS(C49),0) | I49: =IF(AND(ABS(F49)>=$L$2,ABS(H49)>=$L$3),"Explain","")
A50: Use of money and property | B50: =SUMIFS(GF_Budget_Detail!$E$5:$E$295,GF_Budget_Detail!$A$5:$A$295,$J$43,GF_Budget_Detail!$D$5:$D$295,"Use of money and property") | C50: =SUMIFS(GF_Budget_Detail!$F$5:$F$295,GF_Budget_Detail!$A$5:$A$295,$J$43,GF_Budget_Detail!$D$5:$D$295,"Use of money and property") | D50: =SUMIFS(GF_Budget_Detail!$G$5:$G$295,GF_Budget_Detail!$A$5:$A$295,$J$43,GF_Budget_Detail!$D$5:$D$295,"Use of money and property") | E50: =C50-B50 | F50: =(D50-C50) | G50: =(D50-B50) | H50: =IFERROR(F50/ABS(C50),0) | I50: =IF(AND(ABS(F50)>=$L$2,ABS(H50)>=$L$3),"Explain","")
A51: Intergovernmental | B51: =SUMIFS(GF_Budget_Detail!$E$5:$E$295,GF_Budget_Detail!$A$5:$A$295,$J$43,GF_Budget_Detail!$D$5:$D$295,"Intergovernmental") | C51: =SUMIFS(GF_Budget_Detail!$F$5:$F$295,GF_Budget_Detail!$A$5:$A$295,$J$43,GF_Budget_Detail!$D$5:$D$295,"Intergovernmental") | D51: =SUMIFS(GF_Budget_Detail!$G$5:$G$295,GF_Budget_Detail!$A$5:$A$295,$J$43,GF_Budget_Detail!$D$5:$D$295,"Intergovernmental") | E51: =C51-B51 | F51: =(D51-C51) | G51: =(D51-B51) | H51: =IFERROR(F51/ABS(C51),0) | I51: =IF(AND(ABS(F51)>=$L$2,ABS(H51)>=$L$3),"Explain","")
A52: Charges for services | B52: =SUMIFS(GF_Budget_Detail!$E$5:$E$295,GF_Budget_Detail!$A$5:$A$295,$J$43,GF_Budget_Detail!$D$5:$D$295,"Charges for services") | C52: =SUMIFS(GF_Budget_Detail!$F$5:$F$295,GF_Budget_Detail!$A$5:$A$295,$J$43,GF_Budget_Detail!$D$5:$D$295,"Charges for services") | D52: =SUMIFS(GF_Budget_Detail!$G$5:$G$295,GF_Budget_Detail!$A$5:$A$295,$J$43,GF_Budget_Detail!$D$5:$D$295,"Charges for services") | E52: =C52-B52 | F52: =(D52-C52) | G52: =(D52-B52) | H52: =IFERROR(F52/ABS(C52),0) | I52: =IF(AND(ABS(F52)>=$L$2,ABS(H52)>=$L$3),"Explain","")
A53: Other revenues | B53: =SUMIFS(GF_Budget_Detail!$E$5:$E$295,GF_Budget_Detail!$A$5:$A$295,$J$43,GF_Budget_Detail!$D$5:$D$295,"Other revenues") | C53: =SUMIFS(GF_Budget_Detail!$F$5:$F$295,GF_Budget_Detail!$A$5:$A$295,$J$43,GF_Budget_Detail!$D$5:$D$295,"Other revenues") | D53: =SUMIFS(GF_Budget_Detail!$G$5:$G$295,GF_Budget_Detail!$A$5:$A$295,$J$43,GF_Budget_Detail!$D$5:$D$295,"Other revenues") | E53: =C53-B53 | F53: =(D53-C53) | G53: =(D53-B53) | H53: =IFERROR(F53/ABS(C53),0) | I53: =IF(AND(ABS(F53)>=$L$2,ABS(H53)>=$L$3),"Explain","")
A54: Total revenues | B54: =SUM(B45:B53) | C54: =SUM(C45:C53) | D54: =SUM(D45:D53) | E54: =C54-B54 | F54: =(D54-C54) | G54: =(D54-B54) | H54: =IFERROR(F54/ABS(C54),0) | I54: =IF(AND(ABS(F54)>=$L$2,ABS(H54)>=$L$3),"Explain","")
A56: General government | B56: =SUMIFS(GF_Budget_Detail!$E$5:$E$295,GF_Budget_Detail!$A$5:$A$295,$J$43,GF_Budget_Detail!$D$5:$D$295,"General government") | C56: =SUMIFS(GF_Budget_Detail!$F$5:$F$295,GF_Budget_Detail!$A$5:$A$295,$J$43,GF_Budget_Detail!$D$5:$D$295,"General government") | D56: =SUMIFS(GF_Budget_Detail!$G$5:$G$295,GF_Budget_Detail!$A$5:$A$295,$J$43,GF_Budget_Detail!$D$5:$D$295,"General government") | E56: =C56-B56 | F56: =-(D56-C56) | G56: =-(D56-B56) | H56: =IFERROR(F56/ABS(C56),0) | I56: =IF(AND(ABS(F56)>=$L$2,ABS(H56)>=$L$3),"Explain","")
A57: Public works | B57: =SUMIFS(GF_Budget_Detail!$E$5:$E$295,GF_Budget_Detail!$A$5:$A$295,$J$43,GF_Budget_Detail!$D$5:$D$295,"Public works") | C57: =SUMIFS(GF_Budget_Detail!$F$5:$F$295,GF_Budget_Detail!$A$5:$A$295,$J$43,GF_Budget_Detail!$D$5:$D$295,"Public works") | D57: =SUMIFS(GF_Budget_Detail!$G$5:$G$295,GF_Budget_Detail!$A$5:$A$295,$J$43,GF_Budget_Detail!$D$5:$D$295,"Public works") | E57: =C57-B57 | F57: =-(D57-C57) | G57: =-(D57-B57) | H57: =IFERROR(F57/ABS(C57),0) | I57: =IF(AND(ABS(F57)>=$L$2,ABS(H57)>=$L$3),"Explain","")
A58: Recreation | B58: =SUMIFS(GF_Budget_Detail!$E$5:$E$295,GF_Budget_Detail!$A$5:$A$295,$J$43,GF_Budget_Detail!$D$5:$D$295,"Recreation") | C58: =SUMIFS(GF_Budget_Detail!$F$5:$F$295,GF_Budget_Detail!$A$5:$A$295,$J$43,GF_Budget_Detail!$D$5:$D$295,"Recreation") | D58: =SUMIFS(GF_Budget_Detail!$G$5:$G$295,GF_Budget_Detail!$A$5:$A$295,$J$43,GF_Budget_Detail!$D$5:$D$295,"Recreation") | E58: =C58-B58 | F58: =-(D58-C58) | G58: =-(D58-B58) | H58: =IFERROR(F58/ABS(C58),0) | I58: =IF(AND(ABS(F58)>=$L$2,ABS(H58)>=$L$3),"Explain","")
A59: Community development | B59: =SUMIFS(GF_Budget_Detail!$E$5:$E$295,GF_Budget_Detail!$A$5:$A$295,$J$43,GF_Budget_Detail!$D$5:$D$295,"Community development") | C59: =SUMIFS(GF_Budget_Detail!$F$5:$F$295,GF_Budget_Detail!$A$5:$A$295,$J$43,GF_Budget_Detail!$D$5:$D$295,"Community development") | D59: =SUMIFS(GF_Budget_Detail!$G$5:$G$295,GF_Budget_Detail!$A$5:$A$295,$J$43,GF_Budget_Detail!$D$5:$D$295,"Community development") | E59: =C59-B59 | F59: =-(D59-C59) | G59: =-(D59-B59) | H59: =IFERROR(F59/ABS(C59),0) | I59: =IF(AND(ABS(F59)>=$L$2,ABS(H59)>=$L$3),"Explain","")
A60: Public safety - Police | B60: =SUMIFS(GF_Budget_Detail!$E$5:$E$295,GF_Budget_Detail!$A$5:$A$295,$J$43,GF_Budget_Detail!$D$5:$D$295,"Public safety - Police") | C60: =SUMIFS(GF_Budget_Detail!$F$5:$F$295,GF_Budget_Detail!$A$5:$A$295,$J$43,GF_Budget_Detail!$D$5:$D$295,"Public safety - Police") | D60: =SUMIFS(GF_Budget_Detail!$G$5:$G$295,GF_Budget_Detail!$A$5:$A$295,$J$43,GF_Budget_Detail!$D$5:$D$295,"Public safety - Police") | E60: =C60-B60 | F60: =-(D60-C60) | G60: =-(D60-B60) | H60: =IFERROR(F60/ABS(C60),0) | I60: =IF(AND(ABS(F60)>=$L$2,ABS(H60)>=$L$3),"Explain","")
A61: Public safety - Fire | B61: =SUMIFS(GF_Budget_Detail!$E$5:$E$295,GF_Budget_Detail!$A$5:$A$295,$J$43,GF_Budget_Detail!$D$5:$D$295,"Public safety - Fire") | C61: =SUMIFS(GF_Budget_Detail!$F$5:$F$295,GF_Budget_Detail!$A$5:$A$295,$J$43,GF_Budget_Detail!$D$5:$D$295,"Public safety - Fire") | D61: =SUMIFS(GF_Budget_Detail!$G$5:$G$295,GF_Budget_Detail!$A$5:$A$295,$J$43,GF_Budget_Detail!$D$5:$D$295,"Public safety - Fire") | E61: =C61-B61 | F61: =-(D61-C61) | G61: =-(D61-B61) | H61: =IFERROR(F61/ABS(C61),0) | I61: =IF(AND(ABS(F61)>=$L$2,ABS(H61)>=$L$3),"Explain","")
A62: Public safety (combined) | B62: =SUMIFS(GF_Budget_Detail!$E$5:$E$295,GF_Budget_Detail!$A$5:$A$295,$J$43,GF_Budget_Detail!$D$5:$D$295,"Public safety (combined)") | C62: =SUMIFS(GF_Budget_Detail!$F$5:$F$295,GF_Budget_Detail!$A$5:$A$295,$J$43,GF_Budget_Detail!$D$5:$D$295,"Public safety (combined)") | D62: =SUMIFS(GF_Budget_Detail!$G$5:$G$295,GF_Budget_Detail!$A$5:$A$295,$J$43,GF_Budget_Detail!$D$5:$D$295,"Public safety (combined)") | E62: =C62-B62 | F62: =-(D62-C62) | G62: =-(D62-B62) | H62: =IFERROR(F62/ABS(C62),0) | I62: =IF(AND(ABS(F62)>=$L$2,ABS(H62)>=$L$3),"Explain","")
A63: Payment of sales tax to City of Richmond | B63: =SUMIFS(GF_Budget_Detail!$E$5:$E$295,GF_Budget_Detail!$A$5:$A$295,$J$43,GF_Budget_Detail!$D$5:$D$295,"Payment of sales tax to City of Richmond") | C63: =SUMIFS(GF_Budget_Detail!$F$5:$F$295,GF_Budget_Detail!$A$5:$A$295,$J$43,GF_Budget_Detail!$D$5:$D$295,"Payment of sales tax to City of Richmond") | D63: =SUMIFS(GF_Budget_Detail!$G$5:$G$295,GF_Budget_Detail!$A$5:$A$295,$J$43,GF_Budget_Detail!$D$5:$D$295,"Payment of sales tax to City of Richmond") | E63: =C63-B63 | F63: =-(D63-C63) | G63: =-(D63-B63) | H63: =IFERROR(F63/ABS(C63),0) | I63: =IF(AND(ABS(F63)>=$L$2,ABS(H63)>=$L$3),"Explain","")
A64: Capital outlay | B64: =SUMIFS(GF_Budget_Detail!$E$5:$E$295,GF_Budget_Detail!$A$5:$A$295,$J$43,GF_Budget_Detail!$D$5:$D$295,"Capital outlay") | C64: =SUMIFS(GF_Budget_Detail!$F$5:$F$295,GF_Budget_Detail!$A$5:$A$295,$J$43,GF_Budget_Detail!$D$5:$D$295,"Capital outlay") | D64: =SUMIFS(GF_Budget_Detail!$G$5:$G$295,GF_Budget_Detail!$A$5:$A$295,$J$43,GF_Budget_Detail!$D$5:$D$295,"Capital outlay") | E64: =C64-B64 | F64: =-(D64-C64) | G64: =-(D64-B64) | H64: =IFERROR(F64/ABS(C64),0) | I64: =IF(AND(ABS(F64)>=$L$2,ABS(H64)>=$L$3),"Explain","")
A65: Debt service - principal | B65: =SUMIFS(GF_Budget_Detail!$E$5:$E$295,GF_Budget_Detail!$A$5:$A$295,$J$43,GF_Budget_Detail!$D$5:$D$295,"Debt service - principal") | C65: =SUMIFS(GF_Budget_Detail!$F$5:$F$295,GF_Budget_Detail!$A$5:$A$295,$J$43,GF_Budget_Detail!$D$5:$D$295,"Debt service - principal") | D65: =SUMIFS(GF_Budget_Detail!$G$5:$G$295,GF_Budget_Detail!$A$5:$A$295,$J$43,GF_Budget_Detail!$D$5:$D$295,"Debt service - principal") | E65: =C65-B65 | F65: =-(D65-C65) | G65: =-(D65-B65) | H65: =IFERROR(F65/ABS(C65),0) | I65: =IF(AND(ABS(F65)>=$L$2,ABS(H65)>=$L$3),"Explain","")
A66: Debt service - interest | B66: =SUMIFS(GF_Budget_Detail!$E$5:$E$295,GF_Budget_Detail!$A$5:$A$295,$J$43,GF_Budget_Detail!$D$5:$D$295,"Debt service - interest") | C66: =SUMIFS(GF_Budget_Detail!$F$5:$F$295,GF_Budget_Detail!$A$5:$A$295,$J$43,GF_Budget_Detail!$D$5:$D$295,"Debt service - interest") | D66: =SUMIFS(GF_Budget_Detail!$G$5:$G$295,GF_Budget_Detail!$A$5:$A$295,$J$43,GF_Budget_Detail!$D$5:$D$295,"Debt service - interest") | E66: =C66-B66 | F66: =-(D66-C66) | G66: =-(D66-B66) | H66: =IFERROR(F66/ABS(C66),0) | I66: =IF(AND(ABS(F66)>=$L$2,ABS(H66)>=$L$3),"Explain","")
A67: Non-departmental (budget-report basis) | B67: =SUMIFS(GF_Budget_Detail!$E$5:$E$295,GF_Budget_Detail!$A$5:$A$295,$J$43,GF_Budget_Detail!$D$5:$D$295,"Non-departmental (budget-report basis)") | C67: =SUMIFS(GF_Budget_Detail!$F$5:$F$295,GF_Budget_Detail!$A$5:$A$295,$J$43,GF_Budget_Detail!$D$5:$D$295,"Non-departmental (budget-report basis)") | D67: =SUMIFS(GF_Budget_Detail!$G$5:$G$295,GF_Budget_Detail!$A$5:$A$295,$J$43,GF_Budget_Detail!$D$5:$D$295,"Non-departmental (budget-report basis)") | E67: =C67-B67 | F67: =-(D67-C67) | G67: =-(D67-B67) | H67: =IFERROR(F67/ABS(C67),0) | I67: =IF(AND(ABS(F67)>=$L$2,ABS(H67)>=$L$3),"Explain","")
A68: Original budget not itemized by department | B68: =SUMIFS(GF_Budget_Detail!$E$5:$E$295,GF_Budget_Detail!$A$5:$A$295,$J$43,GF_Budget_Detail!$D$5:$D$295,"Original budget not itemized by department") | C68: =SUMIFS(GF_Budget_Detail!$F$5:$F$295,GF_Budget_Detail!$A$5:$A$295,$J$43,GF_Budget_Detail!$D$5:$D$295,"Original budget not itemized by department") | D68: =SUMIFS(GF_Budget_Detail!$G$5:$G$295,GF_Budget_Detail!$A$5:$A$295,$J$43,GF_Budget_Detail!$D$5:$D$295,"Original budget not itemized by department") | E68: =C68-B68 | F68: =-(D68-C68) | G68: =-(D68-B68) | H68: =IFERROR(F68/ABS(C68),0) | I68: =IF(AND(ABS(F68)>=$L$2,ABS(H68)>=$L$3),"Explain","")
A69: Total expenditures | B69: =SUM(B56:B68) | C69: =SUM(C56:C68) | D69: =SUM(D56:D68) | E69: =C69-B69 | F69: =-(D69-C69) | G69: =-(D69-B69) | H69: =IFERROR(F69/ABS(C69),0) | I69: =IF(AND(ABS(F69)>=$L$2,ABS(H69)>=$L$3),"Explain","")
A71: Transfers in | B71: =SUMIFS(GF_Budget_Detail!$E$5:$E$295,GF_Budget_Detail!$A$5:$A$295,$J$43,GF_Budget_Detail!$D$5:$D$295,"Transfers in") | C71: =SUMIFS(GF_Budget_Detail!$F$5:$F$295,GF_Budget_Detail!$A$5:$A$295,$J$43,GF_Budget_Detail!$D$5:$D$295,"Transfers in") | D71: =SUMIFS(GF_Budget_Detail!$G$5:$G$295,GF_Budget_Detail!$A$5:$A$295,$J$43,GF_Budget_Detail!$D$5:$D$295,"Transfers in") | E71: =C71-B71 | F71: =(D71-C71) | G71: =(D71-B71) | H71: =IFERROR(F71/ABS(C71),0) | I71: =IF(AND(ABS(F71)>=$L$2,ABS(H71)>=$L$3),"Explain","")
A72: Transfers out | B72: =SUMIFS(GF_Budget_Detail!$E$5:$E$295,GF_Budget_Detail!$A$5:$A$295,$J$43,GF_Budget_Detail!$D$5:$D$295,"Transfers out") | C72: =SUMIFS(GF_Budget_Detail!$F$5:$F$295,GF_Budget_Detail!$A$5:$A$295,$J$43,GF_Budget_Detail!$D$5:$D$295,"Transfers out") | D72: =SUMIFS(GF_Budget_Detail!$G$5:$G$295,GF_Budget_Detail!$A$5:$A$295,$J$43,GF_Budget_Detail!$D$5:$D$295,"Transfers out") | E72: =C72-B72 | F72: =(D72-C72) | G72: =(D72-B72) | H72: =IFERROR(F72/ABS(C72),0) | I72: =IF(AND(ABS(F72)>=$L$2,ABS(H72)>=$L$3),"Explain","")
A73: Debt / lease financing proceeds | B73: =SUMIFS(GF_Budget_Detail!$E$5:$E$295,GF_Budget_Detail!$A$5:$A$295,$J$43,GF_Budget_Detail!$D$5:$D$295,"Debt / lease financing proceeds") | C73: =SUMIFS(GF_Budget_Detail!$F$5:$F$295,GF_Budget_Detail!$A$5:$A$295,$J$43,GF_Budget_Detail!$D$5:$D$295,"Debt / lease financing proceeds") | D73: =SUMIFS(GF_Budget_Detail!$G$5:$G$295,GF_Budget_Detail!$A$5:$A$295,$J$43,GF_Budget_Detail!$D$5:$D$295,"Debt / lease financing proceeds") | E73: =C73-B73 | F73: =(D73-C73) | G73: =(D73-B73) | H73: =IFERROR(F73/ABS(C73),0) | I73: =IF(AND(ABS(F73)>=$L$2,ABS(H73)>=$L$3),"Explain","")
A74: Proceeds from sale of capital assets | B74: =SUMIFS(GF_Budget_Detail!$E$5:$E$295,GF_Budget_Detail!$A$5:$A$295,$J$43,GF_Budget_Detail!$D$5:$D$295,"Proceeds from sale of capital assets") | C74: =SUMIFS(GF_Budget_Detail!$F$5:$F$295,GF_Budget_Detail!$A$5:$A$295,$J$43,GF_Budget_Detail!$D$5:$D$295,"Proceeds from sale of capital assets") | D74: =SUMIFS(GF_Budget_Detail!$G$5:$G$295,GF_Budget_Detail!$A$5:$A$295,$J$43,GF_Budget_Detail!$D$5:$D$295,"Proceeds from sale of capital assets") | E74: =C74-B74 | F74: =(D74-C74) | G74: =(D74-B74) | H74: =IFERROR(F74/ABS(C74),0) | I74: =IF(AND(ABS(F74)>=$L$2,ABS(H74)>=$L$3),"Explain","")
A75: Special items | B75: =SUMIFS(GF_Budget_Detail!$E$5:$E$295,GF_Budget_Detail!$A$5:$A$295,$J$43,GF_Budget_Detail!$D$5:$D$295,"Special items") | C75: =SUMIFS(GF_Budget_Detail!$F$5:$F$295,GF_Budget_Detail!$A$5:$A$295,$J$43,GF_Budget_Detail!$D$5:$D$295,"Special items") | D75: =SUMIFS(GF_Budget_Detail!$G$5:$G$295,GF_Budget_Detail!$A$5:$A$295,$J$43,GF_Budget_Detail!$D$5:$D$295,"Special items") | E75: =C75-B75 | F75: =(D75-C75) | G75: =(D75-B75) | H75: =IFERROR(F75/ABS(C75),0) | I75: =IF(AND(ABS(F75)>=$L$2,ABS(H75)>=$L$3),"Explain","")
A76: Total other financing sources (uses) and special items | B76: =SUM(B71:B75) | C76: =SUM(C71:C75) | D76: =SUM(D71:D75) | E76: =C76-B76 | F76: =(D76-C76) | G76: =(D76-B76) | H76: =IFERROR(F76/ABS(C76),0) | I76: =IF(AND(ABS(F76)>=$L$2,ABS(H76)>=$L$3),"Explain","")
A78: Net change in fund balance | B78: =B54-B69+B76 | C78: =C54-C69+C76 | D78: =D54-D69+D76 | E78: =C78-B78 | F78: =D78-C78 | G78: =D78-B78
A81: FY2015-16 (year ended June 30, 2016) - Budgetary comparison schedule, General Fund - GAAP (modified accrual) budgetary basis | J81: 2016
A82: Category | B82: Budgeted amounts - Original | C82: Budgeted amounts - Final | D82: Actual amounts (budgetary basis) | E82: Variance: Original to Final budget, increase (decrease) | F82: Variance with Final budget, positive (negative) | G82: Variance with Original budget, positive (negative) [supplementary] | H82: Variance with Final budget % | I82: Significant variance? (GASB 103 note candidate)
A83: Property taxes | B83: =SUMIFS(GF_Budget_Detail!$E$5:$E$295,GF_Budget_Detail!$A$5:$A$295,$J$81,GF_Budget_Detail!$D$5:$D$295,"Property taxes") | C83: =SUMIFS(GF_Budget_Detail!$F$5:$F$295,GF_Budget_Detail!$A$5:$A$295,$J$81,GF_Budget_Detail!$D$5:$D$295,"Property taxes") | D83: =SUMIFS(GF_Budget_Detail!$G$5:$G$295,GF_Budget_Detail!$A$5:$A$295,$J$81,GF_Budget_Detail!$D$5:$D$295,"Property taxes") | E83: =C83-B83 | F83: =(D83-C83) | G83: =(D83-B83) | H83: =IFERROR(F83/ABS(C83),0) | I83: =IF(AND(ABS(F83)>=$L$2,ABS(H83)>=$L$3),"Explain","")
A84: Taxes other than property | B84: =SUMIFS(GF_Budget_Detail!$E$5:$E$295,GF_Budget_Detail!$A$5:$A$295,$J$81,GF_Budget_Detail!$D$5:$D$295,"Taxes other than property") | C84: =SUMIFS(GF_Budget_Detail!$F$5:$F$295,GF_Budget_Detail!$A$5:$A$295,$J$81,GF_Budget_Detail!$D$5:$D$295,"Taxes other than property") | D84: =SUMIFS(GF_Budget_Detail!$G$5:$G$295,GF_Budget_Detail!$A$5:$A$295,$J$81,GF_Budget_Detail!$D$5:$D$295,"Taxes other than property") | E84: =C84-B84 | F84: =(D84-C84) | G84: =(D84-B84) | H84: =IFERROR(F84/ABS(C84),0) | I84: =IF(AND(ABS(F84)>=$L$2,ABS(H84)>=$L$3),"Explain","")
A85: Taxes and assessments (combined) | B85: =SUMIFS(GF_Budget_Detail!$E$5:$E$295,GF_Budget_Detail!$A$5:$A$295,$J$81,GF_Budget_Detail!$D$5:$D$295,"Taxes and assessments (combined)") | C85: =SUMIFS(GF_Budget_Detail!$F$5:$F$295,GF_Budget_Detail!$A$5:$A$295,$J$81,GF_Budget_Detail!$D$5:$D$295,"Taxes and assessments (combined)") | D85: =SUMIFS(GF_Budget_Detail!$G$5:$G$295,GF_Budget_Detail!$A$5:$A$295,$J$81,GF_Budget_Detail!$D$5:$D$295,"Taxes and assessments (combined)") | E85: =C85-B85 | F85: =(D85-C85) | G85: =(D85-B85) | H85: =IFERROR(F85/ABS(C85),0) | I85: =IF(AND(ABS(F85)>=$L$2,ABS(H85)>=$L$3),"Explain","")
A86: Licenses and permits | B86: =SUMIFS(GF_Budget_Detail!$E$5:$E$295,GF_Budget_Detail!$A$5:$A$295,$J$81,GF_Budget_Detail!$D$5:$D$295,"Licenses and permits") | C86: =SUMIFS(GF_Budget_Detail!$F$5:$F$295,GF_Budget_Detail!$A$5:$A$295,$J$81,GF_Budget_Detail!$D$5:$D$295,"Licenses and permits") | D86: =SUMIFS(GF_Budget_Detail!$G$5:$G$295,GF_Budget_Detail!$A$5:$A$295,$J$81,GF_Budget_Detail!$D$5:$D$295,"Licenses and permits") | E86: =C86-B86 | F86: =(D86-C86) | G86: =(D86-B86) | H86: =IFERROR(F86/ABS(C86),0) | I86: =IF(AND(ABS(F86)>=$L$2,ABS(H86)>=$L$3),"Explain","")
A87: Fines and forfeitures | B87: =SUMIFS(GF_Budget_Detail!$E$5:$E$295,GF_Budget_Detail!$A$5:$A$295,$J$81,GF_Budget_Detail!$D$5:$D$295,"Fines and forfeitures") | C87: =SUMIFS(GF_Budget_Detail!$F$5:$F$295,GF_Budget_Detail!$A$5:$A$295,$J$81,GF_Budget_Detail!$D$5:$D$295,"Fines and forfeitures") | D87: =SUMIFS(GF_Budget_Detail!$G$5:$G$295,GF_Budget_Detail!$A$5:$A$295,$J$81,GF_Budget_Detail!$D$5:$D$295,"Fines and forfeitures") | E87: =C87-B87 | F87: =(D87-C87) | G87: =(D87-B87) | H87: =IFERROR(F87/ABS(C87),0) | I87: =IF(AND(ABS(F87)>=$L$2,ABS(H87)>=$L$3),"Explain","")
A88: Use of money and property | B88: =SUMIFS(GF_Budget_Detail!$E$5:$E$295,GF_Budget_Detail!$A$5:$A$295,$J$81,GF_Budget_Detail!$D$5:$D$295,"Use of money and property") | C88: =SUMIFS(GF_Budget_Detail!$F$5:$F$295,GF_Budget_Detail!$A$5:$A$295,$J$81,GF_Budget_Detail!$D$5:$D$295,"Use of money and property") | D88: =SUMIFS(GF_Budget_Detail!$G$5:$G$295,GF_Budget_Detail!$A$5:$A$295,$J$81,GF_Budget_Detail!$D$5:$D$295,"Use of money and property") | E88: =C88-B88 | F88: =(D88-C88) | G88: =(D88-B88) | H88: =IFERROR(F88/ABS(C88),0) | I88: =IF(AND(ABS(F88)>=$L$2,ABS(H88)>=$L$3),"Explain","")
A89: Intergovernmental | B89: =SUMIFS(GF_Budget_Detail!$E$5:$E$295,GF_Budget_Detail!$A$5:$A$295,$J$81,GF_Budget_Detail!$D$5:$D$295,"Intergovernmental") | C89: =SUMIFS(GF_Budget_Detail!$F$5:$F$295,GF_Budget_Detail!$A$5:$A$295,$J$81,GF_Budget_Detail!$D$5:$D$295,"Intergovernmental") | D89: =SUMIFS(GF_Budget_Detail!$G$5:$G$295,GF_Budget_Detail!$A$5:$A$295,$J$81,GF_Budget_Detail!$D$5:$D$295,"Intergovernmental") | E89: =C89-B89 | F89: =(D89-C89) | G89: =(D89-B89) | H89: =IFERROR(F89/ABS(C89),0) | I89: =IF(AND(ABS(F89)>=$L$2,ABS(H89)>=$L$3),"Explain","")
A90: Charges for services | B90: =SUMIFS(GF_Budget_Detail!$E$5:$E$295,GF_Budget_Detail!$A$5:$A$295,$J$81,GF_Budget_Detail!$D$5:$D$295,"Charges for services") | C90: =SUMIFS(GF_Budget_Detail!$F$5:$F$295,GF_Budget_Detail!$A$5:$A$295,$J$81,GF_Budget_Detail!$D$5:$D$295,"Charges for services") | D90: =SUMIFS(GF_Budget_Detail!$G$5:$G$295,GF_Budget_Detail!$A$5:$A$295,$J$81,GF_Budget_Detail!$D$5:$D$295,"Charges for services") | E90: =C90-B90 | F90: =(D90-C90) | G90: =(D90-B90) | H90: =IFERROR(F90/ABS(C90),0) | I90: =IF(AND(ABS(F90)>=$L$2,ABS(H90)>=$L$3),"Explain","")
A91: Other revenues | B91: =SUMIFS(GF_Budget_Detail!$E$5:$E$295,GF_Budget_Detail!$A$5:$A$295,$J$81,GF_Budget_Detail!$D$5:$D$295,"Other revenues") | C91: =SUMIFS(GF_Budget_Detail!$F$5:$F$295,GF_Budget_Detail!$A$5:$A$295,$J$81,GF_Budget_Detail!$D$5:$D$295,"Other revenues") | D91: =SUMIFS(GF_Budget_Detail!$G$5:$G$295,GF_Budget_Detail!$A$5:$A$295,$J$81,GF_Budget_Detail!$D$5:$D$295,"Other revenues") | E91: =C91-B91 | F91: =(D91-C91) | G91: =(D91-B91) | H91: =IFERROR(F91/ABS(C91),0) | I91: =IF(AND(ABS(F91)>=$L$2,ABS(H91)>=$L$3),"Explain","")
A92: Total revenues | B92: =SUM(B83:B91) | C92: =SUM(C83:C91) | D92: =SUM(D83:D91) | E92: =C92-B92 | F92: =(D92-C92) | G92: =(D92-B92) | H92: =IFERROR(F92/ABS(C92),0) | I92: =IF(AND(ABS(F92)>=$L$2,ABS(H92)>=$L$3),"Explain","")
A94: General government | B94: =SUMIFS(GF_Budget_Detail!$E$5:$E$295,GF_Budget_Detail!$A$5:$A$295,$J$81,GF_Budget_Detail!$D$5:$D$295,"General government") | C94: =SUMIFS(GF_Budget_Detail!$F$5:$F$295,GF_Budget_Detail!$A$5:$A$295,$J$81,GF_Budget_Detail!$D$5:$D$295,"General government") | D94: =SUMIFS(GF_Budget_Detail!$G$5:$G$295,GF_Budget_Detail!$A$5:$A$295,$J$81,GF_Budget_Detail!$D$5:$D$295,"General government") | E94: =C94-B94 | F94: =-(D94-C94) | G94: =-(D94-B94) | H94: =IFERROR(F94/ABS(C94),0) | I94: =IF(AND(ABS(F94)>=$L$2,ABS(H94)>=$L$3),"Explain","")
A95: Public works | B95: =SUMIFS(GF_Budget_Detail!$E$5:$E$295,GF_Budget_Detail!$A$5:$A$295,$J$81,GF_Budget_Detail!$D$5:$D$295,"Public works") | C95: =SUMIFS(GF_Budget_Detail!$F$5:$F$295,GF_Budget_Detail!$A$5:$A$295,$J$81,GF_Budget_Detail!$D$5:$D$295,"Public works") | D95: =SUMIFS(GF_Budget_Detail!$G$5:$G$295,GF_Budget_Detail!$A$5:$A$295,$J$81,GF_Budget_Detail!$D$5:$D$295,"Public works") | E95: =C95-B95 | F95: =-(D95-C95) | G95: =-(D95-B95) | H95: =IFERROR(F95/ABS(C95),0) | I95: =IF(AND(ABS(F95)>=$L$2,ABS(H95)>=$L$3),"Explain","")
A96: Recreation | B96: =SUMIFS(GF_Budget_Detail!$E$5:$E$295,GF_Budget_Detail!$A$5:$A$295,$J$81,GF_Budget_Detail!$D$5:$D$295,"Recreation") | C96: =SUMIFS(GF_Budget_Detail!$F$5:$F$295,GF_Budget_Detail!$A$5:$A$295,$J$81,GF_Budget_Detail!$D$5:$D$295,"Recreation") | D96: =SUMIFS(GF_Budget_Detail!$G$5:$G$295,GF_Budget_Detail!$A$5:$A$295,$J$81,GF_Budget_Detail!$D$5:$D$295,"Recreation") | E96: =C96-B96 | F96: =-(D96-C96) | G96: =-(D96-B96) | H96: =IFERROR(F96/ABS(C96),0) | I96: =IF(AND(ABS(F96)>=$L$2,ABS(H96)>=$L$3),"Explain","")
A97: Community development | B97: =SUMIFS(GF_Budget_Detail!$E$5:$E$295,GF_Budget_Detail!$A$5:$A$295,$J$81,GF_Budget_Detail!$D$5:$D$295,"Community development") | C97: =SUMIFS(GF_Budget_Detail!$F$5:$F$295,GF_Budget_Detail!$A$5:$A$295,$J$81,GF_Budget_Detail!$D$5:$D$295,"Community development") | D97: =SUMIFS(GF_Budget_Detail!$G$5:$G$295,GF_Budget_Detail!$A$5:$A$295,$J$81,GF_Budget_Detail!$D$5:$D$295,"Community development") | E97: =C97-B97 | F97: =-(D97-C97) | G97: =-(D97-B97) | H97: =IFERROR(F97/ABS(C97),0) | I97: =IF(AND(ABS(F97)>=$L$2,ABS(H97)>=$L$3),"Explain","")
A98: Public safety - Police | B98: =SUMIFS(GF_Budget_Detail!$E$5:$E$295,GF_Budget_Detail!$A$5:$A$295,$J$81,GF_Budget_Detail!$D$5:$D$295,"Public safety - Police") | C98: =SUMIFS(GF_Budget_Detail!$F$5:$F$295,GF_Budget_Detail!$A$5:$A$295,$J$81,GF_Budget_Detail!$D$5:$D$295,"Public safety - Police") | D98: =SUMIFS(GF_Budget_Detail!$G$5:$G$295,GF_Budget_Detail!$A$5:$A$295,$J$81,GF_Budget_Detail!$D$5:$D$295,"Public safety - Police") | E98: =C98-B98 | F98: =-(D98-C98) | G98: =-(D98-B98) | H98: =IFERROR(F98/ABS(C98),0) | I98: =IF(AND(ABS(F98)>=$L$2,ABS(H98)>=$L$3),"Explain","")
A99: Public safety - Fire | B99: =SUMIFS(GF_Budget_Detail!$E$5:$E$295,GF_Budget_Detail!$A$5:$A$295,$J$81,GF_Budget_Detail!$D$5:$D$295,"Public safety - Fire") | C99: =SUMIFS(GF_Budget_Detail!$F$5:$F$295,GF_Budget_Detail!$A$5:$A$295,$J$81,GF_Budget_Detail!$D$5:$D$295,"Public safety - Fire") | D99: =SUMIFS(GF_Budget_Detail!$G$5:$G$295,GF_Budget_Detail!$A$5:$A$295,$J$81,GF_Budget_Detail!$D$5:$D$295,"Public safety - Fire") | E99: =C99-B99 | F99: =-(D99-C99) | G99: =-(D99-B99) | H99: =IFERROR(F99/ABS(C99),0) | I99: =IF(AND(ABS(F99)>=$L$2,ABS(H99)>=$L$3),"Explain","")
A100: Public safety (combined) | B100: =SUMIFS(GF_Budget_Detail!$E$5:$E$295,GF_Budget_Detail!$A$5:$A$295,$J$81,GF_Budget_Detail!$D$5:$D$295,"Public safety (combined)") | C100: =SUMIFS(GF_Budget_Detail!$F$5:$F$295,GF_Budget_Detail!$A$5:$A$295,$J$81,GF_Budget_Detail!$D$5:$D$295,"Public safety (combined)") | D100: =SUMIFS(GF_Budget_Detail!$G$5:$G$295,GF_Budget_Detail!$A$5:$A$295,$J$81,GF_Budget_Detail!$D$5:$D$295,"Public safety (combined)") | E100: =C100-B100 | F100: =-(D100-C100) | G100: =-(D100-B100) | H100: =IFERROR(F100/ABS(C100),0) | I100: =IF(AND(ABS(F100)>=$L$2,ABS(H100)>=$L$3),"Explain","")
A101: Payment of sales tax to City of Richmond | B101: =SUMIFS(GF_Budget_Detail!$E$5:$E$295,GF_Budget_Detail!$A$5:$A$295,$J$81,GF_Budget_Detail!$D$5:$D$295,"Payment of sales tax to City of Richmond") | C101: =SUMIFS(GF_Budget_Detail!$F$5:$F$295,GF_Budget_Detail!$A$5:$A$295,$J$81,GF_Budget_Detail!$D$5:$D$295,"Payment of sales tax to City of Richmond") | D101: =SUMIFS(GF_Budget_Detail!$G$5:$G$295,GF_Budget_Detail!$A$5:$A$295,$J$81,GF_Budget_Detail!$D$5:$D$295,"Payment of sales tax to City of Richmond") | E101: =C101-B101 | F101: =-(D101-C101) | G101: =-(D101-B101) | H101: =IFERROR(F101/ABS(C101),0) | I101: =IF(AND(ABS(F101)>=$L$2,ABS(H101)>=$L$3),"Explain","")
A102: Capital outlay | B102: =SUMIFS(GF_Budget_Detail!$E$5:$E$295,GF_Budget_Detail!$A$5:$A$295,$J$81,GF_Budget_Detail!$D$5:$D$295,"Capital outlay") | C102: =SUMIFS(GF_Budget_Detail!$F$5:$F$295,GF_Budget_Detail!$A$5:$A$295,$J$81,GF_Budget_Detail!$D$5:$D$295,"Capital outlay") | D102: =SUMIFS(GF_Budget_Detail!$G$5:$G$295,GF_Budget_Detail!$A$5:$A$295,$J$81,GF_Budget_Detail!$D$5:$D$295,"Capital outlay") | E102: =C102-B102 | F102: =-(D102-C102) | G102: =-(D102-B102) | H102: =IFERROR(F102/ABS(C102),0) | I102: =IF(AND(ABS(F102)>=$L$2,ABS(H102)>=$L$3),"Explain","")
A103: Debt service - principal | B103: =SUMIFS(GF_Budget_Detail!$E$5:$E$295,GF_Budget_Detail!$A$5:$A$295,$J$81,GF_Budget_Detail!$D$5:$D$295,"Debt service - principal") | C103: =SUMIFS(GF_Budget_Detail!$F$5:$F$295,GF_Budget_Detail!$A$5:$A$295,$J$81,GF_Budget_Detail!$D$5:$D$295,"Debt service - principal") | D103: =SUMIFS(GF_Budget_Detail!$G$5:$G$295,GF_Budget_Detail!$A$5:$A$295,$J$81,GF_Budget_Detail!$D$5:$D$295,"Debt service - principal") | E103: =C103-B103 | F103: =-(D103-C103) | G103: =-(D103-B103) | H103: =IFERROR(F103/ABS(C103),0) | I103: =IF(AND(ABS(F103)>=$L$2,ABS(H103)>=$L$3),"Explain","")
A104: Debt service - interest | B104: =SUMIFS(GF_Budget_Detail!$E$5:$E$295,GF_Budget_Detail!$A$5:$A$295,$J$81,GF_Budget_Detail!$D$5:$D$295,"Debt service - interest") | C104: =SUMIFS(GF_Budget_Detail!$F$5:$F$295,GF_Budget_Detail!$A$5:$A$295,$J$81,GF_Budget_Detail!$D$5:$D$295,"Debt service - interest") | D104: =SUMIFS(GF_Budget_Detail!$G$5:$G$295,GF_Budget_Detail!$A$5:$A$295,$J$81,GF_Budget_Detail!$D$5:$D$295,"Debt service - interest") | E104: =C104-B104 | F104: =-(D104-C104) | G104: =-(D104-B104) | H104: =IFERROR(F104/ABS(C104),0) | I104: =IF(AND(ABS(F104)>=$L$2,ABS(H104)>=$L$3),"Explain","")
A105: Non-departmental (budget-report basis) | B105: =SUMIFS(GF_Budget_Detail!$E$5:$E$295,GF_Budget_Detail!$A$5:$A$295,$J$81,GF_Budget_Detail!$D$5:$D$295,"Non-departmental (budget-report basis)") | C105: =SUMIFS(GF_Budget_Detail!$F$5:$F$295,GF_Budget_Detail!$A$5:$A$295,$J$81,GF_Budget_Detail!$D$5:$D$295,"Non-departmental (budget-report basis)") | D105: =SUMIFS(GF_Budget_Detail!$G$5:$G$295,GF_Budget_Detail!$A$5:$A$295,$J$81,GF_Budget_Detail!$D$5:$D$295,"Non-departmental (budget-report basis)") | E105: =C105-B105 | F105: =-(D105-C105) | G105: =-(D105-B105) | H105: =IFERROR(F105/ABS(C105),0) | I105: =IF(AND(ABS(F105)>=$L$2,ABS(H105)>=$L$3),"Explain","")
A106: Original budget not itemized by department | B106: =SUMIFS(GF_Budget_Detail!$E$5:$E$295,GF_Budget_Detail!$A$5:$A$295,$J$81,GF_Budget_Detail!$D$5:$D$295,"Original budget not itemized by department") | C106: =SUMIFS(GF_Budget_Detail!$F$5:$F$295,GF_Budget_Detail!$A$5:$A$295,$J$81,GF_Budget_Detail!$D$5:$D$295,"Original budget not itemized by department") | D106: =SUMIFS(GF_Budget_Detail!$G$5:$G$295,GF_Budget_Detail!$A$5:$A$295,$J$81,GF_Budget_Detail!$D$5:$D$295,"Original budget not itemized by department") | E106: =C106-B106 | F106: =-(D106-C106) | G106: =-(D106-B106) | H106: =IFERROR(F106/ABS(C106),0) | I106: =IF(AND(ABS(F106)>=$L$2,ABS(H106)>=$L$3),"Explain","")
A107: Total expenditures | B107: =SUM(B94:B106) | C107: =SUM(C94:C106) | D107: =SUM(D94:D106) | E107: =C107-B107 | F107: =-(D107-C107) | G107: =-(D107-B107) | H107: =IFERROR(F107/ABS(C107),0) | I107: =IF(AND(ABS(F107)>=$L$2,ABS(H107)>=$L$3),"Explain","")
A109: Transfers in | B109: =SUMIFS(GF_Budget_Detail!$E$5:$E$295,GF_Budget_Detail!$A$5:$A$295,$J$81,GF_Budget_Detail!$D$5:$D$295,"Transfers in") | C109: =SUMIFS(GF_Budget_Detail!$F$5:$F$295,GF_Budget_Detail!$A$5:$A$295,$J$81,GF_Budget_Detail!$D$5:$D$295,"Transfers in") | D109: =SUMIFS(GF_Budget_Detail!$G$5:$G$295,GF_Budget_Detail!$A$5:$A$295,$J$81,GF_Budget_Detail!$D$5:$D$295,"Transfers in") | E109: =C109-B109 | F109: =(D109-C109) | G109: =(D109-B109) | H109: =IFERROR(F109/ABS(C109),0) | I109: =IF(AND(ABS(F109)>=$L$2,ABS(H109)>=$L$3),"Explain","")
A110: Transfers out | B110: =SUMIFS(GF_Budget_Detail!$E$5:$E$295,GF_Budget_Detail!$A$5:$A$295,$J$81,GF_Budget_Detail!$D$5:$D$295,"Transfers out") | C110: =SUMIFS(GF_Budget_Detail!$F$5:$F$295,GF_Budget_Detail!$A$5:$A$295,$J$81,GF_Budget_Detail!$D$5:$D$295,"Transfers out") | D110: =SUMIFS(GF_Budget_Detail!$G$5:$G$295,GF_Budget_Detail!$A$5:$A$295,$J$81,GF_Budget_Detail!$D$5:$D$295,"Transfers out") | E110: =C110-B110 | F110: =(D110-C110) | G110: =(D110-B110) | H110: =IFERROR(F110/ABS(C110),0) | I110: =IF(AND(ABS(F110)>=$L$2,ABS(H110)>=$L$3),"Explain","")
A111: Debt / lease financing proceeds | B111: =SUMIFS(GF_Budget_Detail!$E$5:$E$295,GF_Budget_Detail!$A$5:$A$295,$J$81,GF_Budget_Detail!$D$5:$D$295,"Debt / lease financing proceeds") | C111: =SUMIFS(GF_Budget_Detail!$F$5:$F$295,GF_Budget_Detail!$A$5:$A$295,$J$81,GF_Budget_Detail!$D$5:$D$295,"Debt / lease financing proceeds") | D111: =SUMIFS(GF_Budget_Detail!$G$5:$G$295,GF_Budget_Detail!$A$5:$A$295,$J$81,GF_Budget_Detail!$D$5:$D$295,"Debt / lease financing proceeds") | E111: =C111-B111 | F111: =(D111-C111) | G111: =(D111-B111) | H111: =IFERROR(F111/ABS(C111),0) | I111: =IF(AND(ABS(F111)>=$L$2,ABS(H111)>=$L$3),"Explain","")
A112: Proceeds from sale of capital assets | B112: =SUMIFS(GF_Budget_Detail!$E$5:$E$295,GF_Budget_Detail!$A$5:$A$295,$J$81,GF_Budget_Detail!$D$5:$D$295,"Proceeds from sale of capital assets") | C112: =SUMIFS(GF_Budget_Detail!$F$5:$F$295,GF_Budget_Detail!$A$5:$A$295,$J$81,GF_Budget_Detail!$D$5:$D$295,"Proceeds from sale of capital assets") | D112: =SUMIFS(GF_Budget_Detail!$G$5:$G$295,GF_Budget_Detail!$A$5:$A$295,$J$81,GF_Budget_Detail!$D$5:$D$295,"Proceeds from sale of capital assets") | E112: =C112-B112 | F112: =(D112-C112) | G112: =(D112-B112) | H112: =IFERROR(F112/ABS(C112),0) | I112: =IF(AND(ABS(F112)>=$L$2,ABS(H112)>=$L$3),"Explain","")
A113: Special items | B113: =SUMIFS(GF_Budget_Detail!$E$5:$E$295,GF_Budget_Detail!$A$5:$A$295,$J$81,GF_Budget_Detail!$D$5:$D$295,"Special items") | C113: =SUMIFS(GF_Budget_Detail!$F$5:$F$295,GF_Budget_Detail!$A$5:$A$295,$J$81,GF_Budget_Detail!$D$5:$D$295,"Special items") | D113: =SUMIFS(GF_Budget_Detail!$G$5:$G$295,GF_Budget_Detail!$A$5:$A$295,$J$81,GF_Budget_Detail!$D$5:$D$295,"Special items") | E113: =C113-B113 | F113: =(D113-C113) | G113: =(D113-B113) | H113: =IFERROR(F113/ABS(C113),0) | I113: =IF(AND(ABS(F113)>=$L$2,ABS(H113)>=$L$3),"Explain","")
...

Sheet GF_Variance_Notes
A1: City of El Cerrito - GENERAL FUND: explanations of significant budget variances
A2: GASB 103 (effective FY2026) requires notes explaining significant original-to-final and final-to-actual variances. The City's audited reports before FY2026 were not required to include them; explanations below are paraphrased from the ACFR MD&A, budget schedules and the FY2025-26 Q4 update. Lines flagged 'Explain' without a note here are not explained in public sources.
A4: FY | B4: Variance | C4: Explanation | D4: Source
A5: 2019 | B5: Public safety - Fire over final budget by $1.10M | C5: Higher public safety overtime; MD&A notes new revenue 'helped pay for increased Public Safety overtime'. | D5: FY2019 CAFR MD&A
A6: 2019 | B6: Transfers in +$1.06M; special item +$0.80M | C6: Transfers from nonmajor funds and proceeds of a land sale from Contra Costa County not in the original budget. | D6: FY2019 CAFR budget schedule
A7: 2020 | B7: Charges for services under final budget by $1.88M | C7: COVID-19 closures of recreation and other fee-based services; offset by cost reductions and expenditure deferrals. | D7: FY2020 CAFR MD&A
A8: 2021 | B8: Taxes other than property +$4.22M; transfers in +$3.12M | C8: Sales and transfer taxes well above a pandemic-era budget; $3.05M federal relief moved from the grants fund to the General Fund. | D8: FY2021 ACFR budget schedule, transfers note
A9: 2021 | B9: Special item -$1.32M | C9: Write-off of the General Fund advance to the Successor Agency (non-cash). | D9: FY2021 ACFR
A10: 2022 | B10: Total revenues +$5.10M vs. final | C10: Better-than-anticipated tax revenues, licenses and permits, and charges for services; intergovernmental shortfall reflects federal relief received as transfers in (+$2.3M) instead. | D10: FY2022 ACFR MD&A
A11: 2023 | B11: Revenues +$3.92M; public safety $2.23M under final | C11: Strong tax revenues, permits and charges; salaries and benefits under budget due to high vacancies. | D11: FY2023 ACFR MD&A
A12: 2024 | B12: Final budget deficit of $6.31M vs. original surplus | C12: Council voted mid-year to use unassigned fund balance for urgent capital needs (about $6.5M one-time, incl. $1.6M purchase of 10936 San Pablo Ave and $1.1M park/facility repairs). | D12: FY2024 ACFR MD&A, transfers note
A13: 2024 | B13: Revenues +$3.44M; expenditures $2.70M under final | C13: Tax revenues, permits and charges above budget; vacancies and timing of disbursements held spending down. | D13: FY2024 ACFR MD&A
A14: 2025 | B14: Revenues +$2.44M vs. final | C14: Utility users tax +$0.51M (14%) from utility rate increases; transfer tax +$0.21M; franchise fees +$0.2M. | D14: FY2025 ACFR MD&A
A15: 2025 | B15: Public safety $0.49M over final | C15: Not explained in the FY2025 ACFR MD&A; the FY2025-26 Q4 report attributes similar overruns to overtime from vacancies and new labor agreements. | D15: FY2025 ACFR schedule; FY2026 Q4 update
A16: 2026 | B16: Fire $0.48M and Police $0.22M over amended budget (UNAUDITED) | C16: Overtime backfill for long-term absences, a paramedic shortage, and sworn vacancies (21% rate); MOUs approved after budget development. | D16: FY2025-26 Q4 update (9/15/2026)
... A18: 2026 | B18: Revenues 103% of budget (UNAUDITED) | C18: Franchise fees +40% (energy rates), transfer tax +13%, fines doubled (parking citation backlog), interest income above budget. | D18: FY2025-26 Q4 update

Sheet GF_Variance_Trend
A1: City of El Cerrito - GENERAL FUND ONLY
A2: Budget variance trend, $ (links to GF_Budget_Variance)
A3: Expenditure overrun rows: positive = actual spent MORE than budget. FY2026* is UNAUDITED and on the budget-report basis; cumulative totals are shown both with and without it.
N5: UNAUDITED
A6: Fiscal year ended June 30 | B6: 2014 | C6: 2015 | D6: 2016 | E6: 2017 | F6: 2018 | G6: 2019 | H6: 2020 | I6: 2021 | J6: 2022 | K6: 2023 | L6: 2024 | M6: 2025 | N6: 2026
A7: REVENUES
A8: Original budget | B8: =GF_Budget_Variance!B16 | C8: =GF_Budget_Variance!B54 | D8: =GF_Budget_Variance!B92 | E8: =GF_Budget_Variance!B130 | F8: =GF_Budget_Variance!B168 | G8: =GF_Budget_Variance!B206 | H8: =GF_Budget_Variance!B244 | I8: =GF_Budget_Variance!B282 | J8: =GF_Budget_Variance!B320 | K8: =GF_Budget_Variance!B358 | L8: =GF_Budget_Variance!B396 | M8: =GF_Budget_Variance!B434 | N8: =GF_Budget_Variance!B472
A9: Final budget | B9: =GF_Budget_Variance!C16 | C9: =GF_Budget_Variance!C54 | D9: =GF_Budget_Variance!C92 | E9: =GF_Budget_Variance!C130 | F9: =GF_Budget_Variance!C168 | G9: =GF_Budget_Variance!C206 | H9: =GF_Budget_Variance!C244 | I9: =GF_Budget_Variance!C282 | J9: =GF_Budget_Variance!C320 | K9: =GF_Budget_Variance!C358 | L9: =GF_Budget_Variance!C396 | M9: =GF_Budget_Variance!C434 | N9: =GF_Budget_Variance!C472
A10: Actual | B10: =GF_Budget_Variance!D16 | C10: =GF_Budget_Variance!D54 | D10: =GF_Budget_Variance!D92 | E10: =GF_Budget_Variance!D130 | F10: =GF_Budget_Variance!D168 | G10: =GF_Budget_Variance!D206 | H10: =GF_Budget_Variance!D244 | I10: =GF_Budget_Variance!D282 | J10: =GF_Budget_Variance!D320 | K10: =GF_Budget_Variance!D358 | L10: =GF_Budget_Variance!D396 | M10: =GF_Budget_Variance!D434 | N10: =GF_Budget_Variance!D472
A11: Actual - Original | B11: =B10-B8 | C11: =C10-C8 | D11: =D10-D8 | E11: =E10-E8 | F11: =F10-F8 | G11: =G10-G8 | H11: =H10-H8 | I11: =I10-I8 | ... N11: =N10-N8
A13: EXPENDITURES
A14: Original budget | B14: =GF_Budget_Variance!B31 | C14: =GF_Budget_Variance!B69 | D14: =GF_Budget_Variance!B107 | E14: =GF_Budget_Variance!B145 | F14: =GF_Budget_Variance!B183 | G14: =GF_Budget_Variance!B221 | H14: =GF_Budget_Variance!B259 | I14: =GF_Budget_Variance!B297 | J14: =GF_Budget_Variance!B335 | K14: =GF_Budget_Variance!B373 | L14: =GF_Budget_Variance!B411 | M14: =GF_Budget_Variance!B449 | N14: =GF_Budget_Variance!B487
A15: Budget amendments (Final - Original) | B15: =GF_Budget_Variance!E31 | C15: =GF_Budget_Variance!E69 | D15: =GF_Budget_Variance!E107 | E15: =GF_Budget_Variance!E145 | F15: =GF_Budget_Variance!E183 | G15: =GF_Budget_Variance!E221 | H15: =GF_Budget_Variance!E259 | I15: =GF_Budget_Variance!E297 | J15: =GF_Budget_Variance!E335 | K15: =GF_Budget_Variance!E373 | L15: =GF_Budget_Variance!E411 | M15: =GF_Budget_Variance!E449 | N15: =GF_Budget_Variance!E487
A16: Final budget | B16: =GF_Budget_Variance!C31 | C16: =GF_Budget_Variance!C69 | D16: =GF_Budget_Variance!C107 | E16: =GF_Budget_Variance!C145 | F16: =GF_Budget_Variance!C183 | G16: =GF_Budget_Variance!C221 | H16: =GF_Budget_Variance!C259 | I16: =GF_Budget_Variance!C297 | J16: =GF_Budget_Variance!C335 | K16: =GF_Budget_Variance!C373 | L16: =GF_Budget_Variance!C411 | M16: =GF_Budget_Variance!C449 | N16: =GF_Budget_Variance!C487
A17: Actual | B17: =GF_Budget_Variance!D31 | C17: =GF_Budget_Variance!D69 | D17: =GF_Budget_Variance!D107 | E17: =GF_Budget_Variance!D145 | F17: =GF_Budget_Variance!D183 | G17: =GF_Budget_Variance!D221 | H17: =GF_Budget_Variance!D259 | I17: =GF_Budget_Variance!D297 | J17: =GF_Budget_Variance!D335 | K17: =GF_Budget_Variance!D373 | L17: =GF_Budget_Variance!D411 | M17: =GF_Budget_Variance!D449 | N17: =GF_Budget_Variance!D487
A18: Overrun vs. Original (Actual - Original) | B18: =B17-B14 | C18: =C17-C14 | D18: =D17-D14 | E18: =E17-E14 | F18: =F17-F14 | G18: =G17-G14 | H18: =H17-H14 | I18: =I17-I14 | ... N18: =N17-N14
A19: Overrun vs. Final (Actual - Final) | B19: =B17-B16 | C19: =C17-C16 | D19: =D17-D16 | E19: =E17-E16 | F19: =F17-F16 | G19: =G17-G16 | H19: =H17-H16 | I19: =I17-I16 | ... N19: =N17-N16
A20: Overrun vs. Original % | B20: =IFERROR(B18/B14,0) | C20: =IFERROR(C18/C14,0) | D20: =IFERROR(D18/D14,0) | E20: =IFERROR(E18/E14,0) | F20: =IFERROR(F18/F14,0) | G20: =IFERROR(G18/G14,0) | H20: =IFERROR(H18/H14,0) | I20: =IFERROR(I18/I14,0) | ... N20: =IFERROR(N18/N14,0)
A21: Spent more than original budget? (1 = yes) | B21: =IF(B18>0,1,0) | C21: =IF(C18>0,1,0) | D21: =IF(D18>0,1,0) | E21: =IF(E18>0,1,0) | F21: =IF(F18>0,1,0) | G21: =IF(G18>0,1,0) | H21: =IF(H18>0,1,0) | I21: =IF(I18>0,1,0) | ... N21: =IF(N18>0,1,0)
A23: TRANSFERS OUT (negative = outflow)
A24: Original budget | B24: =GF_Budget_Variance!B34 | C24: =GF_Budget_Variance!B72 | D24: =GF_Budget_Variance!B110 | E24: =GF_Budget_Variance!B148 | F24: =GF_Budget_Variance!B186 | G24: =GF_Budget_Variance!B224 | H24: =GF_Budget_Variance!B262 | I24: =GF_Budget_Variance!B300 | J24: =GF_Budget_Variance!B338 | K24: =GF_Budget_Variance!B376 | L24: =GF_Budget_Variance!B414 | M24: =GF_Budget_Variance!B452 | N24: =GF_Budget_Variance!B490
A25: Actual | B25: =GF_Budget_Variance!D34 | C25: =GF_Budget_Variance!D72 | D25: =GF_Budget_Variance!D110 | E25: =GF_Budget_Variance!D148 | F25: =GF_Budget_Variance!D186 | G25: =GF_Budget_Variance!D224 | H25: =GF_Budget_Variance!D262 | I25: =GF_Budget_Variance!D300 | J25: =GF_Budget_Variance!D338 | K25: =GF_Budget_Variance!D376 | L25: =GF_Budget_Variance!D414 | M25: =GF_Budget_Variance!D452 | N25: =GF_Budget_Variance!D490
A26: Extra transfers out vs. Original | B26: =-(B25-B24) | C26: =-(C25-C24) | D26: =-(D25-D24) | E26: =-(E25-E24) | F26: =-(F25-F24) | G26: =-(G25-G24) | H26: =-(H25-H24) | I26: =-(I25-I24) | ... N26: =-(N25-N24)
A28: NET CHANGE IN FUND BALANCE
A29: Original budget (planned) | B29: =GF_Budget_Variance!B40 | C29: =GF_Budget_Variance!B78 | D29: =GF_Budget_Variance!B116 | E29: =GF_Budget_Variance!B154 | F29: =GF_Budget_Variance!B192 | G29: =GF_Budget_Variance!B230 | H29: =GF_Budget_Variance!B268 | I29: =GF_Budget_Variance!B306 | J29: =GF_Budget_Variance!B344 | K29: =GF_Budget_Variance!B382 | L29: =GF_Budget_Variance!B420 | M29: =GF_Budget_Variance!B458 | N29: =GF_Budget_Variance!B496
A30: Final budget | B30: =GF_Budget_Variance!C40 | C30: =GF_Budget_Variance!C78 | D30: =GF_Budget_Variance!C116 | E30: =GF_Budget_Variance!C154 | F30: =GF_Budget_Variance!C192 | G30: =GF_Budget_Variance!C230 | H30: =GF_Budget_Variance!C268 | I30: =GF_Budget_Variance!C306 | J30: =GF_Budget_Variance!C344 | K30: =GF_Budget_Variance!C382 | L30: =GF_Budget_Variance!C420 | M30: =GF_Budget_Variance!C458 | N30: =GF_Budget_Variance!C496
A31: Actual | B31: =GF_Budget_Variance!D40 | C31: =GF_Budget_Variance!D78 | D31: =GF_Budget_Variance!D116 | E31: =GF_Budget_Variance!D154 | F31: =GF_Budget_Variance!D192 | G31: =GF_Budget_Variance!D230 | H31: =GF_Budget_Variance!D268 | I31: =GF_Budget_Variance!D306 | J31: =GF_Budget_Variance!D344 | K31: =GF_Budget_Variance!D382 | L31: =GF_Budget_Variance!D420 | M31: =GF_Budget_Variance!D458 | N31: =GF_Budget_Variance!D496
A32: Actual vs. original plan | B32: =B31-B29 | C32: =C31-C29 | D32: =D31-D29 | E32: =E31-E29 | F32: =F31-F29 | G32: =G31-G29 | H32: =H31-H29 | I32: =I31-I29 | ... N32: =N31-N29
A34: CUMULATIVE
B35: FY2014-FY2025 (audited) | C35: FY2014-FY2026 (incl. unaudited)
A36: Revenue: Actual - Original | B36: =SUM(B11:M11) | C36: =SUM(B11:N11)
A37: Expenditure overrun vs. Original | B37: =SUM(B18:M18) | C37: =SUM(B18:N18)
A38: Expenditure overrun vs. Final | B38: =SUM(B19:M19) | C38: =SUM(B19:N19)
A39: Extra transfers out vs. Original | B39: =SUM(B26:M26) | C39: =SUM(B26:N26)
A40: Net change: actual vs. original plan | B40: =SUM(B32:M32) | C40: =SUM(B32:N32)
A41: Years spending exceeded original budget | B41: =SUM(B21:M21) | C41: =SUM(B21:N21)
A43: Check: GF_Budget_Variance net change vs. GF_Operating_Statement (should be 0) | B43: =B31-GF_Operating_Statement!B48 | C43: =C31-GF_Operating_Statement!C48 | D43: =D31-GF_Operating_Statement!D48 | E43: =E31-GF_Operating_Statement!E48 | F43: =F31-GF_Operating_Statement!F48 | G43: =G31-GF_Operating_Statement!G48 | H43: =H31-GF_Operating_Statement!H48 | I43: =I31-GF_Operating_Statement!I48 | ... N43: =N31-GF_Operating_Statement!N48

Sheet GF_to_Citywide_Bridge
A1: City of El Cerrito - BRIDGE: General Fund -> Citywide
A2: From General Fund fund balance to governmental-activities net position, June 30, $
A3: Shows what the General Fund statements leave out. Lines link to GF_Balance_Sheet and CW_Net_Position; 'Other reconciling items' is computed as the remainder (internal service fund, unavailable revenue, interest payable, refunding deferrals, etc.).
A6: June 30 | B6: 2014 | C6: 2015 | D6: 2016 | E6: 2017 | F6: 2018 | G6: 2019 | H6: 2020 | I6: 2021 | J6: 2022 | K6: 2023 | L6: 2024 | M6: 2025
A7: General Fund - total fund balance | B7: =GF_Balance_Sheet!B40 | C7: =GF_Balance_Sheet!C40 | D7: =GF_Balance_Sheet!D40 | E7: =GF_Balance_Sheet!E40 | F7: =GF_Balance_Sheet!F40 | G7: =GF_Balance_Sheet!G40 | H7: =GF_Balance_Sheet!H40 | I7: =GF_Balance_Sheet!I40 | ... M7: =GF_Balance_Sheet!M40
A8: Total fund balance, all governmental funds (per ACFR) | B8: 8455545 | C8: 8882873 | D8: 10753378 | E8: 15624337 | F8: 14797126 | G8: 12751823 | H8: 14089516 | I8: 21878516 | J8: 31509231 | K8: 39222668 | L8: 41682246 | M8: 43970819
A9: Plus: other governmental funds (special revenue, capital projects, debt service) | B9: =B8-B7 | C9: =C8-C7 | D9: =D8-D7 | E9: =E8-E7 | F9: =F8-F7 | G9: =G8-G7 | H9: =H8-H7 | I9: =I8-I7 | ... M9: =M8-M7
A10: Equals: total governmental funds fund balance | B10: =B7+B9 | C10: =C7+C9 | D10: =D7+D9 | E10: =E7+E9 | F10: =F7+F9 | G10: =G7+G9 | H10: =H7+H9 | I10: =I7+I9 | ... M10: =M7+M9
A12: ITEMS NOT IN THE FUND STATEMENTS
A13: Plus: capital assets, net (buildings, equipment, infrastructure, land) | B13: =CW_Net_Position!B43 | C13: =CW_Net_Position!C43 | D13: =CW_Net_Position!D43 | E13: =CW_Net_Position!E43 | F13: =CW_Net_Position!F43 | G13: =CW_Net_Position!G43 | H13: =CW_Net_Position!H43 | I13: =CW_Net_Position!I43 | ... M13: =CW_Net_Position!M43
A14: Less: long-term debt | B14: =-CW_Net_Position!B26 | C14: =-CW_Net_Position!C26 | D14: =-CW_Net_Position!D26 | E14: =-CW_Net_Position!E26 | F14: =-CW_Net_Position!F26 | G14: =-CW_Net_Position!G26 | H14: =-CW_Net_Position!H26 | I14: =-CW_Net_Position!I26 | ... M14: =-CW_Net_Position!M26
A15: Less: compensated absences and claims | B15: =-(CW_Net_Position!B24+CW_Net_Position!B25) | C15: =-(CW_Net_Position!C24+CW_Net_Position!C25) | D15: =-(CW_Net_Position!D24+CW_Net_Position!D25) | E15: =-(CW_Net_Position!E24+CW_Net_Position!E25) | F15: =-(CW_Net_Position!F24+CW_Net_Position!F25) | G15: =-(CW_Net_Position!G24+CW_Net_Position!G25) | H15: =-(CW_Net_Position!H24+CW_Net_Position!H25) | I15: =-(CW_Net_Position!I24+CW_Net_Position!I25) | ... M15: =-(CW_Net_Position!M24+CW_Net_Position!M25)
A16: Less: net pension and OPEB liability | B16: =-(CW_Net_Position!B28+CW_Net_Position!B27) | C16: =-(CW_Net_Position!C28+CW_Net_Position!C27) | D16: =-(CW_Net_Position!D28+CW_Net_Position!D27) | E16: =-(CW_Net_Position!E28+CW_Net_Position!E27) | F16: =-(CW_Net_Position!F28+CW_Net_Position!F27) | G16: =-(CW_Net_Position!G28+CW_Net_Position!G27) | H16: =-(CW_Net_Position!H28+CW_Net_Position!H27) | I16: =-(CW_Net_Position!I28+CW_Net_Position!I27) | ... M16: =-(CW_Net_Position!M28+CW_Net_Position!M27)
A17: Plus: pension/OPEB deferred outflows less deferred inflows | B17: =CW_Net_Position!B17-CW_Net_Position!B32 | C17: =CW_Net_Position!C17-CW_Net_Position!C32 | D17: =CW_Net_Position!D17-CW_Net_Position!D32 | E17: =CW_Net_Position!E17-CW_Net_Position!E32 | F17: =CW_Net_Position!F17-CW_Net_Position!F32 | G17: =CW_Net_Position!G17-CW_Net_Position!G32 | H17: =CW_Net_Position!H17-CW_Net_Position!H32 | I17: =CW_Net_Position!I17-CW_Net_Position!I32 | ... M17: =CW_Net_Position!M17-CW_Net_Position!M32
A18: Other reconciling items (computed remainder) | B18: =B20-B10-SUM(B13:B17) | C18: =C20-C10-SUM(C13:C17) | D18: =D20-D10-SUM(D13:D17) | E18: =E20-E10-SUM(E13:E17) | F18: =F20-F10-SUM(F13:F17) | G18: =G20-G10-SUM(G13:G17) | H18: =H20-H10-SUM(H13:H17) | I18: =I20-I10-SUM(I13:I17) | ... M18: =M20-M10-SUM(M13:M17)
A20: Equals: net position, governmental activities (citywide) | B20: =CW_Net_Position!B37 | C20: =CW_Net_Position!C37 | D20: =CW_Net_Position!D37 | E20: =CW_Net_Position!E37 | F20: =CW_Net_Position!F37 | G20: =CW_Net_Position!G37 | H20: =CW_Net_Position!H37 | I20: =CW_Net_Position!I37 | ... M20: =CW_Net_Position!M37
A22: SUMMARY
A23: General Fund fund balance | B23: =B7 | C23: =C7 | D23: =D7 | E23: =E7 | F23: =F7 | G23: =G7 | H23: =H7 | I23: =I7 | ... M23: =M7
A24: Effect of pension/OPEB (liability net of deferrals) | B24: =B16+B17 | C24: =C16+C17 | D24: =D16+D17 | E24: =E16+E17 | F24: =F16+F17 | G24: =G16+G17 | H24: =H16+H17 | I24: =I16+I17 | ... M24: =M16+M17
A25: Effect of capital assets net of long-term debt | B25: =B13+B14 | C25: =C13+C14 | D25: =D13+D14 | E25: =E13+E14 | F25: =F13+F14 | G25: =G13+G14 | H25: =H13+H14 | I25: =I13+I14 | ... M25: =M13+M14
A26: Everything else (other funds, leave, claims, other items) | B26: =B9+B15+B18 | C26: =C9+C15+C18 | D26: =D9+D15+D18 | E26: =E9+E15+E18 | F26: =F9+F15+F18 | G26: =G9+G15+G18 | H26: =H9+H15+H18 | I26: =I9+I15+I18 | ... M26: =M9+M15+M18
A27: Citywide net position (governmental activities) | B27: =SUM(B23:B26) | C27: =SUM(C23:C26) | D27: =SUM(D23:D26) | E27: =SUM(E23:E26) | F27: =SUM(F23:F26) | G27: =SUM(G23:G26) | H27: =SUM(H23:H26) | I27: =SUM(I23:I26) | ... M27: =SUM(M23:M26)
A28: Check: summary vs. net position (should be 0) | B28: =B27-B20 | C28: =C27-C20 | D28: =D27-D20 | E28: =E27-E20 | F28: =F27-F20 | G28: =G27-G20 | H28: =H27-H20 | I28: =I27-I20 | ... M28: =M27-M20
A31: ACFR RECONCILIATION, ITEMIZED (total governmental funds -> governmental activities net position)
A32: Total fund balance, all governmental funds | B32: =B8 | C32: =C8 | D32: =D8 | E32: =E8 | F32: =F8 | G32: =G8 | H32: =H8 | I32: =I8 | ... M32: =M8
A33: Capital assets, net (excl. internal service fund) | B33: 85067083 | C33: 83144818 | D33: 80998173 | E33: 78694517 | F33: 76852224 | G33: 73109078 | H33: 71099169 | I33: 69231302 | J33: 68142964 | K33: 67244487 | L33: 68848098 | M33: 73597873
A34: Internal service fund net position | B34: -26862 | C34: -26863 | D34: -157135 | E34: 1055976 | F34: 736159 | G34: 568028 | H34: 509746 | I34: 375645 | J34: 420341 | K34: 456819 | L34: 581323 | M34: 856006
A35: Revenues unavailable in funds, recognized citywide | B35: 5406297 | C35: 7713154 | D35: 7758205 | E35: 1056520 | F35: 1664536 | G35: 1211055 | H35: 1041626 | I35: 1124127 | J35: 1052839 | K35: 1375016 | L35: 3732214 | M35: 5198482
A36: Accrued interest payable | B36: -132133 | C36: -126608 | D36: -120658 | E36: -174625 | F36: -207347 | G36: -201946 | H36: -196933 | I36: -193310 | J36: -202000 | K36: -193310 | L36: -154000 | M36: -157841
A37: Pension/OPEB deferred outflows less inflows (incl. deferred contributions) | B37: 0 | C37: -4899831 | D37: 3536995 | E37: 13438254 | F37: 16463199 | G37: 12719762 | H37: 12955687 | I37: 15419079 | J37: -18735540 | K37: 27297012 | L37: 28643120 | M37: 22853811
A38: Deferred amounts on debt refunding | B38: 0 | C38: 0 | D38: 0 | E38: 335395 | F38: 317723 | G38: 300051 | H38: 282379 | I38: 264707 | J38: 247035 | K38: 229363 | L38: 211691 | M38: 194019
A39: Other (accrued liabilities) | B39: -1037862 | C39: -792263 | D39: -520976 | E39: -233436 | F39: 0 | G39: 0 | H39: 0 | I39: 0 | J39: 0 | K39: 0 | L39: 0 | M39: 0
A40: Long-term debt (net of internal service fund portion) | B40: -23212392 | C40: -22181119 | D40: -20686071 | E40: -19787721 | F40: -19030269 | G40: -18066109 | H40: -17196617 | I40: -16162563 | J40: -15376442 | K40: -14480093 | L40: -13119228 | M40: -12759753
A41: Compensated absences | B41: -1541015 | C41: -1335398 | D41: -1454048 | E41: -1662426 | F41: -1874601 | G41: -2026530 | H41: -2382150 | I41: -2630077 | J41: -2504516 | K41: -1716023 | L41: -1874503 | M41: -2741774
A42: Claims payable | B42: -57349 | C42: -90418 | D42: -375006 | E42: -13827 | F42: -21402 | G42: -36165 | H42: -28741 | I42: -15000 | J42: -15000 | K42: -23968 | L42: -18453 | M42: -20625
A43: OPEB liability | B43: -1573570 | C43: -1867190 | D43: -2160810 | E43: -2454430 | F43: -2845887 | G43: -2994539 | H43: -3906161 | I43: -4887434 | J43: 0 | K43: 0 | L43: 0 | M43: 0
A44: Net pension liability | B44: 0 | C44: -39314773 | D44: -45992107 | E44: -54843657 | F44: -61775131 | G44: -61856499 | H44: -65832700 | I44: -70374424 | J44: -48950390 | K44: -79526924 | L44: -80740039 | M44: -79676034
A45: Net position, governmental activities (computed) | B45: =B32+SUM(B33:B44) | C45: =C32+SUM(C33:C44) | D45: =D32+SUM(D33:D44) | E45: =E32+SUM(E33:E44) | F45: =F32+SUM(F33:F44) | G45: =G32+SUM(G33:G44) | H45: =H32+SUM(H33:H44) | I45: =I32+SUM(I33:I44) | ... M45: =M32+SUM(M33:M44)
A46: Check: vs. CW_Net_Position (should be 0) | B46: =B45-CW_Net_Position!B37 | C46: =C45-CW_Net_Position!C37 | D46: =D45-CW_Net_Position!D37 | E46: =E45-CW_Net_Position!E37 | F46: =F45-CW_Net_Position!F37 | G46: =G45-CW_Net_Position!G37 | H46: =H45-CW_Net_Position!H37 | I46: =I45-CW_Net_Position!I37 | ... M46: =M45-CW_Net_Position!M37
A47: Memo: internal service fund + unavailable revenue + interest + deferrals + refunding + other (itemized items not in the summary above) | B47: =SUM(B34:B38)+B39 | C47: =SUM(C34:C38)+C39 | D47: =SUM(D34:D38)+D39 | E47: =SUM(E34:E38)+E39 | F47: =SUM(F34:F38)+F39 | G47: =SUM(G34:G38)+G39 | H47: =SUM(H34:H38)+H39 | I47: =SUM(I34:I38)+I39 | ... M47: =SUM(M34:M38)+M39

Sheet CW_Net_Position
A1: City of El Cerrito - CITYWIDE (governmental activities)
A2: Statement of Net Position, June 30, $ - includes buildings/equipment/infrastructure, long-term debt and pension liabilities
A3: Full-accrual government-wide statement, GOVERNMENTAL ACTIVITIES column (all governmental funds + internal service fund; excludes the business-type Integrated Waste Management fund). FY2025-26 not yet published (ACFR expected Dec 2026).
A6: June 30 | B6: 2014 | C6: 2015 | D6: 2016 | E6: 2017 | F6: 2018 | G6: 2019 | H6: 2020 | I6: 2021 | J6: 2022 | K6: 2023 | L6: 2024 | M6: 2025
A7: ASSETS
A8: Cash and investments (incl. with fiscal agents) | B8: 1931237 | C8: 1626978 | D8: 9713164 | E8: 7038065 | F8: 7901998 | G8: 8993498 | H8: 15359295 | I8: 20474360 | J8: 32335230 | K8: 35051633 | L8: 37196758 | M8: 38478939
A9: Receivables (accounts, interest, due from other governments) | B9: 5145010 | C9: 3996830 | D9: 2621587 | E9: 3875442 | F9: 4377744 | G9: 4261488 | H9: 3828553 | I9: 7479436 | J9: 5528236 | K9: 7265183 | L9: 8348372 | M9: 11071210
A10: Loans receivable | B10: 5697959 | C10: 8169459 | D10: 8521590 | E10: 7677273 | F10: 7531495 | G10: 7293486 | H10: 7238519 | I10: 7351152 | J10: 7451152 | K10: 7527427 | L10: 8041087 | M10: 9025108
A11: Other assets (inventory, prepaids, internal balances, land held for resale, due from Successor Agency) | B11: 4249710 | C11: 4329359 | D11: 4513976 | E11: 5689011 | F11: 5895357 | G11: 2879392 | H11: 2673608 | I11: 25694 | J11: 356339 | K11: 264865 | L11: 316356 | M11: 323124
A12: Capital assets - non-depreciable (land, construction in progress) | B12: 8050390 | C12: 9739689 | D12: 11701821 | E12: 5820229 | F12: 6770055 | G12: 10159537 | H12: 5866775 | I12: 5989656 | J12: 11128309 | K12: 11826429 | L12: 13041173 | M12: 17158178
A13: Capital assets - depreciable (buildings, equipment, infrastructure), net | B13: 77016693 | C13: 73405129 | D13: 69565283 | E13: 74208670 | F13: 71074895 | G13: 63621090 | H13: 65685505 | I13: 63560656 | J13: 57222362 | K13: 55525441 | L13: 56394492 | M13: 58035209
A14: Total assets | B14: =SUM(B8:B13) | C14: =SUM(C8:C13) | D14: =SUM(D8:D13) | E14: =SUM(E8:E13) | F14: =SUM(F8:F13) | G14: =SUM(G8:G13) | H14: =SUM(H8:H13) | I14: =SUM(I8:I13) | ... M14: =SUM(M8:M13)
A16: DEFERRED OUTFLOWS OF RESOURCES
A17: Pension and OPEB related | B17: 0 | C17: 3700898 | D17: 7649080 | E17: 15420498 | F17: 17370124 | G17: 15482724 | H17: 15758883 | I17: 16312126 | J17: 16073123 | K17: 32955886 | L17: 32242338 | M17: 25367164
A18: Deferred loss on refunding / other | B18: 0 | C18: 0 | D18: 0 | E18: 514127 | F18: 487048 | G18: 459969 | H18: 432890 | I18: 405811 | J18: 247035 | K18: 229363 | L18: 211691 | M18: 194019
A19: Total deferred outflows | B19: =SUM(B17:B18) | C19: =SUM(C17:C18) | D19: =SUM(D17:D18) | E19: =SUM(E17:E18) | F19: =SUM(F17:F18) | G19: =SUM(G17:G18) | H19: =SUM(H17:H18) | I19: =SUM(I17:I18) | ... M19: =SUM(M17:M18)
A21: LIABILITIES
A22: Accounts payable, accrued, interest, deposits, unearned | B22: 4358931 | C22: 2472333 | D22: 2492167 | E22: 2972475 | F22: 3519430 | G22: 3706752 | H22: 5109131 | I22: 3805129 | J22: 5892119 | K22: 8308406 | L22: 7703100 | M22: 9457059
A23: Short-term note payable (TRAN) | B23: 0 | C23: 0 | D23: 5000000 | E23: 5000000 | F23: 6000000 | G23: 6000000 | H23: 9000000 | I23: 8659545 | J23: 6060892 | K23: 0 | L23: 0 | M23: 0
A24: Compensated absences | B24: 1541015 | C24: 1335398 | D24: 1454048 | E24: 1662426 | F24: 1874601 | G24: 2026530 | H24: 2382150 | I24: 2630077 | J24: 2504516 | K24: 1716023 | L24: 1874503 | M24: 2741774
A25: Claims payable | B25: 57349 | C25: 90418 | D25: 375006 | E25: 13827 | F25: 21402 | G25: 36165 | H25: 28741 | I25: 15000 | J25: 15000 | K25: 23968 | L25: 18453 | M25: 20625
A26: Long-term debt (bonds, COPs, loans, leases/financed purchases) | B26: 23212392 | C26: 22181119 | D26: 21120338 | E26: 20100647 | F26: 19219685 | G26: 18129809 | H26: 17196617 | I26: 16162563 | J26: 16521684 | K26: 15526985 | L26: 14064485 | M26: 13929123
A27: Net OPEB liability (retiree health) | B27: 1573570 | C27: 1867190 | D27: 2160810 | E27: 2454430 | F27: 2845887 | G27: 2994539 | H27: 3906161 | I27: 4887434 | J27: 0 | K27: 0 | L27: 0 | M27: 0
A28: Net pension liability (CalPERS) | B28: 0 | C28: 39314773 | D28: 45992107 | E28: 54843657 | F28: 61775131 | G28: 61856499 | H28: 65832700 | I28: 70374424 | J28: 48950390 | K28: 79526924 | L28: 80740039 | M28: 79676034
A29: Total liabilities | B29: =SUM(B22:B28) | C29: =SUM(C22:C28) | D29: =SUM(D22:D28) | E29: =SUM(E22:E28) | F29: =SUM(F22:F28) | G29: =SUM(G22:G28) | H29: =SUM(H22:H28) | I29: =SUM(I22:I28) | ... M29: =SUM(M22:M28)
A31: DEFERRED INFLOWS OF RESOURCES
A32: Pension and OPEB related | B32: 0 | C32: 8600729 | D32: 4112085 | E32: 1982244 | F32: 906925 | G32: 2762962 | H32: 2803196 | I32: 893047 | J32: 34808663 | K32: 5658874 | L32: 3599218 | M32: 2513353
A33: Deferred gain on refunding / leases / other | B33: 0 | C33: 0 | D33: 0 | E33: 178732 | F33: 169325 | G33: 159918 | H33: 150511 | I33: 141104 | J33: 0 | K33: 0 | L33: 0 | M33: 0
A34: Total deferred inflows | B34: =SUM(B32:B33) | C34: =SUM(C32:C33) | D34: =SUM(D32:D33) | E34: =SUM(E32:E33) | F34: =SUM(F32:F33) | G34: =SUM(G32:G33) | H34: =SUM(H32:H33) | I34: =SUM(I32:I33) | ... M34: =SUM(M32:M33)
A36: NET POSITION
A37: Net position (assets + deferred outflows - liabilities - deferred inflows) | B37: =B14+B19-B29-B34 | C37: =C14+C19-C29-C34 | D37: =D14+D19-D29-D34 | E37: =E14+E19-E29-E34 | F37: =F14+F19-F29-F34 | G37: =G14+G19-G29-G34 | H37: =H14+H19-H29-H34 | I37: =I14+I19-I29-I34 | ... M37: =M14+M19-M29-M34
A38: of which: Net investment in capital assets | B38: 63535927 | C38: 62485398 | D38: 61687197 | E38: 60263647 | F38: 58942988 | G38: 55950869 | H38: 54638042 | I38: 53652456 | J38: 53377263 | K38: 53389633 | L38: 56361576 | M38: 61458283
A39: of which: Restricted | B39: 11556030 | C39: 15211282 | D39: 16401240 | E39: 16468323 | F39: 17041501 | G39: 14225506 | H39: 15240589 | I39: 15859381 | J39: 16029304 | K39: 17767175 | L39: 21667676 | M39: 25607946
A40: of which: Unrestricted | B40: -3744215 | C40: -48590298 | D40: -46508497 | E40: -45697093 | F40: -50908159 | G40: -54698365 | H40: -59443810 | I40: -55481269 | J40: -53818045 | K40: -31271761 | L40: -30236783 | M40: -35751246
A42: KEY MEASURES
A43: Capital assets, net (buildings, equipment, infrastructure, land, CIP) | B43: =B12+B13 | C43: =C12+C13 | D43: =D12+D13 | E43: =E12+E13 | F43: =F12+F13 | G43: =G12+G13 | H43: =H12+H13 | I43: =I12+I13 | ... M43: =M12+M13
A44: Long-term debt + compensated absences + claims | B44: =B26+B24+B25 | C44: =C26+C24+C25 | D44: =D26+D24+D25 | E44: =E26+E24+E25 | F44: =F26+F24+F25 | G44: =G26+G24+G25 | H44: =H26+H24+H25 | I44: =I26+I24+I25 | ... M44: =M26+M24+M25
A45: Net pension + OPEB liability | B45: =B28+B27 | C45: =C28+C27 | D45: =D28+D27 | E45: =E28+E27 | F45: =F28+F27 | G45: =G28+G27 | H45: =H28+H27 | I45: =I28+I27 | ... M45: =M28+M27
A46: Net pension/OPEB deferrals (outflows - inflows) | B46: =B17-B32 | C46: =C17-C32 | D46: =D17-D32 | E46: =E17-E32 | F46: =F17-F32 | G46: =G17-G32 | H46: =H17-H32 | I46: =I17-I32 | ... M46: =M17-M32
A47: Net position excluding pension/OPEB liability and deferrals | B47: =B37+B45-B46 | C47: =C37+C45-C46 | D47: =D37+D45-D46 | E47: =E37+E45-E46 | F47: =F37+F45-F46 | G47: =G37+G45-G46 | H47: =H37+H45-H46 | I47: =I37+I45-I46 | ... M47: =M37+M45-M46
A48: Change in net position vs. prior year (incl. restatements) | B48: =0 | C48: =C37-B37 | D48: =D37-C37 | E48: =E37-D37 | F48: =F37-E37 | G48: =G37-F37 | H48: =H37-G37 | I48: =I37-H37 | J48: =J37-I37 | ... M48: =M37-L37
A50: Check: total assets per ACFR | B50: 102090999 | C50: 101267444 | D50: 106637421 | E50: 104308690 | F50: 103551544 | G50: 97208491 | H50: 100652255 | I50: 104880954 | J50: 114021628 | K50: 117460978 | L50: 123338238 | M50: 134091768
A51: Check: total liabilities per ACFR | B51: 30743257 | C51: 67261231 | D51: 78594476 | E51: 87047462 | F51: 95256136 | G51: 94750294 | H51: 103455500 | I51: 106534172 | J51: 79944601 | K51: 105102306 | L51: 104400580 | M51: 105824615
A52: Check: net position per ACFR | B52: 71347742 | C52: 29106382 | D52: 31579940 | E52: 31034877 | F52: 25076330 | G52: 15478010 | H52: 10434821 | I52: 14030568 | J52: 15588522 | K52: 39885047 | L52: 47792469 | M52: 51314983
A53: Check: assets - ACFR (should be 0) | B53: =B14-B50 | C53: =C14-C50 | D53: =D14-D50 | E53: =E14-E50 | F53: =F14-F50 | G53: =G14-G50 | H53: =H14-H50 | I53: =I14-I50 | ... M53: =M14-M50
A54: Check: liabilities - ACFR (should be 0) | B54: =B29-B51 | C54: =C29-C51 | D54: =D29-D51 | E54: =E29-E51 | F54: =F29-F51 | G54: =G29-G51 | H54: =H29-H51 | I54: =I29-I51 | ... M54: =M29-M51
A55: Check: net position - ACFR (should be 0) | B55: =B37-B52 | C55: =C37-C52 | D55: =D37-D52 | E55: =E37-E52 | F55: =F37-F52 | G55: =G37-G52 | H55: =H37-H52 | I55: =I37-I52 | ... M55: =M37-M52
A56: Check: net position components - total (should be 0) | B56: =B38+B39+B40-B37 | C56: =C38+C39+C40-C37 | D56: =D38+D39+D40-D37 | E56: =E38+E39+E40-E37 | F56: =F38+F39+F40-F37 | G56: =G38+G39+G40-G37 | H56: =H38+H39+H40-H37 | I56: =I38+I39+I40-I37 | ... M56: =M38+M39+M40-M37
A58: LONG-TERM LIABILITIES: DUE WITHIN ONE YEAR / DUE IN MORE THAN ONE YEAR (GASB 34 classification)
A59: Compensated absences - due within one year | B59: 1136268 | C59: 1037005 | D59: 951000 | E59: 1080577 | F59: 1218491 | G59: 1317245 | H59: 1548397 | I59: 1709550 | J59: 1627935 | K59: 1115415 | L59: 1218427 | M59: 1782153
A60: Compensated absences - due in more than one year | B60: =B24-B59 | C60: =C24-C59 | D60: =D24-D59 | E60: =E24-E59 | F60: =F24-F59 | G60: =G24-G59 | H60: =H24-H59 | I60: =I24-I59 | ... M60: =M24-M59
A61: Claims payable - due within one year | B61: 12500 | C61: 17600 | D61: 151106 | E61: 5571 | F61: 8623 | G61: 14571 | H61: 11580 | I61: 6000 | J61: 0 | K61: 0 | L61: 0 | M61: 0
A62: Claims payable - due in more than one year | B62: =B25-B61 | C62: =C25-C61 | D62: =D25-D61 | E62: =E25-E61 | F62: =F25-F61 | G62: =G25-G61 | H62: =H25-H61 | I62: =I25-I61 | ... M62: =M25-M61
A63: Long-term debt - due within one year | B63: 1031273 | C63: 1060781 | D63: 1089599 | E63: 877924 | F63: 1181134 | G63: 1154302 | H63: 1010505 | I63: 847435 | J63: 1087738 | K63: 986911 | L63: 968015 | M63: 1243191
A64: Long-term debt - due in more than one year | B64: =B26-B63 | C64: =C26-C63 | D64: =D26-D63 | E64: =E26-E63 | F64: =F26-F63 | G64: =G26-G63 | H64: =H26-H63 | I64: =I26-I63 | ... M64: =M26-M63
A65: Net pension liability and OPEB - due in more than one year | B65: =B28+B27 | C65: =C28+C27 | D65: =D28+D27 | E65: =E28+E27 | F65: =F28+F27 | G65: =G28+G27 | H65: =H28+H27 | I65: =I28+I27 | ... M65: =M28+M27
A66: Total long-term liabilities due within one year | B66: =B59+B61+B63 | C66: =C59+C61+C63 | D66: =D59+D61+D63 | E66: =E59+E61+E63 | F66: =F59+F61+F63 | G66: =G59+G61+G63 | H66: =H59+H61+H63 | I66: =I59+I61+I63 | ... M66: =M59+M61+M63

Sheet CW_Statement_of_Activities
A1: City of El Cerrito - CITYWIDE (governmental activities)
A2: Statement of Activities / Changes in Net Position, $ (full accrual, GASB 34)
A3: Expenses by function, program revenues, general revenues and change in net position. Source: ACFR statistical table 'Changes in Net Position' (FY2025 ACFR Table 2 for FY2016-FY2025; FY2017 CAFR table for FY2014-FY2015). Business-type activities excluded.
A6: Fiscal year ended June 30 | B6: 2014 | C6: 2015 | D6: 2016 | E6: 2017 | F6: 2018 | G6: 2019 | H6: 2020 | I6: 2021 | J6: 2022 | K6: 2023 | L6: 2024 | M6: 2025
A7: EXPENSES
A8: General government | B8: 5637571 | C8: 4218763 | D8: 4791816 | E8: 5138555 | F8: 5758535 | G8: 6723883 | H8: 6853922 | I8: 5811523 | J8: 7884210 | K8: 4892654 | L8: 8271822 | M8: 8947901
A9: Public works | B9: 5444248 | C9: 5576671 | D9: 5276434 | E9: 7296766 | F9: 8956800 | G9: 8800985 | H9: 8041340 | I9: 7677819 | J9: 9260749 | K9: 6244845 | L9: 9122950 | M9: 9702125
A10: Recreation | B10: 4597225 | C10: 4629731 | D10: 4838539 | E10: 5335946 | F10: 6319879 | G10: 6852784 | H10: 6579645 | I10: 4691509 | J10: 6089667 | K10: 3896266 | L10: 6999666 | M10: 7682753
A11: Community development | B11: 6121329 | C11: 2208566 | D11: 2094643 | E11: 2867664 | F11: 2877501 | G11: 2683918 | H11: 2881181 | I11: 3452703 | J11: 4262818 | K11: 2376676 | L11: 4530222 | M11: 4472171
A12: Public safety | B12: 18767955 | C12: 18924124 | D12: 18620431 | E12: 20310165 | F12: 24291518 | G12: 26250994 | H12: 26853126 | I12: 26208413 | J12: 30989792 | K12: 16455373 | L12: 29383735 | M12: 34272713
A13: Interest on long-term debt | B13: 904001 | C13: 880173 | D13: 845437 | E13: 982440 | F13: 852986 | G13: 837272 | H13: 844041 | I13: 879070 | J13: 716380 | K13: 630504 | L13: 166298 | M13: 541187
A14: Total expenses | B14: =SUM(B8:B13) | C14: =SUM(C8:C13) | D14: =SUM(D8:D13) | E14: =SUM(E8:E13) | F14: =SUM(F8:F13) | G14: =SUM(G8:G13) | H14: =SUM(H8:H13) | I14: =SUM(I8:I13) | ... M14: =SUM(M8:M13)
A16: PROGRAM REVENUES
A17: Charges for services:
A18: General government | B18: 106677 | C18: 109345 | D18: 137038 | E18: 1096168 | F18: 1116938 | G18: 983618 | H18: 947409 | I18: 1037096 | J18: 547024 | K18: 480288 | L18: 468692 | M18: 1612875
A19: Public works | B19: 976032 | C19: 987537 | D19: 514039 | E19: 331297 | F19: 433727 | G19: 453911 | H19: 317062 | I19: 410676 | J19: 593215 | K19: 557706 | L19: 735339 | M19: 501889
A20: Recreation | B20: 3221674 | C20: 3285398 | D20: 3112985 | E20: 3611541 | F20: 3785511 | G20: 4385622 | H20: 3108433 | I20: 2142292 | J20: 3932395 | K20: 4398223 | L20: 4958617 | M20: 5799134
A21: Community development | B21: 1731668 | C21: 1132299 | D21: 1439678 | E21: 1848830 | F21: 1813313 | G21: 1917141 | H21: 1841512 | I21: 1756009 | J21: 3096993 | K21: 2673576 | L21: 2896914 | M21: 2564550
A22: Public safety | B22: 2880896 | C22: 2793410 | D22: 2819113 | E22: 3048763 | F22: 3504858 | G22: 3437116 | H22: 3522587 | I22: 3746725 | J22: 4093311 | K22: 4526164 | L22: 4709908 | M22: 4762457
A23: Operating grants and contributions | B23: 3067489 | C23: 2762749 | D23: 2496255 | E23: 1942080 | F23: 2410442 | G23: 3534462 | H23: 2329117 | I23: 5632909 | J23: 4797917 | K23: 1437171 | L23: 1550711 | M23: 3368275
A24: Capital grants and contributions | B24: 3637043 | C24: 3677475 | D24: 1573560 | E24: 2039912 | F24: 3013832 | G24: 5093007 | H24: 2767468 | I24: 3317784 | J24: 1280680 | K24: 1709112 | L24: 4841678 | M24: 6796593
A25: Total program revenues | B25: =SUM(B17:B24) | C25: =SUM(C17:C24) | D25: =SUM(D17:D24) | E25: =SUM(E17:E24) | F25: =SUM(F17:F24) | G25: =SUM(G17:G24) | H25: =SUM(H17:H24) | I25: =SUM(I17:I24) | ... M25: =SUM(M17:M24)
A27: Net (expense) revenue | B27: =B25-B14 | C27: =C25-C14 | D27: =D25-D14 | E27: =E25-E14 | F27: =F25-F14 | G27: =G25-G14 | H27: =H25-H14 | I27: =I25-I14 | ... M27: =M25-M14
A29: GENERAL REVENUES, SPECIAL ITEMS AND TRANSFERS
A30: Property taxes | B30: 9024435 | C30: 9927028 | D30: 11211539 | E30: 12770037 | F30: 13360216 | G30: 14242520 | H30: 14381441 | I30: 15213912 | J30: 16683058 | K30: 17813125 | L30: 18503332 | M30: 18892277
A31: Sales taxes | B31: 6554589 | C31: 6408016 | D31: 7234366 | E31: 7477393 | F31: 8215732 | G31: 8318511 | H31: 8134818 | I31: 9708892 | J31: 9671196 | K31: 12110514 | L31: 11457300 | M31: 12142660
A32: Transient occupancy taxes | B32: 130556 | C32: 114712 | D32: 139084 | E32: 134171 | F32: 145489 | G32: 147550 | H32: 118891 | I32: 126164 | J32: 113434 | K32: 107817 | L32: 89451 | M32: 115058
A33: Franchise and other taxes | B33: 1228307 | C33: 1376771 | D33: 1453351 | E33: 1375048 | F33: 1279037 | G33: 1244897 | H33: 1637666 | I33: 1364257 | J33: 1181509 | K33: 1604218 | L33: 1854938 | M33: 1587267
A34: Business license taxes | B34: 768448 | C34: 722130 | D34: 787122 | E34: 775413 | F34: 846900 | G34: 910104 | H34: 918799 | I34: 924358 | J34: 1040618 | K34: 1069964 | L34: 1128561 | M34: 1176343
A35: Utility users taxes | B35: 3137017 | C35: 3106232 | D35: 3291255 | E35: 3360277 | F35: 2965675 | G35: 3207892 | H35: 3165974 | I35: 3444484 | J35: 3403776 | K35: 4100286 | L35: 4015551 | M35: 4206762
A36: Real property transfer tax | B36: 0 | C36: 0 | D36: 0 | E36: 0 | F36: 0 | G36: 1102563 | H36: 3467532 | I36: 4419107 | J36: 4863035 | K36: 4157840 | L36: 3129523 | M36: 3207242
A37: Other taxes | B37: 129774 | C37: 144539 | D37: 180447 | E37: 154863 | F37: 147623 | G37: 1935 | H37: 2811 | I37: 213044 | J37: 581641 | K37: 706695 | L37: 805437 | M37: 57
A38: Investment earnings and other | B38: 1263663 | C38: 1548232 | D38: 2640631 | E38: 481324 | F38: 300264 | G38: 340572 | H38: 344875 | I38: 176593 | J38: 1146385 | K38: 1887516 | L38: 2920338 | M38: 2404254
A39: Transfers | B39: 327371 | C39: 346319 | D39: 356418 | E39: 9671 | F39: 9671 | G39: 3671 | H39: 3671 | I39: 3671 | J39: 3671 | K39: 3671 | L39: 3671 | M39: 3671
A40: Special items | B40: 0 | C40: 0 | D40: 0 | E40: 0 | F40: 0 | G40: -6773576 | H40: 0 | I40: -1321189 | J40: 0 | K40: 0 | L40: 0 | M40: 0
A41: Total general revenues, special items and transfers | B41: =SUM(B30:B40) | C41: =SUM(C30:C40) | D41: =SUM(D30:D40) | E41: =SUM(E30:E40) | F41: =SUM(F30:F40) | G41: =SUM(G30:G40) | H41: =SUM(H30:H40) | I41: =SUM(I30:I40) | ... M41: =SUM(M30:M40)
A43: Change in net position | B43: =B27+B41 | C43: =C27+C41 | D43: =D27+D41 | E43: =E27+E41 | F43: =F27+F41 | G43: =G27+G41 | H43: =H27+H41 | I43: =I27+I41 | ... M43: =M27+M41
A45: Net position - beginning, as previously reported | C45: =CW_Net_Position!B37 | D45: =CW_Net_Position!C37 | E45: =CW_Net_Position!D37 | F45: =CW_Net_Position!E37 | G45: =CW_Net_Position!F37 | H45: =CW_Net_Position!G37 | I45: =CW_Net_Position!H37 | J45: =CW_Net_Position!I37 | ... M45: =CW_Net_Position!L37
A46: Restatements / accounting changes (computed) | C46: =C48-C45-C43 | D46: =D48-D45-D43 | E46: =E48-E45-E43 | F46: =F48-F45-F43 | G46: =G48-G45-G43 | H46: =H48-H45-H43 | I46: =I48-I45-I43 | J46: =J48-J45-J43 | ... M46: =M48-M45-M43
A47: Net position - beginning, as restated | C47: =C45+C46 | D47: =D45+D46 | E47: =E45+E46 | F47: =F45+F46 | G47: =G45+G46 | H47: =H45+H46 | I47: =I45+I46 | J47: =J45+J46 | ... M47: =M45+M46
A48: Net position - ending (CW_Net_Position) | B48: =CW_Net_Position!B37 | C48: =CW_Net_Position!C37 | D48: =CW_Net_Position!D37 | E48: =CW_Net_Position!E37 | F48: =CW_Net_Position!F37 | G48: =CW_Net_Position!G37 | H48: =CW_Net_Position!H37 | I48: =CW_Net_Position!I37 | ... M48: =CW_Net_Position!M37
A50: MEASURES
A51: Program revenues as % of expenses (self-supporting share) | B51: =IFERROR(B25/B14,0) | C51: =IFERROR(C25/C14,0) | D51: =IFERROR(D25/D14,0) | E51: =IFERROR(E25/E14,0) | F51: =IFERROR(F25/F14,0) | G51: =IFERROR(G25/G14,0) | H51: =IFERROR(H25/H14,0) | I51: =IFERROR(I25/I14,0) | ... M51: =IFERROR(M25/M14,0)
A52: Public safety as % of expenses | B52: =IFERROR(B12/B14,0) | C52: =IFERROR(C12/C14,0) | D52: =IFERROR(D12/D14,0) | E52: =IFERROR(E12/E14,0) | F52: =IFERROR(F12/F14,0) | G52: =IFERROR(G12/G14,0) | H52: =IFERROR(H12/H14,0) | I52: =IFERROR(I12/I14,0) | ... M52: =IFERROR(M12/M14,0)
A53: Taxes as % of general revenues | B53: =IFERROR(SUM(B30:B37)/B41,0) | C53: =IFERROR(SUM(C30:C37)/C41,0) | D53: =IFERROR(SUM(D30:D37)/D41,0) | E53: =IFERROR(SUM(E30:E37)/E41,0) | F53: =IFERROR(SUM(F30:F37)/F41,0) | G53: =IFERROR(SUM(G30:G37)/G41,0) | H53: =IFERROR(SUM(H30:H37)/H41,0) | I53: =IFERROR(SUM(I30:I37)/I41,0) | ... M53: =IFERROR(SUM(M30:M37)/M41,0)
A55: Check: total expenses vs. ACFR (should be 0) | B55: =B14-41472329 | C55: =C14-36438028 | D55: =D14-36467300 | E55: =E14-41931536 | F55: =F14-49057219 | G55: =G14-52149836 | H55: =H14-52053255 | I55: =I14-48721037 | J55: =J14-59203616 | K55: =K14-34496318 | L55: =L14-58474693 | M55: =M14-65618850
A56: Check: program revenues vs. ACFR (should be 0) | B56: =B25-15621479 | C56: =C25-14748213 | D56: =D25-12092668 | E56: =E25-13918591 | F56: =F25-16078621 | G56: =G25-19804877 | H56: =H25-14833588 | I56: =I25-18043491 | J56: =J25-18341535 | K56: =K25-15782240 | L56: =L25-20161859 | M56: =M25-25405773
A57: Check: general revenues vs. ACFR (should be 0) | B57: =B41-22564160 | C57: =C41-23693979 | D57: =D41-27294213 | E57: =E41-26538197 | F57: =F41-27270607 | G57: =G41-22746639 | H57: =H41-32176478 | I57: =I41-34273293 | J57: =J41-38688323 | K57: =K41-43561646 | L57: =L41-43908102 | M57: =M41-43735591
A58: Check: change in net position vs. ACFR (should be 0) | B58: =B43--3286690 | C58: =C43-2004164 | D58: =D43-2919581 | E58: =E43--1474748 | F58: =F43--5707991 | G58: =G43--9598320 | H58: =H43--5043189 | I58: =I43-3595747 | J58: =J43--2173758 | K58: =K43-24847568 | L58: =L43-5595268 | M58: =M43-3522514
A60: NET (EXPENSE) REVENUE BY FUNCTION (basic Statement of Activities format)
A61: General government
A62: Operating grants and contributions | B62: 47941 | C62: 72516 | D62: 11767 | E62: 1790 | F62: 1440 | G62: 600 | H62: 350 | I62: 3359126 | J62: 3051028 | K62: 0 | L62: 0 | M62: 658813
A63: Capital grants and contributions | B63: 0 | C63: 2586000 | D63: 0 | E63: 0 | F63: 0 | G63: 0 | H63: 0 | I63: 0 | J63: 0 | K63: 0 | L63: 0 | M63: 0
A64: Net (expense) revenue | B64: =B18+B62+B63-B8 | C64: =C18+C62+C63-C8 | D64: =D18+D62+D63-D8 | E64: =E18+E62+E63-E8 | F64: =F18+F62+F63-F8 | G64: =G18+G62+G63-G8 | H64: =H18+H62+H63-H8 | I64: =I18+I62+I63-I8 | ... M64: =M18+M62+M63-M8
A65: Public works
A66: Operating grants and contributions | B66: 1517112 | C66: 1466138 | D66: 1288043 | E66: 537675 | F66: 597016 | G66: 1864450 | H66: 1031171 | I66: 404508 | J66: 404597 | K66: 332996 | L66: 300469 | M66: 332501
A67: Capital grants and contributions | B67: 2606487 | C67: 1007571 | D67: 1573560 | E67: 2030912 | F67: 2805400 | G67: 5122545 | H67: 2744098 | I67: 3317784 | J67: 1280680 | K67: 1709112 | L67: 4841678 | M67: 6733923
A68: Net (expense) revenue | B68: =B19+B66+B67-B9 | C68: =C19+C66+C67-C9 | D68: =D19+D66+D67-D9 | E68: =E19+E66+E67-E9 | F68: =F19+F66+F67-F9 | G68: =G19+G66+G67-G9 | H68: =H19+H66+H67-H9 | I68: =I19+I66+I67-I9 | ... M68: =M19+M66+M67-M9
A69: Recreation
A70: Operating grants and contributions | B70: 160125 | C70: 168516 | D70: 182217 | E70: 47382 | F70: 41365 | G70: 26934 | H70: 22958 | I70: 384569 | J70: 0 | K70: 0 | L70: 0 | M70: 56222
A71: Capital grants and contributions | B71: 0 | C71: 0 | D71: 0 | E71: 9000 | F71: 174240 | G71: 4591 | H71: 23370 | I71: 0 | J71: 0 | K71: 0 | L71: 0 | M71: 0
A72: Net (expense) revenue | B72: =B20+B70+B71-B10 | C72: =C20+C70+C71-C10 | D72: =D20+D70+D71-D10 | E72: =E20+E70+E71-E10 | F72: =F20+F70+F71-F10 | G72: =G20+G70+G71-G10 | H72: =H20+H70+H71-H10 | I72: =I20+I70+I71-I10 | ... M72: =M20+M70+M71-M10
A73: Community development
A74: Operating grants and contributions | B74: 637464 | C74: 23000 | D74: 227101 | E74: 75 | F74: 536 | G74: 62679 | H74: 140 | I74: 5703 | J74: 0 | K74: 140509 | L74: 396686 | M74: 406936
A75: Capital grants and contributions | B75: 84643 | C75: 0 | D75: 0 | E75: 0 | F75: 34192 | G75: -34129 | H75: 0 | I75: 0 | J75: 0 | K75: 0 | L75: 0 | M75: 62670
A76: Net (expense) revenue | B76: =B21+B74+B75-B11 | C76: =C21+C74+C75-C11 | D76: =D21+D74+D75-D11 | E76: =E21+E74+E75-E11 | F76: =F21+F74+F75-F11 | G76: =G21+G74+G75-G11 | H76: =H21+H74+H75-H11 | I76: =I21+I74+I75-I11 | ... M76: =M21+M74+M75-M11
A77: Public safety
A78: Operating grants and contributions | B78: 704847 | C78: 1032579 | D78: 787127 | E78: 1355158 | F78: 1770085 | G78: 1579799 | H78: 1274498 | I78: 1479003 | J78: 1342292 | K78: 963666 | L78: 853556 | M78: 1913803
A79: Capital grants and contributions | B79: 945913 | C79: 83904 | D79: 0 | E79: 0 | F79: 0 | G79: 0 | H79: 0 | I79: 0 | J79: 0 | K79: 0 | L79: 0 | M79: 0
A80: Net (expense) revenue | B80: =B22+B78+B79-B12 | C80: =C22+C78+C79-C12 | D80: =D22+D78+D79-D12 | E80: =E22+E78+E79-E12 | F80: =F22+F78+F79-F12 | G80: =G22+G78+G79-G12 | H80: =H22+H78+H79-H12 | I80: =I22+I78+I79-I12 | ... M80: =M22+M78+M79-M12
A81: Interest on long-term debt - net expense | B81: =-B13 | C81: =-C13 | D81: =-D13 | E81: =-E13 | F81: =-F13 | G81: =-G13 | H81: =-H13 | I81: =-I13 | ... M81: =-M13
A82: Total net (expense) revenue by function | B82: =B64+B68+B72+B76+B80+B81 | C82: =C64+C68+C72+C76+C80+C81 | D82: =D64+D68+D72+D76+D80+D81 | E82: =E64+E68+E72+E76+E80+E81 | F82: =F64+F68+F72+F76+F80+F81 | G82: =G64+G68+G72+G76+G80+G81 | H82: =H64+H68+H72+H76+H80+H81 | I82: =I64+I68+I72+I76+I80+I81 | ... M82: =M64+M68+M72+M76+M80+M81
A83: Check: equals net (expense) revenue above (should be 0) | B83: =B82-B27 | C83: =C82-C27 | D83: =D82-D27 | E83: =E82-E27 | F83: =F82-F27 | G83: =G82-G27 | H83: =H82-H27 | I83: =I82-I27 | ... M83: =M82-M27
A84: Check: operating grants by function vs. total (should be 0) | B84: =B62+B66+B70+B74+B78-B23 | C84: =C62+C66+C70+C74+C78-C23 | D84: =D62+D66+D70+D74+D78-D23 | E84: =E62+E66+E70+E74+E78-E23 | F84: =F62+F66+F70+F74+F78-F23 | G84: =G62+G66+G70+G74+G78-G23 | H84: =H62+H66+H70+H74+H78-H23 | I84: =I62+I66+I70+I74+I78-I23 | ... M84: =M62+M66+M70+M74+M78-M23
A85: Check: capital grants by function vs. total (should be 0) | B85: =B63+B67+B71+B75+B79-B24 | C85: =C63+C67+C71+C75+C79-C24 | D85: =D63+D67+D71+D75+D79-D24 | E85: =E63+E67+E71+E75+E79-E24 | F85: =F63+F67+F71+F75+F79-F24 | G85: =G63+G67+G71+G75+G79-G24 | H85: =H63+H67+H71+H75+H79-H24 | I85: =I63+I67+I71+I75+I79-I24 | ... M85: =M63+M67+M71+M75+M79-M24
A86: Public safety: share of cost paid by general revenues | B86: =IFERROR(-B80/B12,0) | C86: =IFERROR(-C80/C12,0) | D86: =IFERROR(-D80/D12,0) | E86: =IFERROR(-E80/E12,0) | F86: =IFERROR(-F80/F12,0) | G86: =IFERROR(-G80/G12,0) | H86: =IFERROR(-H80/H12,0) | I86: =IFERROR(-I80/I12,0) | ... M86: =IFERROR(-M80/M12,0)

Sheet CW_Capital_Assets
A1: City of El Cerrito - CITYWIDE (governmental activities)
A2: Capital assets (buildings, equipment, infrastructure), June 30, $
A3: Historical cost by class less accumulated depreciation. Source: MD&A capital asset table / capital assets note in each CAFR/ACFR.
A6: June 30 | B6: 2014 | C6: 2015 | D6: 2016 | E6: 2017 | F6: 2018 | G6: 2019 | H6: 2020 | I6: 2021 | J6: 2022 | K6: 2023 | L6: 2024 | M6: 2025
A7: AT HISTORICAL COST
A8: Land | B8: 4410941 | C8: 4888926 | D8: 4888926 | E8: 4888926 | F8: 4888926 | G8: 4888926 | H8: 4888926 | I8: 5191639 | J8: 5191639 | K8: 5191639 | L8: 6792165 | M8: 6792165
A9: Construction in progress | B9: 3639449 | C9: 4850763 | D9: 6812895 | E9: 931303 | F9: 1881129 | G9: 5270611 | H9: 977849 | I9: 798016 | J9: 3198707 | K9: 4334851 | L9: 6249008 | M9: 10366013
A10: Buildings and improvements | B10: 36125237 | C10: 36125237 | D10: 36125237 | E10: 32861756 | F10: 32923796 | G10: 27408552 | H10: 27408552 | I10: 27408552 | J10: 27408552 | K10: 27463510 | L10: 27058747 | M10: 28892209
A11: Equipment and vehicles (incl. right-of-use) | B11: 10756019 | C11: 10790917 | D11: 10946416 | E11: 5754072 | F11: 5939358 | G11: 6248620 | H11: 6613690 | I11: 6694533 | J11: 7338161 | K11: 6404496 | L11: 6609698 | M11: 8905461
A12: Infrastructure (streets, storm drains, etc.) | B12: 87798766 | C12: 88237020 | D12: 88253560 | E12: 77388399 | F12: 78460253 | G12: 79213482 | H12: 84950163 | I12: 86769509 | J12: 86769509 | K12: 88122931 | L12: 90120903 | M12: 91253716
A13: Total capital assets at cost | B13: =SUM(B8:B12) | C13: =SUM(C8:C12) | D13: =SUM(D8:D12) | E13: =SUM(E8:E12) | F13: =SUM(F8:F12) | G13: =SUM(G8:G12) | H13: =SUM(H8:H12) | I13: =SUM(I8:I12) | ... M13: =SUM(M8:M12)
A14: Less: accumulated depreciation and amortization | B14: -57663329 | C14: -61748045 | D14: -65759930 | E14: -41795557 | F14: -46248512 | G14: -49249564 | H14: -53286900 | I14: -57311937 | J14: -61555897 | K14: -64165557 | L14: -67394856 | M14: -71016177
A15: Capital assets, net | B15: =B13+B14 | C15: =C13+C14 | D15: =D13+D14 | E15: =E13+E14 | F15: =F13+F14 | G15: =G13+G14 | H15: =H13+H14 | I15: =I13+I14 | ... M15: =M13+M14
A17: MEMO
A18: Depreciable assets at cost (buildings, equipment, infrastructure) | B18: =B10+B11+B12 | C18: =C10+C11+C12 | D18: =D10+D11+D12 | E18: =E10+E11+E12 | F18: =F10+F11+F12 | G18: =G10+G11+G12 | H18: =H10+H11+H12 | I18: =I10+I11+I12 | ... M18: =M10+M11+M12
A19: Share of depreciable assets already depreciated (asset age indicator) | B19: =IFERROR(-B14/B18,0) | C19: =IFERROR(-C14/C18,0) | D19: =IFERROR(-D14/D18,0) | E19: =IFERROR(-E14/E18,0) | F19: =IFERROR(-F14/F18,0) | G19: =IFERROR(-G14/G18,0) | H19: =IFERROR(-H14/H18,0) | I19: =IFERROR(-I14/I18,0) | ... M19: =IFERROR(-M14/M18,0)
A20: Depreciation expense (where disclosed) | J20: 3857782 | L20: 3690407 | M20: 3969230
A21: Change in net capital assets vs. prior year | B21: =0 | C21: =C15-B15 | D21: =D15-C15 | E21: =E15-D15 | F21: =F15-E15 | G21: =G15-F15 | H21: =H15-G15 | I21: =I15-H15 | J21: =J15-I15 | ... M21: =M15-L15
A23: Check: net vs. CW_Net_Position capital assets (should be 0) | B23: =B15-CW_Net_Position!B43 | C23: =C15-CW_Net_Position!C43 | D23: =D15-CW_Net_Position!D43 | E23: =E15-CW_Net_Position!E43 | F23: =F15-CW_Net_Position!F43 | G23: =G15-CW_Net_Position!G43 | H23: =H15-CW_Net_Position!H43 | I23: =I15-CW_Net_Position!I43 | ... M23: =M15-CW_Net_Position!M43

Sheet CW_LT_Liabilities
A1: City of El Cerrito - CITYWIDE (governmental activities)
A2: Long-term debt, pension and other long-term liabilities, June 30, $
A3: Debt by type from the MD&A long-term debt table; other balances link to CW_Net_Position. Pension liability is the CalPERS net pension liability (actuarial); OPEB = retiree health.
A6: June 30 | B6: 2014 | C6: 2015 | D6: 2016 | E6: 2017 | F6: 2018 | G6: 2019 | H6: 2020 | I6: 2021 | J6: 2022 | K6: 2023 | L6: 2024 | M6: 2025
A7: LONG-TERM DEBT
A8: Revenue bonds and notes (incl. certificates of participation) | B8: 21078700 | C8: 20255400 | D8: 19407200 | E8: 18604809 | F8: 17945973 | G8: 17083159 | H8: 16016021 | I8: 15172273 | J8: 14469055 | K8: 13745837 | L8: 12590248 | M8: 11779395
A9: Capital leases / financed purchases | B9: 2133692 | C9: 1925719 | D9: 1713138 | E9: 1495838 | F9: 1273712 | G9: 1046650 | H9: 1180596 | I9: 990291 | J9: 1938097 | K9: 1781148 | L9: 1474237 | M9: 1525364
A10: Leases and subscription liabilities (GASB 87/96) | B10: 0 | C10: 0 | D10: 0 | E10: 0 | F10: 0 | G10: 0 | H10: 0 | I10: 0 | J10: 114531 | K10: 0 | L10: 0 | M10: 624364
A11: Unamortized premiums / rounding (computed) | B11: =CW_Net_Position!B26-B8-B9-B10 | C11: =CW_Net_Position!C26-C8-C9-C10 | D11: =CW_Net_Position!D26-D8-D9-D10 | E11: =CW_Net_Position!E26-E8-E9-E10 | F11: =CW_Net_Position!F26-F8-F9-F10 | G11: =CW_Net_Position!G26-G8-G9-G10 | H11: =CW_Net_Position!H26-H8-H9-H10 | I11: =CW_Net_Position!I26-I8-I9-I10 | ... M11: =CW_Net_Position!M26-M8-M9-M10
A12: Total long-term debt (per Statement of Net Position) | B12: =SUM(B8:B11) | C12: =SUM(C8:C11) | D12: =SUM(D8:D11) | E12: =SUM(E8:E11) | F12: =SUM(F8:F11) | G12: =SUM(G8:G11) | H12: =SUM(H8:H11) | I12: =SUM(I8:I11) | ... M12: =SUM(M8:M11)
A14: OTHER LONG-TERM LIABILITIES
A15: Compensated absences (accrued vacation/leave) | B15: =CW_Net_Position!B24 | C15: =CW_Net_Position!C24 | D15: =CW_Net_Position!D24 | E15: =CW_Net_Position!E24 | F15: =CW_Net_Position!F24 | G15: =CW_Net_Position!G24 | H15: =CW_Net_Position!H24 | I15: =CW_Net_Position!I24 | ... M15: =CW_Net_Position!M24
A16: Claims payable | B16: =CW_Net_Position!B25 | C16: =CW_Net_Position!C25 | D16: =CW_Net_Position!D25 | E16: =CW_Net_Position!E25 | F16: =CW_Net_Position!F25 | G16: =CW_Net_Position!G25 | H16: =CW_Net_Position!H25 | I16: =CW_Net_Position!I25 | ... M16: =CW_Net_Position!M25
A17: Net OPEB liability (retiree health) | B17: =CW_Net_Position!B27 | C17: =CW_Net_Position!C27 | D17: =CW_Net_Position!D27 | E17: =CW_Net_Position!E27 | F17: =CW_Net_Position!F27 | G17: =CW_Net_Position!G27 | H17: =CW_Net_Position!H27 | I17: =CW_Net_Position!I27 | ... M17: =CW_Net_Position!M27
A18: Net pension liability (CalPERS) | B18: =CW_Net_Position!B28 | C18: =CW_Net_Position!C28 | D18: =CW_Net_Position!D28 | E18: =CW_Net_Position!E28 | F18: =CW_Net_Position!F28 | G18: =CW_Net_Position!G28 | H18: =CW_Net_Position!H28 | I18: =CW_Net_Position!I28 | ... M18: =CW_Net_Position!M28
A19: Total long-term obligations | B19: =B12+SUM(B15:B18) | C19: =C12+SUM(C15:C18) | D19: =D12+SUM(D15:D18) | E19: =E12+SUM(E15:E18) | F19: =F12+SUM(F15:F18) | G19: =G12+SUM(G15:G18) | H19: =H12+SUM(H15:H18) | I19: =I12+SUM(I15:I18) | ... M19: =M12+SUM(M15:M18)
A21: PENSION DETAIL
A22: Deferred outflows - pension/OPEB | B22: =CW_Net_Position!B17 | C22: =CW_Net_Position!C17 | D22: =CW_Net_Position!D17 | E22: =CW_Net_Position!E17 | F22: =CW_Net_Position!F17 | G22: =CW_Net_Position!G17 | H22: =CW_Net_Position!H17 | I22: =CW_Net_Position!I17 | ... M22: =CW_Net_Position!M17
A23: Deferred inflows - pension/OPEB | B23: =-CW_Net_Position!B32 | C23: =-CW_Net_Position!C32 | D23: =-CW_Net_Position!D32 | E23: =-CW_Net_Position!E32 | F23: =-CW_Net_Position!F32 | G23: =-CW_Net_Position!G32 | H23: =-CW_Net_Position!H32 | I23: =-CW_Net_Position!I32 | ... M23: =-CW_Net_Position!M32
A24: Net pension + OPEB position on the balance sheet (liability net of deferrals) | B24: =B18+B17-B22-B23 | C24: =C18+C17-C22-C23 | D24: =D18+D17-D22-D23 | E24: =E18+E17-E22-E23 | F24: =F18+F17-F22-F23 | G24: =G18+G17-G22-G23 | H24: =H18+H17-H22-H23 | I24: =I18+I17-I22-I23 | ... M24: =M18+M17-M22-M23
A26: SHORT-TERM BORROWING (memo - also in General Fund)
A27: Tax and revenue anticipation note (TRAN) outstanding at June 30 | B27: =CW_Net_Position!B23 | C27: =CW_Net_Position!C23 | D27: =CW_Net_Position!D23 | E27: =CW_Net_Position!E23 | F27: =CW_Net_Position!F23 | G27: =CW_Net_Position!G23 | H27: =CW_Net_Position!H23 | I27: =CW_Net_Position!I23 | ... M27: =CW_Net_Position!M23
A29: RATIOS
A30: Pension liability as multiple of General Fund revenues | B30: =IFERROR(B18/GF_Operating_Statement!B17,0) | C30: =IFERROR(C18/GF_Operating_Statement!C17,0) | D30: =IFERROR(D18/GF_Operating_Statement!D17,0) | E30: =IFERROR(E18/GF_Operating_Statement!E17,0) | F30: =IFERROR(F18/GF_Operating_Statement!F17,0) | G30: =IFERROR(G18/GF_Operating_Statement!G17,0) | H30: =IFERROR(H18/GF_Operating_Statement!H17,0) | I30: =IFERROR(I18/GF_Operating_Statement!I17,0) | ... M30: =IFERROR(M18/GF_Operating_Statement!M17,0)
A31: Long-term debt as % of General Fund revenues | B31: =IFERROR(B12/GF_Operating_Statement!B17,0) | C31: =IFERROR(C12/GF_Operating_Statement!C17,0) | D31: =IFERROR(D12/GF_Operating_Statement!D17,0) | E31: =IFERROR(E12/GF_Operating_Statement!E17,0) | F31: =IFERROR(F12/GF_Operating_Statement!F17,0) | G31: =IFERROR(G12/GF_Operating_Statement!G17,0) | H31: =IFERROR(H12/GF_Operating_Statement!H17,0) | I31: =IFERROR(I12/GF_Operating_Statement!I17,0) | ... M31: =IFERROR(M12/GF_Operating_Statement!M17,0)
A33: Check: total LT debt vs. CW_Net_Position (should be 0) | B33: =B12-CW_Net_Position!B26 | C33: =C12-CW_Net_Position!C26 | D33: =D12-CW_Net_Position!D26 | E33: =E12-CW_Net_Position!E26 | F33: =F12-CW_Net_Position!F26 | G33: =G12-CW_Net_Position!G26 | H33: =H12-CW_Net_Position!H26 | I33: =I12-CW_Net_Position!I26 | ... M33: =M12-CW_Net_Position!M26

Sheet CW_Pension_OPEB
A1: City of El Cerrito - CITYWIDE: PENSION AND OPEB SCHEDULES (GASB 68 / 75 RSI)
A2: CalPERS cost-sharing plans (Miscellaneous and Safety), $
A3: Fiscal year = City reporting year; the liability is measured one year earlier (e.g. FY2025 uses the June 30, 2024 measurement). Source: FY2025 ACFR RSI pp.103-104; funded ratios and FY2015 from FY2021 ACFR RSI p.109.
A6: Fiscal year ended June 30 | B6: 2014 | C6: 2015 | D6: 2016 | E6: 2017 | F6: 2018 | G6: 2019 | H6: 2020 | I6: 2021 | J6: 2022 | K6: 2023 | L6: 2024 | M6: 2025
A7: SCHEDULE OF PROPORTIONATE SHARE OF THE NET PENSION LIABILITY
A8: Miscellaneous plan
A9: Proportion of the collective net pension liability | D9: 0.002136 | E9: 0.003426 | F9: 0.003385 | G9: 0.003338 | H9: 0.003324 | I9: 0.003346 | J9: 0.003333 | K9: 0.003253 | L9: 0.003196 | M9: 0.003137
A10: Proportionate share of the net pension liability | D10: 14658502 | E10: 17070890 | F10: 19118301 | G10: 18768312 | H10: 19855450 | I10: 20881385 | J10: 14569087 | K10: 23378038 | L10: 24459499 | M10: 24151381
A11: Covered payroll | D11: 5561436 | E11: 5610928 | F11: 6212072 | G11: 6651088 | H11: 6927987 | I11: 7523515 | J11: 6607688 | K11: 6505147 | L11: 7095314 | M11: 8034133
A12: NPL as % of covered payroll | D12: =IFERROR(D10/D11,0) | E12: =IFERROR(E10/E11,0) | F12: =IFERROR(F10/F11,0) | G12: =IFERROR(G10/G11,0) | H12: =IFERROR(H10/H11,0) | I12: =IFERROR(I10/I11,0) | J12: =IFERROR(J10/J11,0) | K12: =IFERROR(K10/K11,0) | ... M12: =IFERROR(M10/M11,0)
A13: Safety plan (police, fire)
A14: Proportion of the collective net pension liability | D14: 0.004565 | E14: 0.006242 | F14: 0.006181 | G14: 0.006181 | H14: 0.006116 | I14: 0.006118 | J14: 0.006012 | K14: 0.006033 | L14: 0.005948 | M14: 0.005905
A15: Proportionate share of the net pension liability | D15: 31333605 | E15: 37772767 | F15: 42656830 | G15: 43088187 | H15: 45977250 | I15: 49493039 | J15: 34381303 | K15: 56148886 | L15: 59781530 | M15: 58981551
A16: Covered payroll | D16: 8802299 | E16: 9063604 | F16: 9597134 | G16: 10327301 | H16: 10308155 | I16: 10389710 | J16: 10283491 | K16: 9659674 | L16: 5930384 | M16: 7075249
A17: NPL as % of covered payroll | D17: =IFERROR(D15/D16,0) | E17: =IFERROR(E15/E16,0) | F17: =IFERROR(F15/F16,0) | G17: =IFERROR(G15/G16,0) | H17: =IFERROR(H15/H16,0) | I17: =IFERROR(I15/I16,0) | J17: =IFERROR(J15/J16,0) | K17: =IFERROR(K15/K16,0) | ... M17: =IFERROR(M15/M16,0)
A18: Total, both plans
A19: Net pension liability | C19: 39314773 | D19: =D10+D15 | E19: =E10+E15 | F19: =F10+F15 | G19: =G10+G15 | H19: =H10+H15 | I19: =I10+I15 | J19: =J10+J15 | K19: =K10+K15 | ... M19: =M10+M15
A20: Covered payroll | C20: 13945374 | D20: =D11+D16 | E20: =E11+E16 | F20: =F11+F16 | G20: =G11+G16 | H20: =H11+H16 | I20: =I11+I16 | J20: =J11+J16 | K20: =K11+K16 | ... M20: =M11+M16
A21: NPL as % of covered payroll | C21: =IFERROR(C19/C20,0) | D21: =IFERROR(D19/D20,0) | E21: =IFERROR(E19/E20,0) | F21: =IFERROR(F19/F20,0) | G21: =IFERROR(G19/G20,0) | H21: =IFERROR(H19/H20,0) | I21: =IFERROR(I19/I20,0) | J21: =IFERROR(J19/J20,0) | ... M21: =IFERROR(M19/M20,0)
A22: Plan fiduciary net position as % of total pension liability (funded ratio) | C22: 0.7982 | D22: 0.784 | E22: 0.7406 | F22: 0.7331 | G22: 0.7526 | H22: 0.7526 | I22: 0.751
A23: CalPERS discount rate | C23: 0.075 | D23: 0.0765 | E23: 0.0765 | F23: 0.0715 | G23: 0.0715 | H23: 0.0715 | I23: 0.0715 | J23: 0.0715 | K23: 0.069 | L23: 0.069 | M23: 0.069
A25: SCHEDULE OF CONTRIBUTIONS
A26: Miscellaneous plan
A27: Actuarially determined (contractually required) contribution | D27: 1444945 | E27: 1615318 | F27: 1780664 | G27: 1973155 | H27: 2264141 | I27: 2343260 | J27: 2510701 | K27: 2734433 | L27: 2834556 | M27: 3116130
A28: Contributions made | D28: 1444945 | E28: 1615318 | F28: 1780664 | G28: 1973692 | H28: 2264141 | I28: 2343260 | J28: 2510701 | K28: 2734433 | L28: 2834556 | M28: 3116130
A29: Contribution deficiency (excess) | D29: =D27-D28 | E29: =E27-E28 | F29: =F27-F28 | G29: =G27-G28 | H29: =H27-H28 | I29: =I27-I28 | J29: =J27-J28 | K29: =K27-K28 | ... M29: =M27-M28
A30: Covered payroll | D30: 5610928 | E30: 6212072 | F30: 6651088 | G30: 6927987 | H30: 7523515 | I30: 6607688 | J30: 6505147 | K30: 7095314 | L30: 8034133 | M30: 8735374
A31: Contributions as % of covered payroll | D31: =IFERROR(D28/D30,0) | E31: =IFERROR(E28/E30,0) | F31: =IFERROR(F28/F30,0) | G31: =IFERROR(G28/G30,0) | H31: =IFERROR(H28/H30,0) | I31: =IFERROR(I28/I30,0) | J31: =IFERROR(J28/J30,0) | K31: =IFERROR(K28/K30,0) | ... M31: =IFERROR(M28/M30,0)
A32: Safety plan (police, fire)
A33: Actuarially determined (contractually required) contribution | D33: 3142334 | E33: 3497289 | F33: 3927298 | G33: 4378562 | H33: 4930336 | I33: 5370170 | J33: 5737722 | K33: 6124456 | L33: 6510917 | M33: 7148153
A34: Contributions made | D34: 3142334 | E34: 3497289 | F34: 3927298 | G34: 4379650 | H34: 4930336 | I34: 5370170 | J34: 5737722 | K34: 6124456 | L34: 6510917 | M34: 7148153
A35: Contribution deficiency (excess) | D35: =D33-D34 | E35: =E33-E34 | F35: =F33-F34 | G35: =G33-G34 | H35: =H33-H34 | I35: =I33-I34 | J35: =J33-J34 | K35: =K33-K34 | ... M35: =M33-M34
A36: Covered payroll | D36: 9063604 | E36: 9597134 | F36: 10327301 | G36: 10308155 | H36: 10389710 | I36: 10283491 | J36: 9659674 | K36: 5930384 | L36: 7075249 | M36: 7607925
A37: Contributions as % of covered payroll | D37: =IFERROR(D34/D36,0) | E37: =IFERROR(E34/E36,0) | F37: =IFERROR(F34/F36,0) | G37: =IFERROR(G34/G36,0) | H37: =IFERROR(H34/H36,0) | I37: =IFERROR(I34/I36,0) | J37: =IFERROR(J34/J36,0) | K37: =IFERROR(K34/K36,0) | ... M37: =IFERROR(M34/M36,0)
A38: Total, both plans
A39: Total pension contributions | C39: 601837 | D39: =D28+D34 | E39: =E28+E34 | F39: =F28+F34 | G39: =G28+G34 | H39: =H28+H34 | I39: =I28+I34 | J39: =J28+J34 | K39: =K28+K34 | ... M39: =M28+M34
A40: Pension contributions as % of General Fund expenditures | D40: =IFERROR(D39/GF_Operating_Statement!D34,0) | E40: =IFERROR(E39/GF_Operating_Statement!E34,0) | F40: =IFERROR(F39/GF_Operating_Statement!F34,0) | G40: =IFERROR(G39/GF_Operating_Statement!G34,0) | H40: =IFERROR(H39/GF_Operating_Statement!H34,0) | I40: =IFERROR(I39/GF_Operating_Statement!I34,0) | J40: =IFERROR(J39/GF_Operating_Statement!J34,0) | K40: =IFERROR(K39/GF_Operating_Statement!K34,0) | ... M40: =IFERROR(M39/GF_Operating_Statement!M34,0)
A42: DISCOUNT-RATE SENSITIVITY OF NET PENSION LIABILITY (both plans)
A43: NPL at discount rate - 1% | L43: 118325156 | M43: 118325156
A44: NPL at current discount rate | L44: 84241029 | M44: 83132932
A45: NPL at discount rate + 1% | L45: 56320729 | M45: 54132240
A47: OTHER POSTEMPLOYMENT BENEFITS (RETIREE HEALTH)
A48: OPEB liability, governmental activities | B48: 1573570 | C48: 1867190 | D48: 2160810 | E48: 2454430 | F48: 2845887 | G48: 2994539 | H48: 3906161 | I48: 4887434 | J48: 0 | K48: 0 | L48: 0 | M48: 0
A49: Measurement basis | B49: Net OPEB obligation (GASB 45) | C49: Net OPEB obligation (GASB 45) | D49: Net OPEB obligation (GASB 45) | E49: Net OPEB obligation (GASB 45) | F49: Net/total OPEB liability (GASB 75) | G49: Net/total OPEB liability (GASB 75) | H49: Net/total OPEB liability (GASB 75) | I49: Net/total OPEB liability (GASB 75) | J49: Net/total OPEB liability (GASB 75) | K49: Net/total OPEB liability (GASB 75) | L49: Net/total OPEB liability (GASB 75) | M49: Net/total OPEB liability (GASB 75)
A51: Check: plans + business-type share - CW_Net_Position NPL (should be 0) | C51: =C19-CW_Net_Position!C28-0 | D51: =D19-CW_Net_Position!D28-0 | E51: =E19-CW_Net_Position!E28-0 | F51: =F19-CW_Net_Position!F28-0 | G51: =G19-CW_Net_Position!G28-0 | H51: =H19-CW_Net_Position!H28-0 | I51: =I19-CW_Net_Position!I28-0 | J51: =J19-CW_Net_Position!J28-0 | K51: =K19-CW_Net_Position!K28-0 | L51: =L19-CW_Net_Position!L28-3500990 | M51: =M19-CW_Net_Position!M28-3456898
A52: Check: OPEB vs. CW_Net_Position (should be 0) | B52: =B48-CW_Net_Position!B27 | C52: =C48-CW_Net_Position!C27 | D52: =D48-CW_Net_Position!D27 | E52: =E48-CW_Net_Position!E27 | F52: =F48-CW_Net_Position!F27 | G52: =G48-CW_Net_Position!G27 | H52: =H48-CW_Net_Position!H27 | I52: =I48-CW_Net_Position!I27 | ... M52: =M48-CW_Net_Position!M27
A54: Notes:
A55: - Safety covered payroll falls from $9.7M to $5.9M in FY2023 in the proportionate-share schedule (and FY2023 contributions schedule), pushing NPL to 1,008% of payroll in FY2024. The ACFR does not explain the drop; it may be a reporting change rather than real staffing.
A56: - FY2025 ACFR's 1%-decrease sensitivity ($118,325,156) is identical to FY2024's, while the current-rate NPL changed - likely carried forward without update. Treat the FY2025 sensitivity figure with caution.
A57: - Plan funded ratios are published in the ACFRs only through FY2021; later ACFRs omit that row.
A58: - FY2015 contribution ($601,837) as printed in the FY2021 ACFR combined schedule; it appears to cover only part of the year (first year of GASB 68).
A59: - On January 2, 2021 the City changed its retiree health (OPEB) benefit terms, removing the implied subsidy; the total OPEB liability became zero and FY2022 beginning net position rose by $3,699,945 (FY2022 ACFR MD&A). ACFRs from FY2023 contain no OPEB disclosures.
A62: CALPERS FUNDING VALUATIONS (funding-policy basis; column = valuation date June 30 of that year)
A63: Miscellaneous plans (rate plans 415, 26319)
A64: Entry-age accrued liability | C64: 47584675 | D64: 50006604 | E64: 53214914 | F64: 58039089 | G64: 61540435 | H64: 64792497 | I64: 67649162 | J64: 70387233 | K64: 73254350 | L64: 76712431 | M64: 80669881
A65: Market value of assets (share of pool) | C65: 32430404 | D65: 31893982 | E65: 35143078 | F65: 37927912 | G65: 40759951 | H65: 42747736 | I65: 50718943 | J65: 45805151 | K65: 47462478 | L65: 51459328 | M65: 57756943
A66: Unfunded accrued liability (UAL) | C66: =C64-C65 | D66: =D64-D65 | E66: =E64-E65 | F66: =F64-F65 | G66: =G64-G65 | H66: =H64-H65 | I66: =I64-I65 | J66: =J64-J65 | ... M66: =M64-M65
A67: Funded ratio | C67: =IFERROR(C65/C64,0) | D67: =IFERROR(D65/D64,0) | E67: =IFERROR(E65/E64,0) | F67: =IFERROR(F65/F64,0) | G67: =IFERROR(G65/G64,0) | H67: =IFERROR(H65/H64,0) | I67: =IFERROR(I65/I64,0) | J67: =IFERROR(J65/J64,0) | ... M67: =IFERROR(M65/M64,0)
A68: Covered payroll | C68: 5350668 | D68: 6073604 | E68: 6154788 | F68: 6465633 | G68: 7128108 | H68: 7333979 | I68: 6060345 | J68: 6421463 | K68: 6930328 | L68: 8335033 | M68: 8732884
A69: UAL as % of covered payroll | C69: =IFERROR(C66/C68,0) | D69: =IFERROR(D66/D68,0) | E69: =IFERROR(E66/E68,0) | F69: =IFERROR(F66/F68,0) | G69: =IFERROR(G66/G68,0) | H69: =IFERROR(H66/H68,0) | I69: =IFERROR(I66/I68,0) | J69: =IFERROR(J66/J68,0) | ... M69: =IFERROR(M66/M68,0)
A70: Safety plans (416 classic; 25344 PEPRA fire; 25345 PEPRA police)
A71: Entry-age accrued liability | C71: 115281867 | D71: 121759451 | E71: 129593080 | F71: 140252866 | G71: 148440995 | H71: 154485736 | I71: 165284322 | J71: 172878254 | K71: 180245592 | L71: 187813555 | M71: 195989059
A72: Market value of assets (share of pool) | C72: 81966243 | D72: 80859059 | E72: 87951732 | F72: 93269696 | G72: 99367418 | H72: 102027867 | I72: 124422322 | J72: 112503502 | K72: 116790571 | L72: 125542529 | M72: 138550994
A73: Unfunded accrued liability (UAL) | C73: =C71-C72 | D73: =D71-D72 | E73: =E71-E72 | F73: =F71-F72 | G73: =G71-G72 | H73: =H71-H72 | I73: =I71-I72 | J73: =J71-J72 | ... M73: =M71-M72
A74: Funded ratio | C74: =IFERROR(C72/C71,0) | D74: =IFERROR(D72/D71,0) | E74: =IFERROR(E72/E71,0) | F74: =IFERROR(F72/F71,0) | G74: =IFERROR(G72/G71,0) | H74: =IFERROR(H72/H71,0) | I74: =IFERROR(I72/I71,0) | J74: =IFERROR(J72/J71,0) | ... M74: =IFERROR(M72/M71,0)
A75: Covered payroll | C75: 8490596 | D75: 8677176 | E75: 9326280 | F75: 9795926 | G75: 9917930 | H75: 10137708 | I75: 9849766 | J75: 9065361 | K75: 9898147 | L75: 10822310 | M75: 11514409
A76: UAL as % of covered payroll | C76: =IFERROR(C73/C75,0) | D76: =IFERROR(D73/D75,0) | E76: =IFERROR(E73/E75,0) | F76: =IFERROR(F73/F75,0) | G76: =IFERROR(G73/G75,0) | H76: =IFERROR(H73/H75,0) | I76: =IFERROR(I73/I75,0) | J76: =IFERROR(J73/J75,0) | ... M76: =IFERROR(M73/M75,0)
A77: Both plans
A78: Total UAL | C78: =C66+C73 | D78: =D66+D73 | E78: =E66+E73 | F78: =F66+F73 | G78: =G66+G73 | H78: =H66+H73 | I78: =I66+I73 | J78: =J66+J73 | ... M78: =M66+M73
A79: Combined funded ratio | C79: =IFERROR((C65+C72)/(C64+C71),0) | D79: =IFERROR((D65+D72)/(D64+D71),0) | E79: =IFERROR((E65+E72)/(E64+E71),0) | F79: =IFERROR((F65+F72)/(F64+F71),0) | G79: =IFERROR((G65+G72)/(G64+G71),0) | H79: =IFERROR((H65+H72)/(H64+H71),0) | I79: =IFERROR((I65+I72)/(I64+I71),0) | J79: =IFERROR((J65+J72)/(J64+J71),0) | ... M79: =IFERROR((M65+M72)/(M64+M71),0)
A80: GASB 68 NPL at the same measurement date (next year's ACFR) | C80: =D19 | D80: =E19 | E80: =F19 | F80: =G19 | G80: =H19 | H80: =I19 | I80: =J19 | J80: =K19 | ... L80: =M19
A82: Required and projected employer contributions (CalPERS)
A83: Fiscal year | B83: Misc. classic normal cost | C83: Misc. PEPRA normal cost | D83: Misc. UAL payment | E83: Safety classic normal cost | F83: Safety PEPRA normal cost | G83: Safety UAL payment | H83: Total UAL payments | I83: Basis
A84: 2025-26 | B84: 0.1609 | C84: 0.0796 | D84: 2454148 | E84: 0.2738 | F84: 0.1399 | G84: 5569430 | H84: =D84+G84 | I84: Required (6/30/2023 valuation, shown in 2024 report)
A85: 2026-27 | B85: 0.1607 | C85: 0.0793 | D85: 2670097 | E85: 0.2742 | F85: 0.1391 | G85: 6061671 | H85: =D85+G85 | I85: Required (6/30/2024 valuation)
A86: 2027-28 | B86: 0.1653 | C86: 0.0805 | D86: 2797654 | E86: 0.2842 | F86: 0.1437 | G86: 6407378 | H86: =D86+G86 | I86: Required (6/30/2025 valuation)
A87: 2028-29 | B87: 0.165 | C87: 0.081 | D87: 2943000 | E87: 0.284 | F87: 0.144 | G87: 6733000 | H87: =D87+G87 | I87: Projected (6/30/2025 valuation)
A88: 2029-30 | B88: 0.165 | C88: 0.081 | D88: 2914000 | E88: 0.284 | F88: 0.144 | G88: 6649000 | H88: =D88+G88 | I88: Projected (6/30/2025 valuation)
A89: 2030-31 | B89: 0.165 | C89: 0.081 | D89: 2880000 | E89: 0.284 | F89: 0.144 | G89: 6550000 | H89: =D89+G89 | I89: Projected (6/30/2025 valuation)
A90: 2031-32 | B90: 0.165 | C90: 0.081 | D90: 2338000 | E90: 0.284 | F90: 0.144 | G90: 6532000 | H90: =D90+G90 | I90: Projected (6/30/2025 valuation)
A91: 2032-33 | B91: 0.165 | C91: 0.081 | D91: 2321000 | E91: 0.284 | F91: 0.144 | G91: 6503000 | H91: =D91+G91 | I91: Projected (6/30/2025 valuation)
A93: Risk measures, June 30, 2025 valuation
A94: Measure | B94: Misc. liability | C94: Misc. unfunded | D94: Misc. funded ratio | E94: Safety liability | F94: Safety unfunded | G94: Safety funded ratio
A95: Discount rate 5.8% (1% lower) | B95: 91141564 | C95: 33384621 | D95: 0.634 | E95: 221795341 | F95: 83244347 | G95: 0.625
A96: Discount rate 6.8% (current) | B96: 80669881 | C96: 22912938 | D96: 0.716 | E96: 195989059 | F96: 57438065 | G96: 0.707
A97: Discount rate 7.8% (1% higher) | B97: 72032414 | C97: 14275471 | D97: 0.802 | E97: 174768985 | F97: 36217991 | G97: 0.793
A98: Termination basis, 3.79% discount | B98: 113977162 | C98: 56220219 | D98: 0.507 | E98: 292088491 | F98: 153537497 | G98: 0.474
A99: Termination basis, 5.79% discount | B99: 86972293 | C99: 29215350 | D99: 0.664 | E99: 221220312 | F99: 82669318 | G99: 0.626
A100: Low-default-risk obligation (LDROM), 5.58% | B100: 93740638 | C100: 35983695 | E100: 228214165 | F100: 89663171
A102: - Funding-basis figures differ from the GASB 68 net pension liability in the ACFR: different asset measure timing, and the City's proportionate share of the pool under GASB vs. the plan's own accrued liability here. Both measure the same underlying obligation.
A103: - A June 30 valuation sets contributions two years later (e.g. the 6/30/2025 valuation sets FY2027-28 rates).
A104: - Projected UAL payments assume CalPERS earns 6.8% each year; actual returns above or below that change future payments.
A105: - Termination liability = what CalPERS would need if the City left the system (lower discount rate, no future contributions).
A106: - Sources: ../calpers/misc_2024.pdf, safety_fire_2024.pdf, misc_2025.pdf, safety_fire_2025.pdf (CalPERS annual valuation reports).
A107: Check: misc funded ratio vs. CalPERS printed, rounded to 0.1% (should be 0) | C107: =ROUND(C67,3)-0.682 | D107: =ROUND(D67,3)-0.638 | E107: =ROUND(E67,3)-0.66 | F107: =ROUND(F67,3)-0.653 | G107: =ROUND(G67,3)-0.662 | H107: =ROUND(H67,3)-0.66 | I107: =ROUND(I67,3)-0.75 | J107: =ROUND(J67,3)-0.651 | K107: =ROUND(K67,3)-0.648 | L107: =ROUND(L67,3)-0.671 | M107: =ROUND(M67,3)-0.716
A108: Check: safe funded ratio vs. CalPERS printed, rounded to 0.1% (should be 0) | C108: =ROUND(C74,3)-0.711 | D108: =ROUND(D74,3)-0.664 | E108: =ROUND(E74,3)-0.679 | F108: =ROUND(F74,3)-0.665 | G108: =ROUND(G74,3)-0.669 | H108: =ROUND(H74,3)-0.66 | I108: =ROUND(I74,3)-0.753 | J108: =ROUND(J74,3)-0.651 | K108: =ROUND(K74,3)-0.648 | L108: =ROUND(L74,3)-0.668 | M108: =ROUND(M74,3)-0.707

Sheet Stat_Trends
A1: City of El Cerrito - STATISTICAL SCHEDULES (GASB 44 format)
A2: Financial trends, debt capacity and demographic schedules, last twelve fiscal years, $
A3: Modeled on the ACFR Statistical Section (Tables 1, 3, 4, 10 and 13; template pages in ../templates/). GASB 44 calls for ten years; twelve are shown. Cross-checks against the City's own FY2025 statistical tables are at the bottom.
A6: Fiscal year ended June 30 | B6: 2014 | C6: 2015 | D6: 2016 | E6: 2017 | F6: 2018 | G6: 2019 | H6: 2020 | I6: 2021 | J6: 2022 | K6: 2023 | L6: 2024 | M6: 2025
A7: SCHEDULE 1 - NET POSITION BY COMPONENT, GOVERNMENTAL ACTIVITIES (cf. ACFR Table 1)
A8: Net investment in capital assets | B8: =CW_Net_Position!B38 | C8: =CW_Net_Position!C38 | D8: =CW_Net_Position!D38 | E8: =CW_Net_Position!E38 | F8: =CW_Net_Position!F38 | G8: =CW_Net_Position!G38 | H8: =CW_Net_Position!H38 | I8: =CW_Net_Position!I38 | ... M8: =CW_Net_Position!M38
A9: Restricted | B9: =CW_Net_Position!B39 | C9: =CW_Net_Position!C39 | D9: =CW_Net_Position!D39 | E9: =CW_Net_Position!E39 | F9: =CW_Net_Position!F39 | G9: =CW_Net_Position!G39 | H9: =CW_Net_Position!H39 | I9: =CW_Net_Position!I39 | ... M9: =CW_Net_Position!M39
A10: Unrestricted | B10: =CW_Net_Position!B40 | C10: =CW_Net_Position!C40 | D10: =CW_Net_Position!D40 | E10: =CW_Net_Position!E40 | F10: =CW_Net_Position!F40 | G10: =CW_Net_Position!G40 | H10: =CW_Net_Position!H40 | I10: =CW_Net_Position!I40 | ... M10: =CW_Net_Position!M40
A11: Total net position | B11: =CW_Net_Position!B37 | C11: =CW_Net_Position!C37 | D11: =CW_Net_Position!D37 | E11: =CW_Net_Position!E37 | F11: =CW_Net_Position!F37 | G11: =CW_Net_Position!G37 | H11: =CW_Net_Position!H37 | I11: =CW_Net_Position!I37 | ... M11: =CW_Net_Position!M37
A13: SCHEDULE 2 - FUND BALANCES OF THE GENERAL FUND, GASB 54 CLASSES (cf. ACFR Table 3)
A14: Nonspendable | B14: =GF_Balance_Sheet!B34 | C14: =GF_Balance_Sheet!C34 | D14: =GF_Balance_Sheet!D34 | E14: =GF_Balance_Sheet!E34 | F14: =GF_Balance_Sheet!F34 | G14: =GF_Balance_Sheet!G34 | H14: =GF_Balance_Sheet!H34 | I14: =GF_Balance_Sheet!I34 | ... M14: =GF_Balance_Sheet!M34
A15: Restricted | B15: =GF_Balance_Sheet!B35 | C15: =GF_Balance_Sheet!C35 | D15: =GF_Balance_Sheet!D35 | E15: =GF_Balance_Sheet!E35 | F15: =GF_Balance_Sheet!F35 | G15: =GF_Balance_Sheet!G35 | H15: =GF_Balance_Sheet!H35 | I15: =GF_Balance_Sheet!I35 | ... M15: =GF_Balance_Sheet!M35
A16: Committed | B16: =GF_Balance_Sheet!B36 | C16: =GF_Balance_Sheet!C36 | D16: =GF_Balance_Sheet!D36 | E16: =GF_Balance_Sheet!E36 | F16: =GF_Balance_Sheet!F36 | G16: =GF_Balance_Sheet!G36 | H16: =GF_Balance_Sheet!H36 | I16: =GF_Balance_Sheet!I36 | ... M16: =GF_Balance_Sheet!M36
A17: Assigned | B17: =GF_Balance_Sheet!B37 | C17: =GF_Balance_Sheet!C37 | D17: =GF_Balance_Sheet!D37 | E17: =GF_Balance_Sheet!E37 | F17: =GF_Balance_Sheet!F37 | G17: =GF_Balance_Sheet!G37 | H17: =GF_Balance_Sheet!H37 | I17: =GF_Balance_Sheet!I37 | ... M17: =GF_Balance_Sheet!M37
A18: Unassigned (incl. Emergency Disaster Relief reserve) | B18: =GF_Balance_Sheet!B45 | C18: =GF_Balance_Sheet!C45 | D18: =GF_Balance_Sheet!D45 | E18: =GF_Balance_Sheet!E45 | F18: =GF_Balance_Sheet!F45 | G18: =GF_Balance_Sheet!G45 | H18: =GF_Balance_Sheet!H45 | I18: =GF_Balance_Sheet!I45 | ... M18: =GF_Balance_Sheet!M45
A19: Total General Fund | B19: =GF_Balance_Sheet!B40 | C19: =GF_Balance_Sheet!C40 | D19: =GF_Balance_Sheet!D40 | E19: =GF_Balance_Sheet!E40 | F19: =GF_Balance_Sheet!F40 | G19: =GF_Balance_Sheet!G40 | H19: =GF_Balance_Sheet!H40 | I19: =GF_Balance_Sheet!I40 | ... M19: =GF_Balance_Sheet!M40
A20: All other governmental funds (total) | B20: =GF_to_Citywide_Bridge!B9 | C20: =GF_to_Citywide_Bridge!C9 | D20: =GF_to_Citywide_Bridge!D9 | E20: =GF_to_Citywide_Bridge!E9 | F20: =GF_to_Citywide_Bridge!F9 | G20: =GF_to_Citywide_Bridge!G9 | H20: =GF_to_Citywide_Bridge!H9 | I20: =GF_to_Citywide_Bridge!I9 | ... M20: =GF_to_Citywide_Bridge!M9
A21: Total governmental funds | B21: =B19+B20 | C21: =C19+C20 | D21: =D19+D20 | E21: =E19+E20 | F21: =F19+F20 | G21: =G19+G20 | H21: =H19+H20 | I21: =I19+I20 | ... M21: =M19+M20
A23: SCHEDULE 3 - CHANGES IN FUND BALANCE OF THE GENERAL FUND (cf. ACFR Table 4, all governmental funds)
A24: Total revenues | B24: =GF_Operating_Statement!B17 | C24: =GF_Operating_Statement!C17 | D24: =GF_Operating_Statement!D17 | E24: =GF_Operating_Statement!E17 | F24: =GF_Operating_Statement!F17 | G24: =GF_Operating_Statement!G17 | H24: =GF_Operating_Statement!H17 | I24: =GF_Operating_Statement!I17 | ... M24: =GF_Operating_Statement!M17
A25: Total expenditures | B25: =GF_Operating_Statement!B34 | C25: =GF_Operating_Statement!C34 | D25: =GF_Operating_Statement!D34 | E25: =GF_Operating_Statement!E34 | F25: =GF_Operating_Statement!F34 | G25: =GF_Operating_Statement!G34 | H25: =GF_Operating_Statement!H34 | I25: =GF_Operating_Statement!I34 | ... M25: =GF_Operating_Statement!M34
A26: Excess (deficiency) of revenues over (under) expenditures | B26: =GF_Operating_Statement!B36 | C26: =GF_Operating_Statement!C36 | D26: =GF_Operating_Statement!D36 | E26: =GF_Operating_Statement!E36 | F26: =GF_Operating_Statement!F36 | G26: =GF_Operating_Statement!G36 | H26: =GF_Operating_Statement!H36 | I26: =GF_Operating_Statement!I36 | ... M26: =GF_Operating_Statement!M36
A27: Total other financing sources (uses) | B27: =GF_Operating_Statement!B43 | C27: =GF_Operating_Statement!C43 | D27: =GF_Operating_Statement!D43 | E27: =GF_Operating_Statement!E43 | F27: =GF_Operating_Statement!F43 | G27: =GF_Operating_Statement!G43 | H27: =GF_Operating_Statement!H43 | I27: =GF_Operating_Statement!I43 | ... M27: =GF_Operating_Statement!M43
A28: Special items | B28: =GF_Operating_Statement!B46 | C28: =GF_Operating_Statement!C46 | D28: =GF_Operating_Statement!D46 | E28: =GF_Operating_Statement!E46 | F28: =GF_Operating_Statement!F46 | G28: =GF_Operating_Statement!G46 | H28: =GF_Operating_Statement!H46 | I28: =GF_Operating_Statement!I46 | ... M28: =GF_Operating_Statement!M46
A29: Net change in fund balance | B29: =GF_Operating_Statement!B48 | C29: =GF_Operating_Statement!C48 | D29: =GF_Operating_Statement!D48 | E29: =GF_Operating_Statement!E48 | F29: =GF_Operating_Statement!F48 | G29: =GF_Operating_Statement!G48 | H29: =GF_Operating_Statement!H48 | I29: =GF_Operating_Statement!I48 | ... M29: =GF_Operating_Statement!M48
